Workbook

Sheet wallet_records
A1: account | B1: category | C1: currency | D1: amount | E1: ref_currency_amount | F1: type | G1: payment_type | H1: note | I1: date | J1: transfer | K1: payee | L1: labels | M1: día | N1: mes | O1: año
A2: Bancolombia | B2: Empleados | C2: COP | D2: 1051000 | E2: 1051000 | F2: Gasto | G2: Transferencia bancaria | H2: MLUJ | I2: 46071.5 | J2: FALSE | K2: Martha Lucia Uribe Jaramillo | L2: Martha Lucía Uribe Jaramillo | M2: 18 | N2: 2 | O2: 2026 | R2: =IF(wallet_records[[#This Row],[type]]="Gasto",wallet_records[[#This Row],[amount]]*(-1),wallet_records[[#This Row],[amount]]) -> -1051000
A3: Bancolombia | B3: Empleados | C3: COP | D3: 1051000 | E3: 1051000 | F3: Gasto | G3: Transferencia bancaria | H3: MLUJ | I3: 46057.5 | J3: FALSE | K3: Martha Lucia Uribe Jaramillo | L3: Martha Lucía Uribe Jaramillo | M3: 4 | N3: 2 | O3: 2026 | R3: =IF(wallet_records[[#This Row],[type]]="Gasto",wallet_records[[#This Row],[amount]]*(-1),wallet_records[[#This Row],[amount]]) -> -1051000
A4: Bancolombia | B4: Empleados | C4: COP | D4: 218900 | E4: 218900 | F4: Gasto | G4: Transferencia bancaria | H4: Seguridad Social | I4: 46054.5 | J4: FALSE | K4: Martha Lucia Uribe Jaramillo | L4: Martha Lucía Uribe Jaramillo | M4: 1 | N4: 2 | O4: 2026 | R4: =IF(wallet_records[[#This Row],[type]]="Gasto",wallet_records[[#This Row],[amount]]*(-1),wallet_records[[#This Row],[amount]]) -> -218900
A5: Bancolombia | B5: Empleados | C5: COP | D5: 575300 | E5: 575300 | F5: Gasto | G5: Transferencia bancaria | H5: Seguridad Social | I5: 46054.5 | J5: FALSE | K5: Eliecer Restrepo Restrepo | L5: Eliecer Restrepo Restrepo | M5: 1 | N5: 2 | O5: 2026 | R5: =IF(wallet_records[[#This Row],[type]]="Gasto",wallet_records[[#This Row],[amount]]*(-1),wallet_records[[#This Row],[amount]]) -> -575300
A6: Bancolombia | B6: Empleados | C6: COP | D6: 1051000 | E6: 1051000 | F6: Gasto | G6: Transferencia bancaria | H6: MLUJ | I6: 46042.5 | J6: FALSE | K6: Martha Lucia Uribe Jaramillo | L6: Martha Lucía Uribe Jaramillo | M6: 20 | N6: 1 | O6: 2026 | R6: =IF(wallet_records[[#This Row],[type]]="Gasto",wallet_records[[#This Row],[amount]]*(-1),wallet_records[[#This Row],[amount]]) -> -1051000
A7: Bancolombia | B7: Empleados | C7: COP | D7: 178000 | E7: 178000 | F7: Gasto | G7: Transferencia bancaria | H7: Seguridad Social | I7: 46027.501 | J7: FALSE | K7: Martha Lucia Uribe Jaramillo | L7: Martha Lucía Uribe Jaramillo | M7: 5 | N7: 1 | O7: 2026 | R7: =IF(wallet_records[[#This Row],[type]]="Gasto",wallet_records[[#This Row],[amount]]*(-1),wallet_records[[#This Row],[amount]]) -> -178000
A8: Efectivo | B8: Empleados | C8: COP | D8: 575300 | E8: 575300 | F8: Gasto | G8: Transferencia bancaria | H8: Seguridad Social | I8: 46027.5 | J8: FALSE | K8: Eliecer Restrepo Restrepo | L8: Eliecer Restrepo Restrepo | M8: 5 | N8: 1 | O8: 2026 | R8: =IF(wallet_records[[#This Row],[type]]="Gasto",wallet_records[[#This Row],[amount]]*(-1),wallet_records[[#This Row],[amount]]) -> -575300
A9: Bancolombia | B9: Empleados | C9: COP | D9: 1053000 | E9: 1053000 | F9: Gasto | G9: Transferencia bancaria | H9: MLUJ | I9: 46027.5 | J9: FALSE | K9: Martha Lucia Uribe Jaramillo | L9: Martha Lucía Uribe Jaramillo | M9: 5 | N9: 1 | O9: 2026 | R9: =IF(wallet_records[[#This Row],[type]]="Gasto",wallet_records[[#This Row],[amount]]*(-1),wallet_records[[#This Row],[amount]]) -> -1053000
A10: Bancolombia | B10: Impuestos - IVA, renta, otros | C10: COP | D10: 4431940 | E10: 4431940 | F10: Gasto | G10: Transferencia bancaria | H10: Impuesto Predial | I10: 46054.5 | J10: FALSE | K10: Municipio de Medellín | L10: Belén | M10: 1 | N10: 2 | O10: 2026 | R10: =IF(wallet_records[[#This Row],[type]]="Gasto",wallet_records[[#This Row],[amount]]*(-1),wallet_records[[#This Row],[amount]]) -> -4431940
A11: Bancolombia | B11: Impuestos - IVA, renta, otros | C11: COP | D11: 2461875 | E11: 2461875 | F11: Gasto | G11: Transferencia bancaria | H11: Impuesto Predial | I11: 46054.5 | J11: FALSE | K11: Municipio de Medellín | L11: Yari | M11: 1 | N11: 2 | O11: 2026 | R11: =IF(wallet_records[[#This Row],[type]]="Gasto",wallet_records[[#This Row],[amount]]*(-1),wallet_records[[#This Row],[amount]]) -> -2461875
A12: Bancolombia | B12: Impuestos - IVA, renta, otros | C12: COP | D12: 1320857 | E12: 1320857 | F12: Gasto | G12: Transferencia bancaria | H12: Impuesto Predial | I12: 46054.5 | J12: FALSE | K12: Municipio de Medellín | L12: Rivera del Valle | M12: 1 | N12: 2 | O12: 2026 | R12: =IF(wallet_records[[#This Row],[type]]="Gasto",wallet_records[[#This Row],[amount]]*(-1),wallet_records[[#This Row],[amount]]) -> -1320857
A13: Bancolombia | B13: Impuestos - IVA, renta, otros | C13: COP | D13: 1823377 | E13: 1823377 | F13: Gasto | G13: Transferencia bancaria | H13: Impuesto Predial | I13: 46054.5 | J13: FALSE | K13: Municipio de Medellín | L13: Ocarinas | M13: 1 | N13: 2 | O13: 2026 | R13: =IF(wallet_records[[#This Row],[type]]="Gasto",wallet_records[[#This Row],[amount]]*(-1),wallet_records[[#This Row],[amount]]) -> -1823377
A14: Bancolombia | B14: Impuestos - IVA, renta, otros | C14: COP | D14: 359256 | E14: 359256 | F14: Gasto | G14: Transferencia bancaria | H14: Impuesto Predial | I14: 46054.5 | J14: FALSE | K14: Municipio de Medellín | L14: Pedregal | M14: 1 | N14: 2 | O14: 2026 | R14: =IF(wallet_records[[#This Row],[type]]="Gasto",wallet_records[[#This Row],[amount]]*(-1),wallet_records[[#This Row],[amount]]) -> -359256
A15: Bancolombia | B15: Impuestos - IVA, renta, otros | C15: COP | D15: 227100 | E15: 227100 | F15: Gasto | G15: Transferencia bancaria | H15: Impuestos Mazda | I15: 46054.5 | J15: FALSE | L15: Mazda | M15: 1 | N15: 2 | O15: 2026 | R15: =IF(wallet_records[[#This Row],[type]]="Gasto",wallet_records[[#This Row],[amount]]*(-1),wallet_records[[#This Row],[amount]]) -> -227100
A16: Fidu Impuestos | B16: Impuestos - IVA, renta, otros | C16: COP | D16: 8610.12 | E16: 8610.12 | F16: Gasto | G16: Transferencia bancaria | H16: Retención en la Fuente | I16: 46052.397 | J16: FALSE | M16: 30 | N16: 1 | O16: 2026 | R16: =IF(wallet_records[[#This Row],[type]]="Gasto",wallet_records[[#This Row],[amount]]*(-1),wallet_records[[#This Row],[amount]]) -> -8610.12
A17: Bancolombia | B17: Impuestos - IVA, renta, otros | C17: COP | D17: 42900 | E17: 42900 | F17: Gasto | G17: Transferencia bancaria | H17: Semaforización Mazda | I17: 46042.5 | J17: FALSE | L17: Mazda | M17: 20 | N17: 1 | O17: 2026 | R17: =IF(wallet_records[[#This Row],[type]]="Gasto",wallet_records[[#This Row],[amount]]*(-1),wallet_records[[#This Row],[amount]]) -> -42900
A18: Bancolombia | B18: Intereses, cargos, seguros | C18: COP | D18: 2194118 | E18: 2194118 | F18: Gasto | G18: Transferencia bancaria | H18: Seguro taxi | I18: 46042.5 | J18: FALSE | L18: Taxi | M18: 20 | N18: 1 | O18: 2026 | R18: =IF(wallet_records[[#This Row],[type]]="Gasto",wallet_records[[#This Row],[amount]]*(-1),wallet_records[[#This Row],[amount]]) -> -2194118
A19: Bancolombia | B19: Intereses, cargos, seguros | C19: COP | D19: 677400 | E19: 677400 | F19: Gasto | G19: Transferencia bancaria | H19: SOAT Mazda | I19: 46027.464 | J19: FALSE | K19: Mazda | L19: Mazda | M19: 5 | N19: 1 | O19: 2026 | R19: =IF(wallet_records[[#This Row],[type]]="Gasto",wallet_records[[#This Row],[amount]]*(-1),wallet_records[[#This Row],[amount]]) -> -677400
A20: Fiducuenta ARU | B20: Intereses, ganancias de capital | C20: COP | D20: 83627.51 | E20: 83627.51 | F20: Ingreso | G20: Transferencia bancaria | H20: Rendimientos | I20: 46053.411 | J20: FALSE | M20: 31 | N20: 1 | O20: 2026 | R20: =IF(wallet_records[[#This Row],[type]]="Gasto",wallet_records[[#This Row],[amount]]*(-1),wallet_records[[#This Row],[amount]]) -> 83627.51
A21: Fidu Impuestos | B21: Intereses, ganancias de capital | C21: COP | D21: 122177.32 | E21: 122177.32 | F21: Ingreso | G21: Transferencia bancaria | H21: Rendimientos | I21: 46053.397 | J21: FALSE | M21: 31 | N21: 1 | O21: 2026 | R21: =IF(wallet_records[[#This Row],[type]]="Gasto",wallet_records[[#This Row],[amount]]*(-1),wallet_records[[#This Row],[amount]]) -> 122177.32
A22: Administración | B22: Intereses, ganancias de capital | C22: COP | D22: 37154.79 | E22: 37154.79 | F22: Ingreso | G22: Transferencia bancaria | H22: Rendimientos | I22: 46053.395 | J22: FALSE | M22: 31 | N22: 1 | O22: 2026 | R22: =IF(wallet_records[[#This Row],[type]]="Gasto",wallet_records[[#This Row],[amount]]*(-1),wallet_records[[#This Row],[amount]]) -> 37154.79
A23: Fidu Mantenimiento | B23: Intereses, ganancias de capital | C23: COP | D23: 26828.37 | E23: 26828.37 | F23: Ingreso | G23: Transferencia bancaria | H23: Rendimientos | I23: 46053.394 | J23: FALSE | M23: 31 | N23: 1 | O23: 2026 | R23: =IF(wallet_records[[#This Row],[type]]="Gasto",wallet_records[[#This Row],[amount]]*(-1),wallet_records[[#This Row],[amount]]) -> 26828.37
A24: Bancolombia | B24: Intereses, ganancias de capital | C24: COP | D24: 155217.34 | E24: 155217.34 | F24: Ingreso | G24: Transferencia bancaria | H24: Rendimientos | I24: 46024.364 | J24: FALSE | K24: Bancolombia | M24: 2 | N24: 1 | O24: 2026 | R24: =IF(wallet_records[[#This Row],[type]]="Gasto",wallet_records[[#This Row],[amount]]*(-1),wallet_records[[#This Row],[amount]]) -> 155217.34
A25: Bancolombia | B25: Intereses, ganancias de capital | C25: COP | D25: 32509.32 | E25: 32509.32 | F25: Ingreso | G25: Transferencia bancaria | H25: Rendimientos | I25: 46024.36 | J25: FALSE | K25: Bancolombia | M25: 2 | N25: 1 | O25: 2026 | R25: =IF(wallet_records[[#This Row],[type]]="Gasto",wallet_records[[#This Row],[amount]]*(-1),wallet_records[[#This Row],[amount]]) -> 32509.32
A26: Bancolombia | B26: Otros gastos administrativos | C26: COP | D26: 156000 | E26: 156000 | F26: Gasto | G26: Transferencia bancaria | H26: Pago de Administración | I26: 46068.5 | J26: FALSE | K26: Yari - Administrador | L26: Yari | M26: 15 | N26: 2 | O26: 2026 | R26: =IF(wallet_records[[#This Row],[type]]="Gasto",wallet_records[[#This Row],[amount]]*(-1),wallet_records[[#This Row],[amount]]) -> -156000
A27: Bancolombia | B27: Otros gastos administrativos | C27: COP | D27: 269400 | E27: 269400 | F27: Gasto | G27: Transferencia bancaria | H27: Pago de Administración | I27: 46068.5 | J27: FALSE | K27: Rivera del Valle - Administrador | L27: Rivera del Valle | M27: 15 | N27: 2 | O27: 2026 | R27: =IF(wallet_records[[#This Row],[type]]="Gasto",wallet_records[[#This Row],[amount]]*(-1),wallet_records[[#This Row],[amount]]) -> -269400
A28: Bancolombia | B28: Otros gastos administrativos | C28: COP | D28: 501542 | E28: 501542 | F28: Gasto | G28: Transferencia bancaria | H28: Pago de Administración | I28: 46068.5 | J28: FALSE | K28: Ocarinas - Administrador | L28: Ocarinas | M28: 15 | N28: 2 | O28: 2026 | R28: =IF(wallet_records[[#This Row],[type]]="Gasto",wallet_records[[#This Row],[amount]]*(-1),wallet_records[[#This Row],[amount]]) -> -501542
A29: Bancolombia | B29: Otros gastos administrativos | C29: COP | D29: 116800 | E29: 116800 | F29: Gasto | G29: Transferencia bancaria | H29: Campos de Paz | I29: 46041.5 | J29: FALSE | L29: Martha Lucía Uribe Jaramillo | M29: 19 | N29: 1 | O29: 2026 | R29: =IF(wallet_records[[#This Row],[type]]="Gasto",wallet_records[[#This Row],[amount]]*(-1),wallet_records[[#This Row],[amount]]) -> -116800
A30: Bancolombia | B30: Otros gastos administrativos | C30: COP | D30: 58000 | E30: 58000 | F30: Gasto | G30: Transferencia bancaria | H30: Fátima | I30: 46041.5 | J30: FALSE | L30: Martha Lucía Uribe Jaramillo | M30: 19 | N30: 1 | O30: 2026 | R30: =IF(wallet_records[[#This Row],[type]]="Gasto",wallet_records[[#This Row],[amount]]*(-1),wallet_records[[#This Row],[amount]]) -> -58000
A31: Bancolombia | B31: Otros gastos administrativos | C31: COP | D31: 501542 | E31: 501542 | F31: Gasto | G31: Transferencia bancaria | H31: Pago de Administración | I31: 46039.501 | J31: FALSE | K31: Ocarinas - Administrador | L31: Ocarinas | M31: 17 | N31: 1 | O31: 2026 | R31: =IF(wallet_records[[#This Row],[type]]="Gasto",wallet_records[[#This Row],[amount]]*(-1),wallet_records[[#This Row],[amount]]) -> -501542
A32: Bancolombia | B32: Otros gastos administrativos | C32: COP | D32: 156000 | E32: 156000 | F32: Gasto | G32: Efectivo | H32: Pago de Administración | I32: 46039.5 | J32: FALSE | K32: Yari - Administrador | L32: Yari | M32: 17 | N32: 1 | O32: 2026 | R32: =IF(wallet_records[[#This Row],[type]]="Gasto",wallet_records[[#This Row],[amount]]*(-1),wallet_records[[#This Row],[amount]]) -> -156000
A33: Bancolombia | B33: Otros gastos administrativos | C33: COP | D33: 269400 | E33: 269400 | F33: Gasto | G33: Transferencia bancaria | H33: Pago de Administración | I33: 46039.5 | J33: FALSE | K33: Rivera del Valle - Administrador | L33: Rivera del Valle | M33: 17 | N33: 1 | O33: 2026 | R33: =IF(wallet_records[[#This Row],[type]]="Gasto",wallet_records[[#This Row],[amount]]*(-1),wallet_records[[#This Row],[amount]]) -> -269400
A34: Bancolombia | B34: Otros gastos administrativos | C34: COP | D34: 2700 | E34: 2700 | F34: Gasto | G34: Efectivo | H34: Comisión retiro | I34: 46027.845 | J34: FALSE | M34: 5 | N34: 1 | O34: 2026 | R34: =IF(wallet_records[[#This Row],[type]]="Gasto",wallet_records[[#This Row],[amount]]*(-1),wallet_records[[#This Row],[amount]]) -> -2700
A35: Bancolombia | B35: Otros gastos administrativos | C35: COP | D35: 124600 | E35: 124600 | F35: Gasto | G35: Efectivo | H35: Fondos para gastos varios | I35: 46025.731 | J35: FALSE | M35: 3 | N35: 1 | O35: 2026 | R35: =IF(wallet_records[[#This Row],[type]]="Gasto",wallet_records[[#This Row],[amount]]*(-1),wallet_records[[#This Row],[amount]]) -> -124600
A36: Bancolombia | B36: Otros gastos administrativos | C36: COP | D36: 156860 | E36: 156860 | F36: Gasto | G36: Transferencia bancaria | H36: Fondos para gastos varios | I36: 46025.73 | J36: FALSE | M36: 3 | N36: 1 | O36: 2026 | R36: =IF(wallet_records[[#This Row],[type]]="Gasto",wallet_records[[#This Row],[amount]]*(-1),wallet_records[[#This Row],[amount]]) -> -156860
A37: Bancolombia | B37: Otros gastos administrativos | C37: COP | D37: 180000 | E37: 180000 | F37: Gasto | G37: Transferencia bancaria | H37: Fondos para gastos varios | I37: 46023.456 | J37: FALSE | L37: Martha Lucía Uribe Jaramillo | M37: 1 | N37: 1 | O37: 2026 | R37: =IF(wallet_records[[#This Row],[type]]="Gasto",wallet_records[[#This Row],[amount]]*(-1),wallet_records[[#This Row],[amount]]) -> -180000
A38: Bancolombia | B38: Reparaciones y mantenimiento | C38: COP | D38: 50000 | E38: 50000 | F38: Gasto | G38: Transferencia bancaria | H38: Mantenimiento | I38: 46067.4 | J38: FALSE | K38: Elmer Marin - Fontanero | L38: Yari | M38: 14 | N38: 2 | O38: 2026 | R38: =IF(wallet_records[[#This Row],[type]]="Gasto",wallet_records[[#This Row],[amount]]*(-1),wallet_records[[#This Row],[amount]]) -> -50000
A39: Bancolombia | B39: Reparaciones y mantenimiento | C39: COP | D39: 520000 | E39: 520000 | F39: Gasto | G39: Transferencia bancaria | H39: Mantenimiento | I39: 46064.372 | J39: FALSE | K39: Elmer Marin - Fontanero | L39: Yari | M39: 11 | N39: 2 | O39: 2026 | R39: =IF(wallet_records[[#This Row],[type]]="Gasto",wallet_records[[#This Row],[amount]]*(-1),wallet_records[[#This Row],[amount]]) -> -520000
A40: Bancolombia | B40: Reparaciones y mantenimiento | C40: COP | D40: 80500 | E40: 80500 | F40: Gasto | G40: Efectivo | H40: Mantenimiento | I40: 46063.371 | J40: FALSE | K40: Pisende | L40: Yari | M40: 10 | N40: 2 | O40: 2026 | R40: =IF(wallet_records[[#This Row],[type]]="Gasto",wallet_records[[#This Row],[amount]]*(-1),wallet_records[[#This Row],[amount]]) -> -80500
A41: Bancolombia | B41: Reparaciones y mantenimiento | C41: COP | D41: 15750 | E41: 15750 | F41: Gasto | G41: Efectivo | H41: Mantenimiento | I41: 46063.367 | J41: FALSE | K41: Medina y CIA SAS | L41: Yari | M41: 10 | N41: 2 | O41: 2026 | R41: =IF(wallet_records[[#This Row],[type]]="Gasto",wallet_records[[#This Row],[amount]]*(-1),wallet_records[[#This Row],[amount]]) -> -15750
A42: Bancolombia | B42: Reparaciones y mantenimiento | C42: COP | D42: 423900 | E42: 423900 | F42: Gasto | G42: Efectivo | H42: Mantenimiento Taxi | I42: 46042.77 | J42: FALSE | L42: Taxi | M42: 20 | N42: 1 | O42: 2026 | R42: =IF(wallet_records[[#This Row],[type]]="Gasto",wallet_records[[#This Row],[amount]]*(-1),wallet_records[[#This Row],[amount]]) -> -423900
A43: Efectivo | B43: Reparaciones y mantenimiento | C43: COP | D43: 5400 | E43: 5400 | F43: Gasto | G43: Efectivo | H43: Mantenimiento | I43: 46041.733 | J43: FALSE | K43: Martha Lucia Uribe Jaramillo | L43: Pedregal | M43: 19 | N43: 1 | O43: 2026 | R43: =IF(wallet_records[[#This Row],[type]]="Gasto",wallet_records[[#This Row],[amount]]*(-1),wallet_records[[#This Row],[amount]]) -> -5400
A44: Bancolombia | B44: Reparaciones y mantenimiento | C44: COP | D44: 364600 | E44: 364600 | F44: Gasto | G44: Transferencia bancaria | H44: CDA Mazda | I44: 46025.731 | J44: FALSE | L44: Mazda | M44: 3 | N44: 1 | O44: 2026 | R44: =IF(wallet_records[[#This Row],[type]]="Gasto",wallet_records[[#This Row],[amount]]*(-1),wallet_records[[#This Row],[amount]]) -> -364600
A45: Bancolombia | B45: Servicios | C45: COP | D45: 3146600 | E45: 3146600 | F45: Ingreso | G45: Transferencia bancaria | H45: Arriendo | I45: 46069.5 | J45: FALSE | K45: Alejandro Restrepo - Belén | L45: Belén | M45: 16 | N45: 2 | O45: 2026 | R45: =IF(wallet_records[[#This Row],[type]]="Gasto",wallet_records[[#This Row],[amount]]*(-1),wallet_records[[#This Row],[amount]]) -> 3146600
A46: Bancolombia | B46: Servicios | C46: COP | D46: 1750000 | E46: 1750000 | F46: Ingreso | G46: Transferencia bancaria | H46: Arriendo | I46: 46068.5 | J46: FALSE | K46: Elizabeth Restrepo - Yari | L46: Yari | M46: 15 | N46: 2 | O46: 2026 | R46: =IF(wallet_records[[#This Row],[type]]="Gasto",wallet_records[[#This Row],[amount]]*(-1),wallet_records[[#This Row],[amount]]) -> 1750000
A47: Bancolombia | B47: Servicios | C47: COP | D47: 1540000 | E47: 1540000 | F47: Ingreso | G47: Transferencia bancaria | H47: Arriendo | I47: 46066.5 | J47: FALSE | K47: Jorge Mario Naranjo Henao - Ocarinas | L47: Ocarinas | M47: 13 | N47: 2 | O47: 2026 | R47: =IF(wallet_records[[#This Row],[type]]="Gasto",wallet_records[[#This Row],[amount]]*(-1),wallet_records[[#This Row],[amount]]) -> 1540000
A48: Bancolombia | B48: Servicios | C48: COP | D48: 1715000 | E48: 1715000 | F48: Ingreso | G48: Transferencia bancaria | H48: Arriendo | I48: 46053.5 | J48: FALSE | K48: David Alejandro Restrepo - Rivera del Valle | L48: Rivera del Valle | M48: 31 | N48: 1 | O48: 2026 | R48: =IF(wallet_records[[#This Row],[type]]="Gasto",wallet_records[[#This Row],[amount]]*(-1),wallet_records[[#This Row],[amount]]) -> 1715000
A49: Bancolombia | B49: Servicios | C49: COP | D49: 500000 | E49: 500000 | F49: Ingreso | G49: Transferencia bancaria | H49: Arriendo | I49: 46051.5 | J49: FALSE | K49: Juan David Echeverri - Pedregal | L49: Pedregal | M49: 29 | N49: 1 | O49: 2026 | R49: =IF(wallet_records[[#This Row],[type]]="Gasto",wallet_records[[#This Row],[amount]]*(-1),wallet_records[[#This Row],[amount]]) -> 500000
A50: Bancolombia | B50: Servicios | C50: COP | D50: 881000 | E50: 881000 | F50: Ingreso | G50: Transferencia bancaria | H50: Arriendo | I50: 46050.5 | J50: FALSE | L50: La Ceja | M50: 28 | N50: 1 | O50: 2026 | R50: =IF(wallet_records[[#This Row],[type]]="Gasto",wallet_records[[#This Row],[amount]]*(-1),wallet_records[[#This Row],[amount]]) -> 881000
A51: Bancolombia | B51: Servicios | C51: COP | D51: 3146600 | E51: 3146600 | F51: Ingreso | G51: Transferencia bancaria | H51: Arriendo | I51: 46038.5 | J51: FALSE | K51: Alejandro Restrepo - Belén | L51: Belén | M51: 16 | N51: 1 | O51: 2026 | R51: =IF(wallet_records[[#This Row],[type]]="Gasto",wallet_records[[#This Row],[amount]]*(-1),wallet_records[[#This Row],[amount]]) -> 3146600
A52: Bancolombia | B52: Servicios | C52: COP | D52: 1750000 | E52: 1750000 | F52: Ingreso | G52: Transferencia bancaria | H52: Arriendo | I52: 46037.5 | J52: FALSE | K52: Elizabeth Restrepo - Yari | L52: Yari | M52: 15 | N52: 1 | O52: 2026 | R52: =IF(wallet_records[[#This Row],[type]]="Gasto",wallet_records[[#This Row],[amount]]*(-1),wallet_records[[#This Row],[amount]]) -> 1750000
A53: Bancolombia | B53: Servicios | C53: COP | D53: 1500000 | E53: 1500000 | F53: Ingreso | G53: Transferencia bancaria | H53: Arriendo | I53: 46036.5 | J53: FALSE | K53: Jorge Mario Naranjo Henao - Ocarinas | L53: Ocarinas | M53: 14 | N53: 1 | O53: 2026 | R53: =IF(wallet_records[[#This Row],[type]]="Gasto",wallet_records[[#This Row],[amount]]*(-1),wallet_records[[#This Row],[amount]]) -> 1500000
A54: Bancolombia | B54: Empleados | C54: COP | D54: 178000 | E54: 178000 | F54: Gasto | G54: Transferencia bancaria | H54: Seguridad Social | I54: 45992.792 | J54: FALSE | K54: Martha Lucia Uribe Jaramillo | L54: Martha Lucía Uribe Jaramillo | M54: 1 | N54: 12 | O54: 2025 | R54: =IF(wallet_records[[#This Row],[type]]="Gasto",wallet_records[[#This Row],[amount]]*(-1),wallet_records[[#This Row],[amount]]) -> -178000
A55: Bancolombia | B55: Empleados | C55: COP | D55: 178000 | E55: 178000 | F55: Gasto | G55: Transferencia bancaria | H55: Seguridad Social | I55: 45963.792 | J55: FALSE | K55: Martha Lucia Uribe Jaramillo | L55: Martha Lucía Uribe Jaramillo | M55: 2 | N55: 11 | O55: 2025 | R55: =IF(wallet_records[[#This Row],[type]]="Gasto",wallet_records[[#This Row],[amount]]*(-1),wallet_records[[#This Row],[amount]]) -> -178000
A56: Bancolombia | B56: Empleados | C56: COP | D56: 178000 | E56: 178000 | F56: Gasto | G56: Transferencia bancaria | H56: Seguridad Social | I56: 45931.792 | J56: FALSE | K56: Martha Lucia Uribe Jaramillo | L56: Martha Lucía Uribe Jaramillo | M56: 1 | N56: 10 | O56: 2025 | R56: =IF(wallet_records[[#This Row],[type]]="Gasto",wallet_records[[#This Row],[amount]]*(-1),wallet_records[[#This Row],[amount]]) -> -178000
A57: Bancolombia | B57: Empleados | C57: COP | D57: 178000 | E57: 178000 | F57: Gasto | G57: Transferencia bancaria | H57: Seguridad Social | I57: 45901.792 | J57: FALSE | K57: Martha Lucia Uribe Jaramillo | L57: Martha Lucía Uribe Jaramillo | M57: 1 | N57: 9 | O57: 2025 | R57: =IF(wallet_records[[#This Row],[type]]="Gasto",wallet_records[[#This Row],[amount]]*(-1),wallet_records[[#This Row],[amount]]) -> -178000
A58: Bancolombia | B58: Empleados | C58: COP | D58: 178000 | E58: 178000 | F58: Gasto | G58: Transferencia bancaria | H58: Seguridad Social | I58: 45870.792 | J58: FALSE | K58: Martha Lucia Uribe Jaramillo | L58: Martha Lucía Uribe Jaramillo | M58: 1 | N58: 8 | O58: 2025 | R58: =IF(wallet_records[[#This Row],[type]]="Gasto",wallet_records[[#This Row],[amount]]*(-1),wallet_records[[#This Row],[amount]]) -> -178000
A59: Bancolombia | B59: Empleados | C59: COP | D59: 178000 | E59: 178000 | F59: Gasto | G59: Transferencia bancaria | H59: Seguridad Social | I59: 45840.792 | J59: FALSE | K59: Martha Lucia Uribe Jaramillo | L59: Martha Lucía Uribe Jaramillo | M59: 2 | N59: 7 | O59: 2025 | R59: =IF(wallet_records[[#This Row],[type]]="Gasto",wallet_records[[#This Row],[amount]]*(-1),wallet_records[[#This Row],[amount]]) -> -178000
A60: Bancolombia | B60: Empleados | C60: COP | D60: 178000 | E60: 178000 | F60: Gasto | G60: Transferencia bancaria | H60: Seguridad Social | I60: 45809.792 | J60: FALSE | K60: Martha Lucia Uribe Jaramillo | L60: Martha Lucía Uribe Jaramillo | M60: 1 | N60: 6 | O60: 2025 | R60: =IF(wallet_records[[#This Row],[type]]="Gasto",wallet_records[[#This Row],[amount]]*(-1),wallet_records[[#This Row],[amount]]) -> -178000
A61: Bancolombia | B61: Empleados | C61: COP | D61: 178000 | E61: 178000 | F61: Gasto | G61: Transferencia bancaria | H61: Seguridad Social | I61: 45782.792 | J61: FALSE | K61: Martha Lucia Uribe Jaramillo | L61: Martha Lucía Uribe Jaramillo | M61: 5 | N61: 5 | O61: 2025 | R61: =IF(wallet_records[[#This Row],[type]]="Gasto",wallet_records[[#This Row],[amount]]*(-1),wallet_records[[#This Row],[amount]]) -> -178000
A62: Bancolombia | B62: Empleados | C62: COP | D62: 405800 | E62: 405800 | F62: Gasto | G62: Transferencia bancaria | H62: Seguridad Social | I62: 45748.792 | J62: FALSE | K62: Martha Lucia Uribe Jaramillo | L62: Martha Lucía Uribe Jaramillo | M62: 1 | N62: 4 | O62: 2025 | R62: =IF(wallet_records[[#This Row],[type]]="Gasto",wallet_records[[#This Row],[amount]]*(-1),wallet_records[[#This Row],[amount]]) -> -405800
... A65: Bancolombia | B65: Empleados | C65: COP | D65: 405800 | E65: 405800 | F65: Gasto | G65: Transferencia bancaria | H65: Seguridad Social | I65: 45658.792 | J65: FALSE | K65: Martha Lucia Uribe Jaramillo | L65: Martha Lucía Uribe Jaramillo | M65: 1 | N65: 1 | O65: 2025 | R65: =IF(wallet_records[[#This Row],[type]]="Gasto",wallet_records[[#This Row],[amount]]*(-1),wallet_records[[#This Row],[amount]]) -> -405800
A66: Fidu Impuestos | B66: Gastos de viaje | C66: COP | D66: 5000000 | E66: 5000000 | F66: Gasto | G66: Transferencia bancaria | H66: Paseo | I66: 45696.792 | J66: FALSE | L66: Martha Lucía Uribe Jaramillo | M66: 8 | N66: 2 | O66: 2025 | R66: =IF(wallet_records[[#This Row],[type]]="Gasto",wallet_records[[#This Row],[amount]]*(-1),wallet_records[[#This Row],[amount]]) -> -5000000
A67: NU Bank | B67: Impuestos - IVA, renta, otros | C67: COP | D67: 5176 | E67: 5176 | F67: Gasto | G67: Transferencia bancaria | H67: Pago de 4X1000 | I67: 45972.792 | J67: FALSE | L67: Martha Lucía Uribe Jaramillo | M67: 11 | N67: 11 | O67: 2025 | R67: =IF(wallet_records[[#This Row],[type]]="Gasto",wallet_records[[#This Row],[amount]]*(-1),wallet_records[[#This Row],[amount]]) -> -5176
A68: NU Bank | B68: Impuestos - IVA, renta, otros | C68: COP | D68: 4000 | E68: 4000 | F68: Gasto | G68: Transferencia bancaria | H68: Pago de 4X1000 | I68: 45969.792 | J68: FALSE | L68: Martha Lucía Uribe Jaramillo | M68: 8 | N68: 11 | O68: 2025 | R68: =IF(wallet_records[[#This Row],[type]]="Gasto",wallet_records[[#This Row],[amount]]*(-1),wallet_records[[#This Row],[amount]]) -> -4000
A69: Fidu Impuestos | B69: Impuestos - IVA, renta, otros | C69: COP | D69: 15000 | E69: 15000 | F69: Gasto | G69: Transferencia bancaria | H69: Tasa de seguridad | I69: 45962.792 | J69: FALSE | K69: Gobernación de Antioquia | L69: Yari | M69: 1 | N69: 11 | O69: 2025 | R69: =IF(wallet_records[[#This Row],[type]]="Gasto",wallet_records[[#This Row],[amount]]*(-1),wallet_records[[#This Row],[amount]]) -> -15000
A70: Fidu Impuestos | B70: Impuestos - IVA, renta, otros | C70: COP | D70: 13000 | E70: 13000 | F70: Gasto | G70: Transferencia bancaria | H70: Tasa de seguridad | I70: 45962.792 | J70: FALSE | K70: Gobernación de Antioquia | L70: Belén | M70: 1 | N70: 11 | O70: 2025 | R70: =IF(wallet_records[[#This Row],[type]]="Gasto",wallet_records[[#This Row],[amount]]*(-1),wallet_records[[#This Row],[amount]]) -> -13000
A71: Fidu Impuestos | B71: Impuestos - IVA, renta, otros | C71: COP | D71: 15000 | E71: 15000 | F71: Gasto | G71: Transferencia bancaria | H71: Tasa de seguridad | I71: 45962.792 | J71: FALSE | K71: Gobernación de Antioquia | L71: Yari | M71: 1 | N71: 11 | O71: 2025 | R71: =IF(wallet_records[[#This Row],[type]]="Gasto",wallet_records[[#This Row],[amount]]*(-1),wallet_records[[#This Row],[amount]]) -> -15000
A72: Fidu Impuestos | B72: Impuestos - IVA, renta, otros | C72: COP | D72: 16000 | E72: 16000 | F72: Gasto | G72: Transferencia bancaria | H72: Tasa de seguridad | I72: 45962.792 | J72: FALSE | K72: Gobernación de Antioquia | L72: Rivera del Valle | M72: 1 | N72: 11 | O72: 2025 | R72: =IF(wallet_records[[#This Row],[type]]="Gasto",wallet_records[[#This Row],[amount]]*(-1),wallet_records[[#This Row],[amount]]) -> -16000
A73: Fidu Impuestos | B73: Impuestos - IVA, renta, otros | C73: COP | D73: 12600 | E73: 12600 | F73: Gasto | G73: Transferencia bancaria | H73: Tasa de seguridad | I73: 45962.792 | J73: FALSE | K73: Gobernación de Antioquia | L73: Ocarinas | M73: 1 | N73: 11 | O73: 2025 | R73: =IF(wallet_records[[#This Row],[type]]="Gasto",wallet_records[[#This Row],[amount]]*(-1),wallet_records[[#This Row],[amount]]) -> -12600
A74: Fidu Impuestos | B74: Impuestos - IVA, renta, otros | C74: COP | D74: 16000 | E74: 16000 | F74: Gasto | G74: Transferencia bancaria | H74: Tasa de seguridad | I74: 45962.792 | J74: FALSE | K74: Gobernación de Antioquia | L74: Rivera del Valle | M74: 1 | N74: 11 | O74: 2025 | R74: =IF(wallet_records[[#This Row],[type]]="Gasto",wallet_records[[#This Row],[amount]]*(-1),wallet_records[[#This Row],[amount]]) -> -16000
A75: Fidu Impuestos | B75: Impuestos - IVA, renta, otros | C75: COP | D75: 13000 | E75: 13000 | F75: Gasto | G75: Transferencia bancaria | H75: Tasa de seguridad | I75: 45962.792 | J75: FALSE | K75: Gobernación de Antioquia | L75: Ocarinas | M75: 1 | N75: 11 | O75: 2025 | R75: =IF(wallet_records[[#This Row],[type]]="Gasto",wallet_records[[#This Row],[amount]]*(-1),wallet_records[[#This Row],[amount]]) -> -13000
A76: Fidu Impuestos | B76: Impuestos - IVA, renta, otros | C76: COP | D76: 10800 | E76: 10800 | F76: Gasto | G76: Transferencia bancaria | H76: Tasa de seguridad | I76: 45962.792 | J76: FALSE | K76: Gobernación de Antioquia | L76: Belén | M76: 1 | N76: 11 | O76: 2025 | R76: =IF(wallet_records[[#This Row],[type]]="Gasto",wallet_records[[#This Row],[amount]]*(-1),wallet_records[[#This Row],[amount]]) -> -10800
A77: Fidu Impuestos | B77: Impuestos - IVA, renta, otros | C77: COP | D77: 14400 | E77: 14400 | F77: Gasto | G77: Transferencia bancaria | H77: Tasa de seguridad | I77: 45962.792 | J77: FALSE | K77: Gobernación de Antioquia | L77: Rivera del Valle | M77: 1 | N77: 11 | O77: 2025 | R77: =IF(wallet_records[[#This Row],[type]]="Gasto",wallet_records[[#This Row],[amount]]*(-1),wallet_records[[#This Row],[amount]]) -> -14400
A78: Fidu Impuestos | B78: Impuestos - IVA, renta, otros | C78: COP | D78: 13000 | E78: 13000 | F78: Gasto | G78: Transferencia bancaria | H78: Tasa de seguridad | I78: 45962.792 | J78: FALSE | K78: Gobernación de Antioquia | L78: Ocarinas | M78: 1 | N78: 11 | O78: 2025 | R78: =IF(wallet_records[[#This Row],[type]]="Gasto",wallet_records[[#This Row],[amount]]*(-1),wallet_records[[#This Row],[amount]]) -> -13000
A79: Fidu Impuestos | B79: Impuestos - IVA, renta, otros | C79: COP | D79: 12000 | E79: 12000 | F79: Gasto | G79: Transferencia bancaria | H79: Tasa de seguridad | I79: 45962.792 | J79: FALSE | K79: Gobernación de Antioquia | L79: Belén | M79: 1 | N79: 11 | O79: 2025 | R79: =IF(wallet_records[[#This Row],[type]]="Gasto",wallet_records[[#This Row],[amount]]*(-1),wallet_records[[#This Row],[amount]]) -> -12000
A80: Fidu Impuestos | B80: Impuestos - IVA, renta, otros | C80: COP | D80: 12600 | E80: 12600 | F80: Gasto | G80: Transferencia bancaria | H80: Tasa de seguridad | I80: 45962.792 | J80: FALSE | K80: Gobernación de Antioquia | L80: Yari | M80: 1 | N80: 11 | O80: 2025 | R80: =IF(wallet_records[[#This Row],[type]]="Gasto",wallet_records[[#This Row],[amount]]*(-1),wallet_records[[#This Row],[amount]]) -> -12600
A81: Fidu Impuestos | B81: Impuestos - IVA, renta, otros | C81: COP | D81: 8010 | E81: 8010 | F81: Gasto | G81: Transferencia bancaria | H81: Tasa de seguridad | I81: 45962.792 | J81: FALSE | K81: La Ceja | L81: La Ceja | M81: 1 | N81: 11 | O81: 2025 | R81: =IF(wallet_records[[#This Row],[type]]="Gasto",wallet_records[[#This Row],[amount]]*(-1),wallet_records[[#This Row],[amount]]) -> -8010
A82: NU Bank | B82: Impuestos - IVA, renta, otros | C82: COP | D82: 20000 | E82: 20000 | F82: Gasto | G82: Transferencia bancaria | H82: Pago de 4X1000 | I82: 45954.792 | J82: FALSE | L82: Martha Lucía Uribe Jaramillo | M82: 24 | N82: 10 | O82: 2025 | R82: =IF(wallet_records[[#This Row],[type]]="Gasto",wallet_records[[#This Row],[amount]]*(-1),wallet_records[[#This Row],[amount]]) -> -20000
A83: NU Bank | B83: Impuestos - IVA, renta, otros | C83: COP | D83: 400 | E83: 400 | F83: Gasto | G83: Transferencia bancaria | H83: Pago de 4X1000 | I83: 45943.792 | J83: FALSE | L83: Martha Lucía Uribe Jaramillo | M83: 13 | N83: 10 | O83: 2025 | R83: =IF(wallet_records[[#This Row],[type]]="Gasto",wallet_records[[#This Row],[amount]]*(-1),wallet_records[[#This Row],[amount]]) -> -400
A84: NU Bank | B84: Impuestos - IVA, renta, otros | C84: COP | D84: 4000 | E84: 4000 | F84: Gasto | G84: Transferencia bancaria | H84: Pago de 4X1000 | I84: 45913.792 | J84: FALSE | L84: Martha Lucía Uribe Jaramillo | M84: 13 | N84: 9 | O84: 2025 | R84: =IF(wallet_records[[#This Row],[type]]="Gasto",wallet_records[[#This Row],[amount]]*(-1),wallet_records[[#This Row],[amount]]) -> -4000
A85: NU Bank | B85: Impuestos - IVA, renta, otros | C85: COP | D85: 4000 | E85: 4000 | F85: Gasto | G85: Transferencia bancaria | H85: Pago de 4X1000 | I85: 45910.792 | J85: FALSE | M85: 10 | N85: 9 | O85: 2025 | R85: =IF(wallet_records[[#This Row],[type]]="Gasto",wallet_records[[#This Row],[amount]]*(-1),wallet_records[[#This Row],[amount]]) -> -4000
A86: NU Bank | B86: Impuestos - IVA, renta, otros | C86: COP | D86: 28000 | E86: 28000 | F86: Gasto | G86: Transferencia bancaria | H86: Pago de 4X1000 | I86: 45909.792 | J86: FALSE | L86: Martha Lucía Uribe Jaramillo | M86: 9 | N86: 9 | O86: 2025 | R86: =IF(wallet_records[[#This Row],[type]]="Gasto",wallet_records[[#This Row],[amount]]*(-1),wallet_records[[#This Row],[amount]]) -> -28000
A87: NU Bank | B87: Impuestos - IVA, renta, otros | C87: COP | D87: 4400 | E87: 4400 | F87: Gasto | G87: Transferencia bancaria | H87: Pago de 4X1000 | I87: 45903.792 | J87: FALSE | L87: Martha Lucía Uribe Jaramillo | M87: 3 | N87: 9 | O87: 2025 | R87: =IF(wallet_records[[#This Row],[type]]="Gasto",wallet_records[[#This Row],[amount]]*(-1),wallet_records[[#This Row],[amount]]) -> -4400
A88: Fidu Impuestos | B88: Impuestos - IVA, renta, otros | C88: COP | D88: 961000 | E88: 961000 | F88: Gasto | G88: Transferencia bancaria | H88: Impuestos DIAN | I88: 45900.792 | J88: FALSE | K88: Varios | L88: Martha Lucía Uribe Jaramillo | M88: 31 | N88: 8 | O88: 2025 | R88: =IF(wallet_records[[#This Row],[type]]="Gasto",wallet_records[[#This Row],[amount]]*(-1),wallet_records[[#This Row],[amount]]) -> -961000
A89: Fidu Impuestos | B89: Impuestos - IVA, renta, otros | C89: COP | D89: 38000 | E89: 38000 | F89: Gasto | G89: Transferencia bancaria | H89: Tasa de seguridad | I89: 45896.792 | J89: FALSE | K89: Gobernación de Antioquia | L89: Belén | M89: 27 | N89: 8 | O89: 2025 | R89: =IF(wallet_records[[#This Row],[type]]="Gasto",wallet_records[[#This Row],[amount]]*(-1),wallet_records[[#This Row],[amount]]) -> -38000
A90: Fidu Impuestos | B90: Impuestos - IVA, renta, otros | C90: COP | D90: 15000 | E90: 15000 | F90: Gasto | G90: Transferencia bancaria | H90: Tasa de seguridad | I90: 45896.792 | J90: FALSE | K90: Gobernación de Antioquia | L90: Yari | M90: 27 | N90: 8 | O90: 2025 | R90: =IF(wallet_records[[#This Row],[type]]="Gasto",wallet_records[[#This Row],[amount]]*(-1),wallet_records[[#This Row],[amount]]) -> -15000
A91: Fidu Impuestos | B91: Impuestos - IVA, renta, otros | C91: COP | D91: 17000 | E91: 17000 | F91: Gasto | G91: Transferencia bancaria | H91: Tasa de seguridad | I91: 45896.792 | J91: FALSE | K91: Gobernación de Antioquia | L91: Rivera del Valle | M91: 27 | N91: 8 | O91: 2025 | R91: =IF(wallet_records[[#This Row],[type]]="Gasto",wallet_records[[#This Row],[amount]]*(-1),wallet_records[[#This Row],[amount]]) -> -17000
A92: Fidu Impuestos | B92: Impuestos - IVA, renta, otros | C92: COP | D92: 12000 | E92: 12000 | F92: Gasto | G92: Transferencia bancaria | H92: Tasa de seguridad | I92: 45896.792 | J92: FALSE | K92: Gobernación de Antioquia | L92: Ocarinas | M92: 27 | N92: 8 | O92: 2025 | R92: =IF(wallet_records[[#This Row],[type]]="Gasto",wallet_records[[#This Row],[amount]]*(-1),wallet_records[[#This Row],[amount]]) -> -12000
A93: Fidu Impuestos | B93: Impuestos - IVA, renta, otros | C93: COP | D93: 9500 | E93: 9500 | F93: Gasto | G93: Transferencia bancaria | H93: Tasa de seguridad | I93: 45896.792 | J93: FALSE | K93: La Ceja | L93: La Ceja | M93: 27 | N93: 8 | O93: 2025 | R93: =IF(wallet_records[[#This Row],[type]]="Gasto",wallet_records[[#This Row],[amount]]*(-1),wallet_records[[#This Row],[amount]]) -> -9500
A94: Fidu Impuestos | B94: Impuestos - IVA, renta, otros | C94: COP | D94: 12000 | E94: 12000 | F94: Gasto | G94: Transferencia bancaria | H94: Tasa de seguridad | I94: 45843.792 | J94: FALSE | K94: Gobernación de Antioquia | L94: Ocarinas | M94: 5 | N94: 7 | O94: 2025 | R94: =IF(wallet_records[[#This Row],[type]]="Gasto",wallet_records[[#This Row],[amount]]*(-1),wallet_records[[#This Row],[amount]]) -> -12000
A95: Fidu Impuestos | B95: Impuestos - IVA, renta, otros | C95: COP | D95: 14400 | E95: 14400 | F95: Gasto | G95: Transferencia bancaria | H95: Tasa de seguridad | I95: 45843.792 | J95: FALSE | K95: Gobernación de Antioquia | L95: Rivera del Valle | M95: 5 | N95: 7 | O95: 2025 | R95: =IF(wallet_records[[#This Row],[type]]="Gasto",wallet_records[[#This Row],[amount]]*(-1),wallet_records[[#This Row],[amount]]) -> -14400
A96: Fidu Impuestos | B96: Impuestos - IVA, renta, otros | C96: COP | D96: 11700 | E96: 11700 | F96: Gasto | G96: Transferencia bancaria | H96: Tasa de seguridad | I96: 45843.792 | J96: FALSE | K96: Gobernación de Antioquia | L96: Ocarinas | M96: 5 | N96: 7 | O96: 2025 | R96: =IF(wallet_records[[#This Row],[type]]="Gasto",wallet_records[[#This Row],[amount]]*(-1),wallet_records[[#This Row],[amount]]) -> -11700
A97: Fidu Impuestos | B97: Impuestos - IVA, renta, otros | C97: COP | D97: 15000 | E97: 15000 | F97: Gasto | G97: Transferencia bancaria | H97: Tasa de seguridad | I97: 45843.792 | J97: FALSE | K97: Gobernación de Antioquia | L97: Rivera del Valle | M97: 5 | N97: 7 | O97: 2025 | R97: =IF(wallet_records[[#This Row],[type]]="Gasto",wallet_records[[#This Row],[amount]]*(-1),wallet_records[[#This Row],[amount]]) -> -15000
A98: Fidu Impuestos | B98: Impuestos - IVA, renta, otros | C98: COP | D98: 13000 | E98: 13000 | F98: Gasto | G98: Transferencia bancaria | H98: Tasa de seguridad | I98: 45843.792 | J98: FALSE | K98: Gobernación de Antioquia | L98: Yari | M98: 5 | N98: 7 | O98: 2025 | R98: =IF(wallet_records[[#This Row],[type]]="Gasto",wallet_records[[#This Row],[amount]]*(-1),wallet_records[[#This Row],[amount]]) -> -13000
A99: Fidu Impuestos | B99: Impuestos - IVA, renta, otros | C99: COP | D99: 13500 | E99: 13500 | F99: Gasto | G99: Transferencia bancaria | H99: Tasa de seguridad | I99: 45843.792 | J99: FALSE | K99: Gobernación de Antioquia | L99: Yari | M99: 5 | N99: 7 | O99: 2025 | R99: =IF(wallet_records[[#This Row],[type]]="Gasto",wallet_records[[#This Row],[amount]]*(-1),wallet_records[[#This Row],[amount]]) -> -13500
... A102: Fidu Impuestos | B102: Impuestos - IVA, renta, otros | C102: COP | D102: 34000 | E102: 34000 | F102: Gasto | G102: Transferencia bancaria | H102: Tasa de seguridad | I102: 45807.792 | J102: FALSE | K102: Gobernación de Antioquia | L102: Rivera del Valle | M102: 30 | N102: 5 | O102: 2025 | R102: =IF(wallet_records[[#This Row],[type]]="Gasto",wallet_records[[#This Row],[amount]]*(-1),wallet_records[[#This Row],[amount]]) -> -34000
A103: Fiducuenta ARU | B103: Impuestos - IVA, renta, otros | C103: COP | D103: 3127.75 | E103: 3127.75 | F103: Gasto | G103: Transferencia bancaria | H103: Retención en la fuente | I103: 45732.792 | J103: FALSE | L103: Martha Lucía Uribe Jaramillo | M103: 16 | N103: 3 | O103: 2025 | R103: =IF(wallet_records[[#This Row],[type]]="Gasto",wallet_records[[#This Row],[amount]]*(-1),wallet_records[[#This Row],[amount]]) -> -3127.75
A104: Fidu Impuestos | B104: Impuestos - IVA, renta, otros | C104: COP | D104: 756032 | E104: 756032 | F104: Gasto | G104: Transferencia bancaria | H104: Impuesto Predial | I104: 45725.792 | J104: FALSE | K104: La Ceja | L104: La Ceja | M104: 9 | N104: 3 | O104: 2025 | R104: =IF(wallet_records[[#This Row],[type]]="Gasto",wallet_records[[#This Row],[amount]]*(-1),wallet_records[[#This Row],[amount]]) -> -756032
...

Sheet Activos
E5: Propiedad | F5: Avaluo catastral | G5: Avaluo Comercial | H5: Valor arriendo | M5: Impuesto predial | R5: Administracion
H6: 2022 | I6: 2023 | J6: 2024 | K6: 2025 | L6: 2026 | M6: 2022 | N6: 2023 | O6: 2024 | P6: 2025 | Q6: 2026 | R6: 2022 | S6: 2023 | T6: 2024 | U6: 2025 | V6: 2026
E7: Yari | F7: =260263000+11327000 -> 271590000 | G7: =(260263000+11327000)*1.4 -> 380226000 | H7: 1100000 | I7: 1350000 | J7: 1350000 | K7: 1650000 | N7: 1652293 | O7: 1926459 | P7: 2177825 | Q7: =P7*1.22 -> 2656946.5 | R7: 114000 | S7: 126000 | T7: 138000 | U7: 247500 | V7: =U7*1.237 -> 306157.5
E8: Belén | F8: 784665000 | G8: =784665000*1.4 -> 1098531000 | J8: 3000000 | K8: 3144600 | N8: 2905777 | O8: 3442766 | P8: 3904447 | Q8: =P8*1.22 -> 4763425.3 | V8: =U8*1.237 -> 0
E9: Ocarinas | F9: =168413000+20280000 -> 188693000 | G9: =(168413000+20280000)*1.4 -> 2.641702e+08 | H9: 980000 | I9: 1500000 | J9: 1400000 | K9: 1520000 | N9: 1442921 | O9: 1556970 | P9: 1613328 | Q9: =P9*1.22 -> 1968260.2 | R9: 314205 | S9: 393205 | T9: 437505 | U9: 477205 | V9: =U9*1.237 -> 590302.59
E10: Pedregal | F10: 130962000 | G10: =130962000*1.4 -> 183346800 | H10: 360000 | I10: 400000 | J10: 450000 | K10: 500000 | N10: 269629 | O10: 279068 | P10: 316495 | Q10: =P10*1.22 -> 386123.9 | V10: =U10*1.237 -> 0
E11: Ribera del valle | F11: =137811000+31940000 -> 169751000 | G11: =(137811000+31940000)*1.4 -> 2.376514e+08 | H11: 1200000 | I11: 1500000 | J11: 1630000 | K11: 1715000 | N11: 871419 | O11: 1032495 | P11: 1170958 | Q11: =P11*1.22 -> 1428568.8 | R11: 173200 | S11: 195900 | T11: 243000 | U11: 156300 | V11: =U11*1.237 -> 193343.1
E12: La Ceja | F12: 85100000 | G12: =85100000*1.4 -> 1.1914e+08 | H12: 225000 | I12: 881000 | J12: 881000 | K12: 881000 | M12: 550458 | N12: 765580 | O12: 911108 | P12: 765532 | Q12: =P12*1.22 -> 933949.04 | V12: =U12*1.237 -> 0
E13: Total | F13: =SUM(F7:F12) -> 1630761000 | G13: =SUM(G7:G12) -> 2283065400 | H13: =SUM(H7:H12) -> 3865000 | I13: =SUM(I7:I12) -> 5631000 | J13: =SUM(J7:J12) -> 8711000 | K13: =SUM(K7:K12) -> 9410600 | L13: =SUM(L7:L12) -> 0 | M13: =SUM(M7:M12) -> 550458 | ... P13: =SUM(P7:P12) -> 9948585 | Q13: =P13*1.22 -> 12137274 | R13: =SUM(R7:R12) -> 601405 | S13: =SUM(S7:S12) -> 715105 | T13: =SUM(T7:T12) -> 818505 | U13: =SUM(U7:U12) -> 881005 | V13: =SUM(V7:V12) -> 1089803.2
G14: Total Anualizado | H14: =H13*12 -> 46380000 | I14: =I13*12 -> 67572000 | J14: =J13*12 -> 104532000 | K14: =K13*12 -> 112927200 | L14: 0 | T14: =R13*12 -> 7216860 | U14: =S13*12 -> 8581260 | V14: =T13*12 -> 9822060 | W14: =U13*12 -> 10572060 | X14: =V13*12 -> 13077638
I17: Diciembre | O17: =(O7-N7)/N7 -> 0.16593062 | P17: =(P7-O7)/O7 -> 0.13048085 | Q17: =(Q7-P7)/P7 -> 0.22
I18: Noviembre | O18: =(O8-N8)/N8 -> 0.18480049 | P18: =(P8-O8)/O8 -> 0.13410177 | Q18: =(Q8-P8)/P8 -> 0.22
I19: Junio | O19: =(O9-N9)/N9 -> 0.079040363 | P19: =(P9-O9)/O9 -> 0.036197229 | Q19: =(Q9-P9)/P9 -> 0.22
O20: =(O10-N10)/N10 -> 0.035007362 | P20: =(P10-O10)/O10 -> 0.13411427 | Q20: =(Q10-P10)/P10 -> 0.22
O21: =(O11-N11)/N11 -> 0.18484334 | P21: =(P11-O11)/O11 -> 0.13410525 | Q21: =(Q11-P11)/P11 -> 0.22
O22: =(O12-N12)/N12 -> 0.19008856 | P22: =(P12-O12)/O12 -> -0.15977908 | Q22: =(Q12-P12)/P12 -> 0.22
G23: Mazda | H23: =4039975*1.1 -> 4443972.5
G24: Campos de Paz y Fatima | H24: =86600*1.1 -> 95260
G25: Taxi | H25: =2051498*1.1 -> 2256647.8
B29: Datos generales Ocarinas
B30: Municipio | C30: Medellin | F30: Históricos | G30: 2022 | H30: 2023 | I30: 2024 | J30: 2025 | K30: 2026 | L30: 2027
B31: Dirección | C31: Ocarinas PH Carrera 65 CC # 31 - 34
B32: Apartamento | C32: 205 | F32: Avalúo catastral | G32: =17500000+146744000 -> 164244000 | H32: =18254000+153069000 -> 171323000 | I32: =19689000+163508000 -> 183197000 | J32: =20280000+168413000 -> 188693000
B33: Parqueadero | C33: 99048 | H33: =(H32/G32)-1 -> 0.043100509 | I33: =(I32/H32)-1 -> 0.069307682 | J33: =(J32/I32)-1 -> 0.030000491
B34: Inquilino | C34: Jorge | F34: Avalúo comercial | G34: =G32*1.4 -> 229941600 | H34: =H32*1.4 -> 2.398522e+08 | I34: =I32*1.4 -> 2.564758e+08 | J34: =J32*1.4 -> 2.641702e+08
B35: Contacto | C35: 3003895464 | H35: =(H34/G34)-1 -> 0.043100509 | I35: =(I34/H34)-1 -> 0.069307682 | J35: =(J34/I34)-1 -> 0.030000491
B36: Inicio Contrato | F36: Arriendo | G36: 980000 | H36: 1500000 | I36: 1400000 | J36: 1520000 | K36: =J36*(1+K37) -> 1597520 | L36: =K36*(1+L37) -> 1693371.2
B37: Adminisrador | H37: =(H36/G36)-1 -> 0.53061224 | I37: =(I36/H36)-1 -> -0.066666667 | J37: =(J36/I36)-1 -> 0.085714286 | K37: 0.051 | L37: 0.06
B38: Contacto administrador | F38: Administración | G38: 314205 | H38: 393205 | I38: 437505 | J38: 477205 | K38: =J38*(1+K39) -> 590302.59 | L38: =K38*(1+L39) -> 678847.97
B39: Fecha pago administracion | H39: =(H38/G38)-1 -> 0.25142821 | I39: =(I38/H38)-1 -> 0.11266388 | J39: =(J38/I38)-1 -> 0.09074182 | K39: 0.237 | L39: 0.15
B40: Cuenta pago administacion | C40: 55194145283 Bancolombia ahorros | F40: Predial | G40: =1098724+111610 -> 1210334 | H40: 1442921 | I40: 1556970 | J40: 1613328 | K40: =J40*(1+K41) -> 1995686.7 | L40: =K40*(1+L41) -> 2295039.7
B41: Fecha pago canon de arriendo | C41: 18 de cada mes | H41: =(H40/G40)-1 -> 0.19216762 | I41: =(I40/H40)-1 -> 0.079040363 | J41: =(J40/I40)-1 -> 0.036197229 | K41: 0.237 | L41: 0.15
B42: Arriendo Anual | C42: 2026 | D42: =J36*5+K36*7 -> 18782640 | G42: =G40/G32 -> 0.0073691216 | H42: =H40/H32 -> 0.0084222259 | I42: =I40/I32 -> 0.0084988837 | J42: =J40/J32 -> 0.0085500151
B43: Arriendo Anual Ajustado | C43: =1/12 -> 0.083333333 | D43: =D42*(1-C43) -> 17217420
B44: Valor Administración | C44: 2026 | D44: =K38*12 -> 7083631
B45: Predial estimado | C45: 2026 | D45: =K40 -> 1995686.7
B48: Datos generales Rivera del Valle
B49: Municipio | D49: Medellin | F49: Históricos | G49: 2022 | H49: 2023 | I49: 2024 | J49: 2025 | K49: 2026 | L49: 2027
B50: Dirección | D50: Rivera del Valle Calle 60 #75-150
B51: Apartamento | D51: 11-643 | F51: Avalúo catastral | H51: =125255000+28750000 -> 154005000 | I51: =133797000+31010000 -> 164807000 | J51: =137811000+31940000 -> 169751000
B52: Parqueadero | D52: 347 | I52: =(I51/H51)-1 -> 0.07014058 | J52: =(J51/I51)-1 -> 0.029998726
B53: Inquilino | D53: Diana Patricia Restrepo Ruiz | F53: Avalúo comercial | H53: =H51*1.4 -> 215607000 | I53: =I51*1.4 -> 230729800 | J53: =J51*1.4 -> 2.376514e+08
B54: Contacto | D54: 300 8037155 | I54: =(I53/H53)-1 -> 0.07014058 | J54: =(J53/I53)-1 -> 0.029998726
B55: Inicio Contrato | D55: 44681 | F55: Arriendo | G55: 1200000 | H55: 1500000 | I55: 1630000 | J55: 1715000 | K55: =J55*(1+K56) -> 1802465 | L55: =K55*(1+L56) -> 1910612.9
B56: Adminisrador | D56: Juan Camilo | H56: =(H55/G55)-1 -> 0.25 | I56: =(I55/H55)-1 -> 0.086666667 | J56: =(J55/I55)-1 -> 0.052147239 | K56: 0.051 | L56: 0.06
B57: Contacto administrador | D57: 3002381296 | F57: Administración | G57: 173200 | H57: 195900 | I57: 243000 | J57: 256300 | K57: =J57*(1+K58) -> 317043.1 | L57: =K57*(1+L58) -> 364599.57
B58: Fecha pago administracion | D58: Todo el mes | H58: =(H57/G57)-1 -> 0.13106236 | I58: =(I57/H57)-1 -> 0.24042879 | J58: =(J57/I57)-1 -> 0.05473251 | K58: 0.237 | L58: 0.15
B59: Cuenta pago administacion | D59: https://www.pagosvirtualesavvillas.com.co/personal/pagos/162 | F59: Predial | H59: 871419 | I59: 1032495 | J59: 1170958 | K59: =J59*(1+K60) -> 1448475 | L59: =K59*(1+L60) -> 1665746.3
B60: Fecha pago canon de arriendo | D60: 30 de cada mes | I60: =(I59/H59)-1 -> 0.18484334 | J60: =(J59/I59)-1 -> 0.13410525 | K60: 0.237 | L60: 0.15
B61: Arriendo Anual | C61: 2026 | D61: =J55*11+K55*1 -> 20667465 | H61: =H59/H51 -> 0.0056583812 | I61: =I59/I51 -> 0.0062648735 | J61: =J59/J51 -> 0.0068980919
B62: Arriendo Anual Ajustado | C62: =1/12 -> 0.083333333 | D62: =D61*(1-C62) -> 18945176
B63: Valor Administración | C63: 2026 | D63: =K57*12 -> 3804517.2
B64: Predial estimado | C64: 2026 | D64: =K59 -> 1448475
B67: Datos generales La Ceja
B68: Municipio | D68: La ceja | F68: Históricos | G68: 2022 | H68: 2023 | I68: 2024 | J68: 2025 | K68: 2026 | L68: 2027
B69: Dirección | D69: Pinal del Rio Carrera 19A #13-19
B70: Apartamento | D70: No aplica | F70: Avalúo catastral | G70: 75789458 | H70: 79055984 | I70: 82621500 | J70: 85100000
B71: Parqueadero | D71: Carrera 19A #13-21 | H71: =(H70/G70)-1 -> 0.043100005 | I71: =(I70/H70)-1 -> 0.045101153 | J71: =(J70/I70)-1 -> 0.029998245
B72: Inquilino | F72: Avalúo comercial | G72: =G70*1.4 -> 1.0610524e+08 | H72: =H70*1.4 -> 1.1067838e+08 | I72: =I70*1.4 -> 115670100 | J72: =J70*1.4 -> 1.1914e+08
B73: Contacto | H73: =(H72/G72)-1 -> 0.043100005 | I73: =(I72/H72)-1 -> 0.045101153 | J73: =(J72/I72)-1 -> 0.029998245
B74: Inicio Contrato | F74: Arriendo | G74: 225000 | H74: 881000 | I74: 881000 | J74: 881000 | K74: =J74*(1+K75) -> 925931 | L74: =K74*(1+L75) -> 981486.86
B75: Adminisrador | D75: No paga | H75: =(H74/G74)-1 -> 2.9155556 | I75: =(I74/H74)-1 -> 0 | J75: =(J74/I74)-1 -> 0 | K75: 0.051 | L75: 0.06
B76: Contacto administrador | F76: Administración
B77: Fecha pago administracion
B78: Cuenta pago administacion | F78: Predial | G78: 550458 | H78: 765580 | I78: 911108 | J78: 765532 | K78: =J78*(1+K79) -> 946963.08 | L78: =K78*(1+L79) -> 1089007.5
B79: Fecha pago canon de arriendo | D79: 27 de cada mes | H79: =(H78/G78)-1 -> 0.39080547 | I79: =(I78/H78)-1 -> 0.19008856 | J79: =(J78/I78)-1 -> -0.15977908 | K79: 0.237 | L79: 0.15
B80: Arriendo Anual | C80: 2026 | D80: =J74*12 -> 10572000 | G80: =G78/G70 -> 0.007262989 | H80: =H78/H70 -> 0.0096840234 | I80: =I78/I70 -> 0.011027493 | J80: =J78/J70 -> 0.0089956757
B81: Arriendo Anual Ajustado | C81: =1/12 -> 0.083333333 | D81: =D80*(1-C81) -> 9691000
B82: Valor Administración | C82: 2026 | D82: =K76*12 -> 0
B83: Predial estimado | C83: 2026 | D83: =K78 -> 946963.08
B86: Datos generales Pedregal
B87: Municipio | D87: Medellin | F87: Históricos | G87: 2022 | H87: 2023 | I87: 2024 | J87: 2025 | K87: 2026 | L87: 2027
B88: Dirección | D88: Pedregal
B89: Apartamento | F89: Avalúo catastral | G89: 38870000 | H89: 40545000 | I89: 127148000 | J89: 130962000
B90: Parqueadero | H90: =(H89/G89)-1 -> 0.043092359 | I90: =(I89/H89)-1 -> 2.1359724 | J90: =(J89/I89)-1 -> 0.029996539
B91: Inquilino | F91: Avalúo comercial | G91: =G89*1.4 -> 54418000 | H91: =H89*1.4 -> 56763000 | I91: =I89*1.4 -> 178007200 | J91: =J89*1.4 -> 183346800
B92: Contacto | H92: =(H91/G91)-1 -> 0.043092359 | I92: =(I91/H91)-1 -> 2.1359724 | J92: =(J91/I91)-1 -> 0.029996539
B93: Inicio Contrato | F93: Arriendo | G93: 360000 | H93: 400000 | I93: 450000 | J93: 500000 | K93: =J93*(1+K94) -> 525500 | L93: =K93*(1+L94) -> 557030
B94: Adminisrador | D94: No paga | H94: =(H93/G93)-1 -> 0.11111111 | I94: =(I93/H93)-1 -> 0.125 | J94: =(J93/I93)-1 -> 0.11111111 | K94: 0.051 | L94: 0.06
B95: Contacto administrador | F95: Administración
B96: Fecha pago administracion
B97: Cuenta pago administacion | F97: Predial | G97: 258487 | H97: 269629 | I97: 279068 | J97: 316495 | K97: =J97*(1+K98) -> 391504.32 | L97: =K97*(1+L98) -> 450229.96
B98: Fecha pago canon de arriendo | H98: =(H97/G97)-1 -> 0.043104682 | I98: =(I97/H97)-1 -> 0.035007362 | J98: =(J97/I97)-1 -> 0.13411427 | K98: 0.237 | L98: 0.15
B99: Arriendo Anual | C99: 2026 | D99: =J93*11+K93*1 -> 6025500 | G99: =G97/G89 -> 0.0066500386 | H99: =H97/H89 -> 0.0066501172 | I99: =I97/I89 -> 0.0021948281 | J99: =J97/J89 -> 0.0024166934
B100: Arriendo Anual Ajustado | C100: =1/12 -> 0.083333333 | D100: =D99*(1-C100) -> 5523375
B101: Valor Administración | C101: 2026 | D101: =K95*12 -> 0
B102: Predial estimado | C102: 2026 | D102: =K97 -> 391504.32
B105: Datos generales Belén El Nogal
B106: Municipio | D106: Medellin | F106: Históricos | G106: 2022 | H106: 2023 | I106: 2024 | J106: 2025 | K106: 2026 | L106: 2027
B107: Dirección | D107: El Nogal
B108: Apartamento | F108: Avalúo catastral | G108: 680520000 | H108: 709850000 | I108: 761811000 | J108: 784665000
B109: Parqueadero | H109: =(H108/G108)-1 -> 0.043099395 | I109: =(I108/H108)-1 -> 0.073199972 | J109: =(J108/I108)-1 -> 0.029999567
B110: Inquilino | F110: Avalúo comercial | G110: =G108*1.4 -> 9.52728e+08 | H110: =H108*1.4 -> 9.9379e+08 | I110: =I108*1.4 -> 1.0665354e+09 | J110: =J108*1.4 -> 1098531000
B111: Contacto | H111: =(H110/G110)-1 -> 0.043099395 | I111: =(I110/H110)-1 -> 0.073199972 | J111: =(J110/I110)-1 -> 0.029999567
B112: Inicio Contrato | F112: Arriendo | I112: 3000000 | J112: 3144600 | K112: =J112*(1+K113) -> 3304974.6 | L112: =K112*(1+L113) -> 3503273.1
B113: Adminisrador | D113: No paga | J113: =(J112/I112)-1 -> 0.0482 | K113: 0.051 | L113: 0.06
B114: Contacto administrador | F114: Administración
B115: Fecha pago administracion
B116: Cuenta pago administacion | F116: Predial | G116: 2417047 | H116: 2905777 | I116: 3442766 | J116: 3904447 | K116: =J116*(1+K117) -> 4829800.9 | L116: =K116*(1+L117) -> 5554271.1
B117: Fecha pago canon de arriendo | H117: =(H116/G116)-1 -> 0.20220128 | I117: =(I116/H116)-1 -> 0.18480049 | J117: =(J116/I116)-1 -> 0.13410177 | K117: 0.237 | L117: 0.15
...

Sheet Saldos
D2: Bancolombia | E2: Mantenimiento | F2: Impuestos | G2: Administración | H2: ARU | I2: Nu Bank | J2: Total | L2: Bancolombia | M2: Mantenimiento | N2: Impuestos | O2: ARU | P2: Nu Bank | Q2: Total | S2: Bancolombia | T2: Mantenimiento | U2: Impuestos | V2: ARU | W2: Nu Bank | X2: Total | Z2: Bancolombia | AA2: Mantenimiento | AB2: Impuestos | AC2: ARU | AD2: Nu Bank | AE2: Total
B3: Mes | C3: Año | D3: Saldo | E3: Saldo | F3: Saldo | G3: Saldo | H3: Saldo | I3: Saldo | J3: Saldo | L3: Diferencia | M3: Diferencia | N3: Diferencia | O3: Diferencia | P3: Diferencia | Q3: Diferencia | S3: Imputado | T3: Imputado | U3: Imputado | V3: Imputado | W3: Imputado | X3: Imputado | Z3: Ajuste | AA3: Ajuste | AB3: Ajuste | AC3: Ajuste | AD3: Ajuste | AE3: Ajuste
B4: 1 | C4: 2022 | D4: 8545970.5 | E4: 0 | F4: 0 | H4: 0 | I4: 0 | J4: =SUM(D4:I4) -> 8545970.5
B5: 2 | C5: 2022 | D5: 8552288.9 | E5: 0 | F5: 0 | H5: 0 | I5: 0 | J5: =SUM(D5:I5) -> 8552288.9
B6: 3 | C6: 2022 | D6: 7634668.6 | E6: 0 | F6: 0 | H6: 0 | I6: 0 | J6: =SUM(D6:I6) -> 7634668.6 | L6: =D6-D5 -> -917620.3 | M6: =E6-E5 -> 0 | N6: =F6-F5 -> 0 | O6: =H6-H5 -> 0 | P6: =I6-I5 -> 0 | Q6: =J6-J5 -> -917620.3 | S6: =SUMIFS(wallet_records!$R:$R,wallet_records!$A:$A,"Bancolombia",wallet_records!$N:$N,Saldos!$B6,wallet_records!$O:$O,Saldos!$C6) -> -917620.3 | T6: =SUMIFS(wallet_records!$R:$R,wallet_records!$A:$A,"Fidu Mantenimiento",wallet_records!$N:$N,Saldos!$B6,wallet_records!$O:$O,Saldos!$C6) -> 0 | U6: =SUMIFS(wallet_records!$R:$R,wallet_records!$A:$A,"Fidu Impuestos",wallet_records!$N:$N,Saldos!$B6,wallet_records!$O:$O,Saldos!$C6) -> 0 | V6: =SUMIFS(wallet_records!$R:$R,wallet_records!$A:$A,"Fiducuenta ARU",wallet_records!$N:$N,Saldos!$B6,wallet_records!$O:$O,Saldos!$C6) -> 0 | W6: =SUMIFS(wallet_records!$R:$R,wallet_records!$A:$A,"Nu Bank",wallet_records!$N:$N,Saldos!$B6,wallet_records!$O:$O,Saldos!$C6) -> 0 | X6: =SUM(S6:W6) -> -917620.3 | Z6: =L6-S6 -> 1.1641532e-09 | AA6: =M6-T6 -> 0 | AB6: =N6-U6 -> 0 | AC6: =O6-V6 -> 0 | AD6: =P6-W6 -> 0 | AE6: =SUM(Z6:AD6) -> 1.1641532e-09
B7: 4 | C7: 2022 | D7: 7332270.5 | E7: 0 | F7: 0 | H7: 0 | I7: 0 | J7: =SUM(D7:I7) -> 7332270.5 | L7: =D7-D6 -> -302398.05 | M7: =E7-E6 -> 0 | N7: =F7-F6 -> 0 | O7: =H7-H6 -> 0 | P7: =I7-I6 -> 0 | Q7: =J7-J6 -> -302398.05 | S7: =SUMIFS(wallet_records!$R:$R,wallet_records!$A:$A,"Bancolombia",wallet_records!$N:$N,Saldos!$B7,wallet_records!$O:$O,Saldos!$C7) -> -302398.05 | T7: =SUMIFS(wallet_records!$R:$R,wallet_records!$A:$A,"Fidu Mantenimiento",wallet_records!$N:$N,Saldos!$B7,wallet_records!$O:$O,Saldos!$C7) -> 0 | U7: =SUMIFS(wallet_records!$R:$R,wallet_records!$A:$A,"Fidu Impuestos",wallet_records!$N:$N,Saldos!$B7,wallet_records!$O:$O,Saldos!$C7) -> 0 | V7: =SUMIFS(wallet_records!$R:$R,wallet_records!$A:$A,"Fiducuenta ARU",wallet_records!$N:$N,Saldos!$B7,wallet_records!$O:$O,Saldos!$C7) -> 0 | W7: =SUMIFS(wallet_records!$R:$R,wallet_records!$A:$A,"Nu Bank",wallet_records!$N:$N,Saldos!$B7,wallet_records!$O:$O,Saldos!$C7) -> 0 | X7: =SUM(S7:W7) -> -302398.05 | Z7: =L7-S7 -> -9.3132257e-10 | AA7: =M7-T7 -> 0 | AB7: =N7-U7 -> 0 | AC7: =O7-V7 -> 0 | AD7: =P7-W7 -> 0 | AE7: =SUM(Z7:AD7) -> -9.3132257e-10
B8: 5 | C8: 2022 | D8: 8165035.1 | E8: 500000 | F8: 1562500 | H8: 0 | I8: 0 | J8: =SUM(D8:I8) -> 10227535 | L8: =D8-D7 -> 832764.58 | M8: =E8-E7 -> 500000 | N8: =F8-F7 -> 1562500 | O8: =H8-H7 -> 0 | P8: =I8-I7 -> 0 | Q8: =J8-J7 -> 2895264.6 | S8: =SUMIFS(wallet_records!$R:$R,wallet_records!$A:$A,"Bancolombia",wallet_records!$N:$N,Saldos!$B8,wallet_records!$O:$O,Saldos!$C8) -> 2895264.6 | T8: =SUMIFS(wallet_records!$R:$R,wallet_records!$A:$A,"Fidu Mantenimiento",wallet_records!$N:$N,Saldos!$B8,wallet_records!$O:$O,Saldos!$C8) -> 0 | U8: =SUMIFS(wallet_records!$R:$R,wallet_records!$A:$A,"Fidu Impuestos",wallet_records!$N:$N,Saldos!$B8,wallet_records!$O:$O,Saldos!$C8) -> 0 | V8: =SUMIFS(wallet_records!$R:$R,wallet_records!$A:$A,"Fiducuenta ARU",wallet_records!$N:$N,Saldos!$B8,wallet_records!$O:$O,Saldos!$C8) -> 0 | W8: =SUMIFS(wallet_records!$R:$R,wallet_records!$A:$A,"Nu Bank",wallet_records!$N:$N,Saldos!$B8,wallet_records!$O:$O,Saldos!$C8) -> 0 | X8: =SUM(S8:W8) -> 2895264.6 | Z8: =L8-S8 -> -2062500 | AA8: =M8-T8 -> 500000 | AB8: =N8-U8 -> 1562500 | AC8: =O8-V8 -> 0 | AD8: =P8-W8 -> 0 | AE8: =SUM(Z8:AD8) -> 0
B9: 6 | C9: 2022 | D9: 7027980.2 | E9: 901956 | F9: 3131111 | H9: 0 | I9: 0 | J9: =SUM(D9:I9) -> 11061047 | L9: =D9-D8 -> -1137054.9 | M9: =E9-E8 -> 401956 | N9: =F9-F8 -> 1568611 | O9: =H9-H8 -> 0 | P9: =I9-I8 -> 0 | Q9: =J9-J8 -> 833512.09 | S9: =SUMIFS(wallet_records!$R:$R,wallet_records!$A:$A,"Bancolombia",wallet_records!$N:$N,Saldos!$B9,wallet_records!$O:$O,Saldos!$C9) -> 875445.09 | T9: =SUMIFS(wallet_records!$R:$R,wallet_records!$A:$A,"Fidu Mantenimiento",wallet_records!$N:$N,Saldos!$B9,wallet_records!$O:$O,Saldos!$C9) -> -48044 | U9: =SUMIFS(wallet_records!$R:$R,wallet_records!$A:$A,"Fidu Impuestos",wallet_records!$N:$N,Saldos!$B9,wallet_records!$O:$O,Saldos!$C9) -> 6111 | V9: =SUMIFS(wallet_records!$R:$R,wallet_records!$A:$A,"Fiducuenta ARU",wallet_records!$N:$N,Saldos!$B9,wallet_records!$O:$O,Saldos!$C9) -> 0 | W9: =SUMIFS(wallet_records!$R:$R,wallet_records!$A:$A,"Nu Bank",wallet_records!$N:$N,Saldos!$B9,wallet_records!$O:$O,Saldos!$C9) -> 0 | X9: =SUM(S9:W9) -> 833512.09 | Z9: =L9-S9 -> -2012500 | AA9: =M9-T9 -> 450000 | AB9: =N9-U9 -> 1562500 | AC9: =O9-V9 -> 0 | AD9: =P9-W9 -> 0 | AE9: =SUM(Z9:AD9) -> 9.3132257e-10
B10: 7 | C10: 2022 | D10: 7321266.8 | E10: 1355484 | F10: 4705857 | H10: 0 | I10: 0 | J10: =SUM(D10:I10) -> 13382608 | L10: =D10-D9 -> 293286.57 | M10: =E10-E9 -> 453528 | N10: =F10-F9 -> 1574746 | O10: =H10-H9 -> 0 | P10: =I10-I9 -> 0 | Q10: =J10-J9 -> 2321560.6 | S10: =SUMIFS(wallet_records!$R:$R,wallet_records!$A:$A,"Bancolombia",wallet_records!$N:$N,Saldos!$B10,wallet_records!$O:$O,Saldos!$C10) -> 2305786.6 | T10: =SUMIFS(wallet_records!$R:$R,wallet_records!$A:$A,"Fidu Mantenimiento",wallet_records!$N:$N,Saldos!$B10,wallet_records!$O:$O,Saldos!$C10) -> 3528 | U10: =SUMIFS(wallet_records!$R:$R,wallet_records!$A:$A,"Fidu Impuestos",wallet_records!$N:$N,Saldos!$B10,wallet_records!$O:$O,Saldos!$C10) -> 12246 | V10: =SUMIFS(wallet_records!$R:$R,wallet_records!$A:$A,"Fiducuenta ARU",wallet_records!$N:$N,Saldos!$B10,wallet_records!$O:$O,Saldos!$C10) -> 0 | W10: =SUMIFS(wallet_records!$R:$R,wallet_records!$A:$A,"Nu Bank",wallet_records!$N:$N,Saldos!$B10,wallet_records!$O:$O,Saldos!$C10) -> 0 | X10: =SUM(S10:W10) -> 2321560.6 | Z10: =L10-S10 -> -2012500 | AA10: =M10-T10 -> 450000 | AB10: =N10-U10 -> 1562500 | AC10: =O10-V10 -> 0 | AD10: =P10-W10 -> 0 | AE10: =SUM(Z10:AD10) -> -9.3132257e-10
B11: 8 | C11: 2022 | D11: 5780011.8 | E11: 1811303 | F11: 6288560 | H11: 0 | I11: 0 | J11: =SUM(D11:I11) -> 13879875 | L11: =D11-D10 -> -1541255 | M11: =E11-E10 -> 455819 | N11: =F11-F10 -> 1582703 | O11: =H11-H10 -> 0 | P11: =I11-I10 -> 0 | Q11: =J11-J10 -> 497266.99 | S11: =SUMIFS(wallet_records!$R:$R,wallet_records!$A:$A,"Bancolombia",wallet_records!$N:$N,Saldos!$B11,wallet_records!$O:$O,Saldos!$C11) -> 471244.99 | T11: =SUMIFS(wallet_records!$R:$R,wallet_records!$A:$A,"Fidu Mantenimiento",wallet_records!$N:$N,Saldos!$B11,wallet_records!$O:$O,Saldos!$C11) -> 5819 | U11: =SUMIFS(wallet_records!$R:$R,wallet_records!$A:$A,"Fidu Impuestos",wallet_records!$N:$N,Saldos!$B11,wallet_records!$O:$O,Saldos!$C11) -> 20203 | V11: =SUMIFS(wallet_records!$R:$R,wallet_records!$A:$A,"Fiducuenta ARU",wallet_records!$N:$N,Saldos!$B11,wallet_records!$O:$O,Saldos!$C11) -> 0 | W11: =SUMIFS(wallet_records!$R:$R,wallet_records!$A:$A,"Nu Bank",wallet_records!$N:$N,Saldos!$B11,wallet_records!$O:$O,Saldos!$C11) -> 0 | X11: =SUM(S11:W11) -> 497266.99 | Z11: =L11-S11 -> -2012500 | AA11: =M11-T11 -> 450000 | AB11: =N11-U11 -> 1562500 | AC11: =O11-V11 -> 0 | AD11: =P11-W11 -> 0 | AE11: =SUM(Z11:AD11) -> 0
B12: 9 | C12: 2022 | D12: 2490748.8 | E12: 2270178 | F12: 7881873 | H12: 0 | I12: 0 | J12: =SUM(D12:I12) -> 12642800 | L12: =D12-D11 -> -3289263 | M12: =E12-E11 -> 458875 | N12: =F12-F11 -> 1593313 | O12: =H12-H11 -> 0 | P12: =I12-I11 -> 0 | Q12: =J12-J11 -> -1237075 | S12: =SUMIFS(wallet_records!$R:$R,wallet_records!$A:$A,"Bancolombia",wallet_records!$N:$N,Saldos!$B12,wallet_records!$O:$O,Saldos!$C12) -> -1276763 | T12: =SUMIFS(wallet_records!$R:$R,wallet_records!$A:$A,"Fidu Mantenimiento",wallet_records!$N:$N,Saldos!$B12,wallet_records!$O:$O,Saldos!$C12) -> 8875 | U12: =SUMIFS(wallet_records!$R:$R,wallet_records!$A:$A,"Fidu Impuestos",wallet_records!$N:$N,Saldos!$B12,wallet_records!$O:$O,Saldos!$C12) -> 30813 | V12: =SUMIFS(wallet_records!$R:$R,wallet_records!$A:$A,"Fiducuenta ARU",wallet_records!$N:$N,Saldos!$B12,wallet_records!$O:$O,Saldos!$C12) -> 0 | W12: =SUMIFS(wallet_records!$R:$R,wallet_records!$A:$A,"Nu Bank",wallet_records!$N:$N,Saldos!$B12,wallet_records!$O:$O,Saldos!$C12) -> 0 | X12: =SUM(S12:W12) -> -1237075 | Z12: =L12-S12 -> -2012500 | AA12: =M12-T12 -> 450000 | AB12: =N12-U12 -> 1562500 | AC12: =O12-V12 -> 0 | AD12: =P12-W12 -> 0 | AE12: =SUM(Z12:AD12) -> 0
B13: 10 | C13: 2022 | D13: 3348640.8 | E13: 2732330 | F13: 9486564 | H13: 0 | I13: 0 | J13: =SUM(D13:I13) -> 15567535 | L13: =D13-D12 -> 857892.05 | M13: =E13-E12 -> 462152 | N13: =F13-F12 -> 1604691 | O13: =H13-H12 -> 0 | P13: =I13-I12 -> 0 | Q13: =J13-J12 -> 2924735.1 | S13: =SUMIFS(wallet_records!$R:$R,wallet_records!$A:$A,"Bancolombia",wallet_records!$N:$N,Saldos!$B13,wallet_records!$O:$O,Saldos!$C13) -> 2870392 | T13: =SUMIFS(wallet_records!$R:$R,wallet_records!$A:$A,"Fidu Mantenimiento",wallet_records!$N:$N,Saldos!$B13,wallet_records!$O:$O,Saldos!$C13) -> 12152 | U13: =SUMIFS(wallet_records!$R:$R,wallet_records!$A:$A,"Fidu Impuestos",wallet_records!$N:$N,Saldos!$B13,wallet_records!$O:$O,Saldos!$C13) -> 42191 | V13: =SUMIFS(wallet_records!$R:$R,wallet_records!$A:$A,"Fiducuenta ARU",wallet_records!$N:$N,Saldos!$B13,wallet_records!$O:$O,Saldos!$C13) -> 0 | W13: =SUMIFS(wallet_records!$R:$R,wallet_records!$A:$A,"Nu Bank",wallet_records!$N:$N,Saldos!$B13,wallet_records!$O:$O,Saldos!$C13) -> 0 | X13: =SUM(S13:W13) -> 2924735 | Z13: =L13-S13 -> -2012500 | AA13: =M13-T13 -> 450000 | AB13: =N13-U13 -> 1562500 | AC13: =O13-V13 -> 0 | AD13: =P13-W13 -> 0 | AE13: =SUM(Z13:AD13) -> 4.6566129e-10
B14: 11 | C14: 2022 | D14: 3247667.9 | E14: 3196956 | F14: 11099846 | H14: 0 | I14: 500000 | J14: =SUM(D14:I14) -> 18044470 | L14: =D14-D13 -> -100972.87 | M14: =E14-E13 -> 464626 | N14: =F14-F13 -> 1613282 | O14: =H14-H13 -> 0 | P14: =I14-I13 -> 500000 | Q14: =J14-J13 -> 2476935.1 | S14: =SUMIFS(wallet_records!$R:$R,wallet_records!$A:$A,"Bancolombia",wallet_records!$N:$N,Saldos!$B14,wallet_records!$O:$O,Saldos!$C14) -> 1911527.1 | T14: =SUMIFS(wallet_records!$R:$R,wallet_records!$A:$A,"Fidu Mantenimiento",wallet_records!$N:$N,Saldos!$B14,wallet_records!$O:$O,Saldos!$C14) -> 14626 | U14: =SUMIFS(wallet_records!$R:$R,wallet_records!$A:$A,"Fidu Impuestos",wallet_records!$N:$N,Saldos!$B14,wallet_records!$O:$O,Saldos!$C14) -> 50782 | V14: =SUMIFS(wallet_records!$R:$R,wallet_records!$A:$A,"Fiducuenta ARU",wallet_records!$N:$N,Saldos!$B14,wallet_records!$O:$O,Saldos!$C14) -> 0 | W14: =SUMIFS(wallet_records!$R:$R,wallet_records!$A:$A,"Nu Bank",wallet_records!$N:$N,Saldos!$B14,wallet_records!$O:$O,Saldos!$C14) -> 500000 | X14: =SUM(S14:W14) -> 2476935.1 | Z14: =L14-S14 -> -2012500 | AA14: =M14-T14 -> 450000 | AB14: =N14-U14 -> 1562500 | AC14: =O14-V14 -> 0 | AD14: =P14-W14 -> 0 | AE14: =SUM(Z14:AD14) -> 0
B15: 12 | C15: 2022 | D15: 2169341.6 | E15: 3666466 | F15: 12730085 | H15: 0 | I15: 1003052 | J15: =SUM(D15:I15) -> 19568945 | L15: =D15-D14 -> -1078326.3 | M15: =E15-E14 -> 469510 | N15: =F15-F14 -> 1630239 | O15: =H15-H14 -> 0 | P15: =I15-I14 -> 503052 | Q15: =J15-J14 -> 1524474.7 | S15: =SUMIFS(wallet_records!$R:$R,wallet_records!$A:$A,"Bancolombia",wallet_records!$N:$N,Saldos!$B15,wallet_records!$O:$O,Saldos!$C15) -> 971673.67 | T15: =SUMIFS(wallet_records!$R:$R,wallet_records!$A:$A,"Fidu Mantenimiento",wallet_records!$N:$N,Saldos!$B15,wallet_records!$O:$O,Saldos!$C15) -> 19510 | U15: =SUMIFS(wallet_records!$R:$R,wallet_records!$A:$A,"Fidu Impuestos",wallet_records!$N:$N,Saldos!$B15,wallet_records!$O:$O,Saldos!$C15) -> 30239 | V15: =SUMIFS(wallet_records!$R:$R,wallet_records!$A:$A,"Fiducuenta ARU",wallet_records!$N:$N,Saldos!$B15,wallet_records!$O:$O,Saldos!$C15) -> 0 | W15: =SUMIFS(wallet_records!$R:$R,wallet_records!$A:$A,"Nu Bank",wallet_records!$N:$N,Saldos!$B15,wallet_records!$O:$O,Saldos!$C15) -> 503052 | X15: =SUM(S15:W15) -> 1524474.7 | Z15: =L15-S15 -> -2050000 | AA15: =M15-T15 -> 450000 | AB15: =N15-U15 -> 1600000 | AC15: =O15-V15 -> 0 | AD15: =P15-W15 -> 0 | AE15: =SUM(Z15:AD15) -> 0
B16: 1 | C16: 2023 | D16: 1808563.3 | E16: 4113189 | F16: 14422866 | H16: 0 | I16: 1510362 | J16: =SUM(D16:I16) -> 21854980 | L16: =D16-D15 -> -360778.35 | M16: =E16-E15 -> 446723 | N16: =F16-F15 -> 1692781 | O16: =H16-H15 -> 0 | P16: =I16-I15 -> 507310 | Q16: =J16-J15 -> 2286035.6 | S16: =SUMIFS(wallet_records!$R:$R,wallet_records!$A:$A,"Bancolombia",wallet_records!$N:$N,Saldos!$B16,wallet_records!$O:$O,Saldos!$C16) -> 1689221.6 | T16: =SUMIFS(wallet_records!$R:$R,wallet_records!$A:$A,"Fidu Mantenimiento",wallet_records!$N:$N,Saldos!$B16,wallet_records!$O:$O,Saldos!$C16) -> -3277 | U16: =SUMIFS(wallet_records!$R:$R,wallet_records!$A:$A,"Fidu Impuestos",wallet_records!$N:$N,Saldos!$B16,wallet_records!$O:$O,Saldos!$C16) -> 92781 | V16: =SUMIFS(wallet_records!$R:$R,wallet_records!$A:$A,"Fiducuenta ARU",wallet_records!$N:$N,Saldos!$B16,wallet_records!$O:$O,Saldos!$C16) -> 0 | W16: =SUMIFS(wallet_records!$R:$R,wallet_records!$A:$A,"Nu Bank",wallet_records!$N:$N,Saldos!$B16,wallet_records!$O:$O,Saldos!$C16) -> 507310 | X16: =SUM(S16:W16) -> 2286035.6 | Z16: =L16-S16 -> -2050000 | AA16: =M16-T16 -> 450000 | AB16: =N16-U16 -> 1600000 | AC16: =O16-V16 -> 0 | AD16: =P16-W16 -> 0 | AE16: =SUM(Z16:AD16) -> 2.3283064e-10
B17: 2 | C17: 2023 | D17: 9770944 | E17: 4626180 | F17: 4982392 | H17: 0 | I17: 2646478 | J17: =SUM(D17:I17) -> 22025994 | L17: =D17-D16 -> 7962380.7 | M17: =E17-E16 -> 512991 | N17: =F17-F16 -> -9440474 | O17: =H17-H16 -> 0 | P17: =I17-I16 -> 1136116 | Q17: =J17-J16 -> 171013.73 | S17: =SUMIFS(wallet_records!$R:$R,wallet_records!$A:$A,"Bancolombia",wallet_records!$N:$N,Saldos!$B17,wallet_records!$O:$O,Saldos!$C17) -> 10012381 | T17: =SUMIFS(wallet_records!$R:$R,wallet_records!$A:$A,"Fidu Mantenimiento",wallet_records!$N:$N,Saldos!$B17,wallet_records!$O:$O,Saldos!$C17) -> 62991 | U17: =SUMIFS(wallet_records!$R:$R,wallet_records!$A:$A,"Fidu Impuestos",wallet_records!$N:$N,Saldos!$B17,wallet_records!$O:$O,Saldos!$C17) -> -11040474 | V17: =SUMIFS(wallet_records!$R:$R,wallet_records!$A:$A,"Fiducuenta ARU",wallet_records!$N:$N,Saldos!$B17,wallet_records!$O:$O,Saldos!$C17) -> 0 | W17: =SUMIFS(wallet_records!$R:$R,wallet_records!$A:$A,"Nu Bank",wallet_records!$N:$N,Saldos!$B17,wallet_records!$O:$O,Saldos!$C17) -> 1136116 | X17: =SUM(S17:W17) -> 171013.73 | Z17: =L17-S17 -> -2050000 | AA17: =M17-T17 -> 450000 | AB17: =N17-U17 -> 1600000 | AC17: =O17-V17 -> 0 | AD17: =P17-W17 -> 0 | AE17: =SUM(Z17:AD17) -> 0
... B51: 12 | C51: 2025 | D51: 4112943.4 | E51: 5263268 | F51: 24828736 | H51: 14238316 | I51: 32246510 | J51: =SUM(D51:I51) -> 80689773 | L51: =D51-D50 -> -1827410.7 | M51: =E51-E50 -> -849486 | N51: =F51-F50 -> 711176 | O51: =H51-H50 -> 1037491.3 | P51: =I51-I50 -> 5303061 | Q51: =J51-J50 -> 4374831.5 | S51: =SUMIFS(wallet_records!$R:$R,wallet_records!$A:$A,"Bancolombia",wallet_records!$N:$N,Saldos!$B51,wallet_records!$O:$O,Saldos!$C51) -> -1827410.7 | T51: =SUMIFS(wallet_records!$R:$R,wallet_records!$A:$A,"Fidu Mantenimiento",wallet_records!$N:$N,Saldos!$B51,wallet_records!$O:$O,Saldos!$C51) -> -849486 | U51: =SUMIFS(wallet_records!$R:$R,wallet_records!$A:$A,"Fidu Impuestos",wallet_records!$N:$N,Saldos!$B51,wallet_records!$O:$O,Saldos!$C51) -> 711176 | V51: =SUMIFS(wallet_records!$R:$R,wallet_records!$A:$A,"Fiducuenta ARU",wallet_records!$N:$N,Saldos!$B51,wallet_records!$O:$O,Saldos!$C51) -> 1037491.3 | W51: =SUMIFS(wallet_records!$R:$R,wallet_records!$A:$A,"Nu Bank",wallet_records!$N:$N,Saldos!$B51,wallet_records!$O:$O,Saldos!$C51) -> 5303061 | X51: =SUM(S51:W51) -> 4374831.5 | Z51: =L51-S51 -> 0 | AA51: =M51-T51 -> 0 | AB51: =N51-U51 -> 0 | AC51: =O51-V51 -> -1.1641532e-09 | AD51: =P51-W51 -> 0 | AE51: =SUM(Z51:AD51) -> -1.1641532e-09
B52: 1 | C52: 2026 | D52: 21288892 | E52: 5322606.4 | F52: 14349590 | G52: 14088855 | H52: 15321943 | I52: 0 | J52: =SUM(D52:H52) -> 70371886 | L52: =J52-J51 -> -10317887 | Z52: =SUM(Z6:Z51) -> -24387500 | AA52: =SUM(AA6:AA51) -> 6050000 | AB52: =SUM(AB6:AB51) -> 18937500 | AC52: =SUM(AC6:AC51) -> -4.6566129e-10 | AD52: =SUM(AD6:AD51) -> -1.0477379e-09 | AE52: =SUM(AE6:AE51) -> 600000
B53: 2 | C53: 2026 | D53: 11288892 | E53: 5322606.4 | F53: 14349590 | G53: 14088855 | H53: 16321943 | I53: 0 | J53: =SUM(D53:H53) -> 61371886
B54: 3 | C54: 2026 | I54: 0 | J54: =SUM(D54:H54) -> 0
B55: 4 | C55: 2026 | I55: 0 | J55: =SUM(D55:H55) -> 0
B56: 5 | C56: 2026 | I56: 0 | J56: =SUM(D56:H56) -> 0
B57: 6 | C57: 2026 | I57: 0 | J57: =SUM(D57:H57) -> 0
B58: 7 | C58: 2026 | I58: 0 | J58: =SUM(D58:H58) -> 0
B59: 8 | C59: 2026 | I59: 0 | J59: =SUM(D59:H59) -> 0
B60: 9 | C60: 2026 | I60: 0 | J60: =SUM(D60:H60) -> 0
B61: 10 | C61: 2026 | I61: 0 | J61: =SUM(D61:H61) -> 0
B62: 11 | C62: 2026 | I62: 0 | J62: =SUM(D62:H62) -> 0
B63: 12 | C63: 2026 | I63: 0 | J63: =SUM(D63:H63) -> 0

Sheet Presupuesto
B1: 156000
B2: 590302.59
B3: 317043.1 | D3: 46023 | F3: 46054 | H3: 46082 | J3: 46113 | L3: 46143 | N3: 46174 | P3: 46204 | R3: 46235 | T3: 46266 | V3: 46296 | X3: 46327 | Z3: 46357 | AB3: Acumulado 2026 | AE3: 46388 | AG3: 46419 | AI3: 46447 | AK3: 46478 | AM3: 46508 | AO3: 46539 | AQ3: 46569 | AS3: 46600 | AU3: 46631 | AW3: 46661 | AY3: 46692 | BA3: 46722 | BC3: Acumulado 2027
C5: Yari | D5: =E5/$E$11 -> 0.18264304 | E5: =Activos!$K$131 -> 1734150 | F5: =G5/$G$11 -> 0.18264304 | G5: =Activos!$K$131 -> 1734150 | H5: =I5/$I$11 -> 0.18264304 | I5: =Activos!$K$131 -> 1734150 | J5: =K5/$K$11 -> 0.18264304 | K5: =Activos!$K$131 -> 1734150 | L5: =M5/$M$11 -> 0.18264304 | M5: =Activos!$K$131 -> 1734150 | N5: =O5/$O$11 -> 0.17428205 | O5: =Activos!$K$131 -> 1734150 | P5: =Q5/$Q$11 -> 0.16901018 | Q5: =Activos!$K$131 -> 1734150 | R5: =S5/$S$11 -> 0.16827331 | S5: =Activos!$K$131 -> 1734150 | T5: =U5/$U$11 -> 0.16827331 | U5: =Activos!$K$131 -> 1734150 | V5: =W5/$W$11 -> 0.16827331 | W5: =Activos!$K$131 -> 1734150 | X5: =Y5/$Y$11 -> 0.16827331 | Y5: =Activos!$K$131 -> 1734150 | Z5: =AA5/$AA$11 -> 0.16685717 | AA5: =Activos!$K$131 -> 1734150 | AB5: =AC5/$AC$11 -> 0.17443272 | AC5: =E5+G5+I5+K5+M5+O5+Q5+S5+U5+W5+Y5+AA5 -> 20809800 | AE5: =AF5/$AF$11 -> 0.18391941 | AF5: =Activos!$L$131 -> 1838199 | AG5: =AH5/$AH$11 -> 0.18391941 | AH5: =Activos!$L$131 -> 1838199 | AI5: =AJ5/$AJ$11 -> 0.18391941 | AJ5: =Activos!$L$131 -> 1838199 | AK5: =AL5/$AL$11 -> 0.18391941 | AL5: =Activos!$L$131 -> 1838199 | AM5: =AN5/$AN$11 -> 0.18391941 | AN5: =Activos!$L$131 -> 1838199 | AO5: =AP5/$AP$11 -> 0.18217232 | AP5: =Activos!$L$131 -> 1838199 | AQ5: =AR5/$AR$11 -> 0.17866125 | AR5: =Activos!$L$131 -> 1838199 | AS5: =AT5/$AT$11 -> 0.17770172 | AT5: =Activos!$L$131 -> 1838199 | AU5: =AV5/$AV$11 -> 0.17770172 | AV5: =Activos!$L$131 -> 1838199 | AW5: =AX5/$AX$11 -> 0.17770172 | AX5: =Activos!$L$131 -> 1838199 | AY5: =AZ5/$AZ$11 -> 0.17770172 | AZ5: =Activos!$L$131 -> 1838199 | BA5: =BB5/$BB$11 -> 0.1753342 | BB5: =Activos!$L$131 -> 1838199 | BC5: =BD5/$BD$11 -> 0.18049092 | BD5: =AF5+AH5+AJ5+AL5+AN5+AP5+AR5+AT5+AV5+AX5+AZ5+BB5 -> 22058388
C6: Belén | D6: =E6/$E$11 -> 0.33119355 | E6: =Activos!$J$112 -> 3144600 | F6: =G6/$G$11 -> 0.33119355 | G6: =Activos!$J$112 -> 3144600 | H6: =I6/$I$11 -> 0.33119355 | I6: =Activos!$J$112 -> 3144600 | J6: =K6/$K$11 -> 0.33119355 | K6: =Activos!$J$112 -> 3144600 | L6: =M6/$M$11 -> 0.33119355 | M6: =Activos!$J$112 -> 3144600 | N6: =O6/$O$11 -> 0.31603226 | O6: =Activos!$J$112 -> 3144600 | P6: =Q6/$Q$11 -> 0.32210267 | Q6: =Activos!$K$112 -> 3304974.6 | R6: =S6/$S$11 -> 0.32069834 | S6: =Activos!$K$112 -> 3304974.6 | T6: =U6/$U$11 -> 0.32069834 | U6: =Activos!$K$112 -> 3304974.6 | V6: =W6/$W$11 -> 0.32069834 | W6: =Activos!$K$112 -> 3304974.6 | X6: =Y6/$Y$11 -> 0.32069834 | Y6: =Activos!$K$112 -> 3304974.6 | Z6: =AA6/$AA$11 -> 0.31799943 | AA6: =Activos!$K$112 -> 3304974.6 | AB6: =AC6/$AC$11 -> 0.32437125 | AC6: =E6+G6+I6+K6+M6+O6+Q6+S6+U6+W6+Y6+AA6 -> 38697448 | AE6: =AF6/$AF$11 -> 0.33067637 | AF6: =Activos!$K$112 -> 3304974.6 | AG6: =AH6/$AH$11 -> 0.33067637 | AH6: =Activos!$K$112 -> 3304974.6 | AI6: =AJ6/$AJ$11 -> 0.33067637 | AJ6: =Activos!$K$112 -> 3304974.6 | AK6: =AL6/$AL$11 -> 0.33067637 | AL6: =Activos!$K$112 -> 3304974.6 | AM6: =AN6/$AN$11 -> 0.33067637 | AN6: =Activos!$K$112 -> 3304974.6 | AO6: =AP6/$AP$11 -> 0.32753521 | AP6: =Activos!$K$112 -> 3304974.6 | AQ6: =AR6/$AR$11 -> 0.34049585 | AR6: =Activos!$L$112 -> 3503273.1 | AS6: =AT6/$AT$11 -> 0.33866716 | AT6: =Activos!$L$112 -> 3503273.1 | AU6: =AV6/$AV$11 -> 0.33866716 | AV6: =Activos!$L$112 -> 3503273.1 | AW6: =AX6/$AX$11 -> 0.33866716 | AX6: =Activos!$L$112 -> 3503273.1 | AY6: =AZ6/$AZ$11 -> 0.33866716 | AZ6: =Activos!$L$112 -> 3503273.1 | BA6: =BB6/$BB$11 -> 0.3341551 | BB6: =Activos!$L$112 -> 3503273.1 | BC6: =BD6/$BD$11 -> 0.33424752 | BD6: =AF6+AH6+AJ6+AL6+AN6+AP6+AR6+AT6+AV6+AX6+AZ6+BB6 -> 40849486
C7: Ocarinas | D7: =E7/$E$11 -> 0.16008847 | E7: =Activos!$J$36 -> 1520000 | F7: =G7/$G$11 -> 0.16008847 | G7: =Activos!$J$36 -> 1520000 | H7: =I7/$I$11 -> 0.16008847 | I7: =Activos!$J$36 -> 1520000 | J7: =K7/$K$11 -> 0.16008847 | K7: =Activos!$J$36 -> 1520000 | L7: =M7/$M$11 -> 0.16008847 | M7: =Activos!$J$36 -> 1520000 | N7: =O7/$O$11 -> 0.19597498 | O7: 1950000 | P7: =Q7/$Q$11 -> 0.2046659 | Q7: 2100000 | R7: =S7/$S$11 -> 0.20377358 | S7: 2100000 | T7: =U7/$U$11 -> 0.20377358 | U7: 2100000 | V7: =W7/$W$11 -> 0.20377358 | W7: 2100000 | X7: =Y7/$Y$11 -> 0.20377358 | Y7: 2100000 | Z7: =AA7/$AA$11 -> 0.20205868 | AA7: 2100000 | AB7: =AC7/$AC$11 -> 0.18566659 | AC7: =E7+G7+I7+K7+M7+O7+Q7+S7+U7+W7+Y7+AA7 -> 22150000 | AE7: =AF7/$AF$11 -> 0.15983848 | AF7: =Activos!$K$36 -> 1597520 | AG7: =AH7/$AH$11 -> 0.15983848 | AH7: =Activos!$K$36 -> 1597520 | AI7: =AJ7/$AJ$11 -> 0.15983848 | AJ7: =Activos!$K$36 -> 1597520 | AK7: =AL7/$AL$11 -> 0.15983848 | AL7: =Activos!$K$36 -> 1597520 | AM7: =AN7/$AN$11 -> 0.15983848 | AN7: =Activos!$K$36 -> 1597520 | AO7: =AP7/$AP$11 -> 0.16781935 | AP7: =Activos!$L$36 -> 1693371.2 | AQ7: =AR7/$AR$11 -> 0.16458491 | AR7: =Activos!$L$36 -> 1693371.2 | AS7: =AT7/$AT$11 -> 0.16370098 | AT7: =Activos!$L$36 -> 1693371.2 | AU7: =AV7/$AV$11 -> 0.16370098 | AV7: =Activos!$L$36 -> 1693371.2 | AW7: =AX7/$AX$11 -> 0.16370098 | AX7: =Activos!$L$36 -> 1693371.2 | AY7: =AZ7/$AZ$11 -> 0.16370098 | AZ7: =Activos!$L$36 -> 1693371.2 | BA7: =BB7/$BB$11 -> 0.16151999 | BB7: =Activos!$L$36 -> 1693371.2 | BC7: =BD7/$BD$11 -> 0.16234895 | BD7: =AF7+AH7+AJ7+AL7+AN7+AP7+AR7+AT7+AV7+AX7+AZ7+BB7 -> 19841198
C8: Pedregal | D8: =E8/$E$11 -> 0.052660681 | E8: =Activos!$J$93 -> 500000 | F8: =G8/$G$11 -> 0.052660681 | G8: =Activos!$J$93 -> 500000 | H8: =I8/$I$11 -> 0.052660681 | I8: =Activos!$J$93 -> 500000 | J8: =K8/$K$11 -> 0.052660681 | K8: =Activos!$J$93 -> 500000 | L8: =M8/$M$11 -> 0.052660681 | M8: =Activos!$J$93 -> 500000 | N8: =O8/$O$11 -> 0.052812743 | O8: =Activos!$K$93 -> 525500 | P8: =Q8/$Q$11 -> 0.051215206 | Q8: 525500 | R8: =S8/$S$11 -> 0.050991914 | S8: 525500 | T8: =U8/$U$11 -> 0.050991914 | U8: 525500 | V8: =W8/$W$11 -> 0.050991914 | W8: 525500 | X8: =Y8/$Y$11 -> 0.050991914 | Y8: 525500 | Z8: =AA8/$AA$11 -> 0.050562779 | AA8: 525500 | AB8: =AC8/$AC$11 -> 0.051789664 | AC8: =E8+G8+I8+K8+M8+O8+Q8+S8+U8+W8+Y8+AA8 -> 6178500 | AE8: =AF8/$AF$11 -> 0.052578447 | AF8: =Activos!$K$93 -> 525500 | AG8: =AH8/$AH$11 -> 0.052578447 | AH8: =Activos!$K$93 -> 525500 | AI8: =AJ8/$AJ$11 -> 0.052578447 | AJ8: =Activos!$K$93 -> 525500 | AK8: =AL8/$AL$11 -> 0.052578447 | AL8: =Activos!$K$93 -> 525500 | AM8: =AN8/$AN$11 -> 0.052578447 | AN8: =Activos!$K$93 -> 525500 | AO8: =AP8/$AP$11 -> 0.052078993 | AP8: =Activos!$K$93 -> 525500 | AQ8: =AR8/$AR$11 -> 0.051075257 | AR8: =Activos!$K$93 -> 525500 | AS8: =AT8/$AT$11 -> 0.050800948 | AT8: =Activos!$K$93 -> 525500 | AU8: =AV8/$AV$11 -> 0.050800948 | AV8: =Activos!$K$93 -> 525500 | AW8: =AX8/$AX$11 -> 0.050800948 | AX8: =Activos!$K$93 -> 525500 | AY8: =AZ8/$AZ$11 -> 0.050800948 | AZ8: =Activos!$K$93 -> 525500 | BA8: =BB8/$BB$11 -> 0.053131575 | BB8: =Activos!$L$93 -> 557030 | BC8: =BD8/$BD$11 -> 0.051856311 | BD8: =AF8+AH8+AJ8+AL8+AN8+AP8+AR8+AT8+AV8+AX8+AZ8+BB8 -> 6337530
C9: Rivera del Valle | D9: =E9/$E$11 -> 0.18062614 | E9: =Activos!$J$55 -> 1715000 | F9: =G9/$G$11 -> 0.18062614 | G9: =Activos!$J$55 -> 1715000 | H9: =I9/$I$11 -> 0.18062614 | I9: =Activos!$J$55 -> 1715000 | J9: =K9/$K$11 -> 0.18062614 | K9: =Activos!$J$55 -> 1715000 | L9: =M9/$M$11 -> 0.18062614 | M9: =Activos!$J$55 -> 1715000 | N9: =O9/$O$11 -> 0.17235748 | O9: =Activos!$J$55 -> 1715000 | P9: =Q9/$Q$11 -> 0.16714382 | Q9: =Activos!$J$55 -> 1715000 | R9: =S9/$S$11 -> 0.16641509 | S9: =Activos!$J$55 -> 1715000 | T9: =U9/$U$11 -> 0.16641509 | U9: =Activos!$J$55 -> 1715000 | V9: =W9/$W$11 -> 0.16641509 | W9: =Activos!$J$55 -> 1715000 | X9: =Y9/$Y$11 -> 0.16641509 | Y9: =Activos!$J$55 -> 1715000 | Z9: =AA9/$AA$11 -> 0.17343033 | AA9: =Activos!$K$55 -> 1802465 | AB9: =AC9/$AC$11 -> 0.17323963 | AC9: =E9+G9+I9+K9+M9+O9+Q9+S9+U9+W9+Y9+AA9 -> 20667465 | AE9: =AF9/$AF$11 -> 0.18034407 | AF9: =Activos!$K$55 -> 1802465 | AG9: =AH9/$AH$11 -> 0.18034407 | AH9: =Activos!$K$55 -> 1802465 | AI9: =AJ9/$AJ$11 -> 0.18034407 | AJ9: =Activos!$K$55 -> 1802465 | AK9: =AL9/$AL$11 -> 0.18034407 | AL9: =Activos!$K$55 -> 1802465 | AM9: =AN9/$AN$11 -> 0.18034407 | AN9: =Activos!$K$55 -> 1802465 | AO9: =AP9/$AP$11 -> 0.17863095 | AP9: =Activos!$K$55 -> 1802465 | AQ9: =AR9/$AR$11 -> 0.17518813 | AR9: =Activos!$K$55 -> 1802465 | AS9: =AT9/$AT$11 -> 0.17424725 | AT9: =Activos!$K$55 -> 1802465 | AU9: =AV9/$AV$11 -> 0.17424725 | AV9: =Activos!$K$55 -> 1802465 | AW9: =AX9/$AX$11 -> 0.17424725 | AX9: =Activos!$K$55 -> 1802465 | AY9: =AZ9/$AZ$11 -> 0.17424725 | AZ9: =Activos!$K$55 -> 1802465 | BA9: =BB9/$BB$11 -> 0.1822413 | BB9: =Activos!$L$55 -> 1910612.9 | BC9: =BD9/$BD$11 -> 0.17786715 | BD9: =AF9+AH9+AJ9+AL9+AN9+AP9+AR9+AT9+AV9+AX9+AZ9+BB9 -> 21737728
C10: La Ceja | D10: =E10/$E$11 -> 0.09278812 | E10: =Activos!$J$74 -> 881000 | F10: =G10/$G$11 -> 0.09278812 | G10: =Activos!$J$74 -> 881000 | H10: =I10/$I$11 -> 0.09278812 | I10: =Activos!$J$74 -> 881000 | J10: =K10/$K$11 -> 0.09278812 | K10: =Activos!$J$74 -> 881000 | L10: =M10/$M$11 -> 0.09278812 | M10: =Activos!$J$74 -> 881000 | N10: =O10/$O$11 -> 0.088540489 | O10: =Activos!$J$74 -> 881000 | P10: =Q10/$Q$11 -> 0.085862219 | Q10: =Activos!$J$74 -> 881000 | R10: =S10/$S$11 -> 0.089847752 | S10: =Activos!$K$74 -> 925931 | T10: =U10/$U$11 -> 0.089847752 | U10: =Activos!$K$74 -> 925931 | V10: =W10/$W$11 -> 0.089847752 | W10: =Activos!$K$74 -> 925931 | X10: =Y10/$Y$11 -> 0.089847752 | Y10: =Activos!$K$74 -> 925931 | Z10: =AA10/$AA$11 -> 0.089091616 | AA10: =Activos!$K$74 -> 925931 | AB10: =AC10/$AC$11 -> 0.090500142 | AC10: =E10+G10+I10+K10+M10+O10+Q10+S10+U10+W10+Y10+AA10 -> 10796655 | AE10: =AF10/$AF$11 -> 0.092643224 | AF10: =Activos!$K$74 -> 925931 | AG10: =AH10/$AH$11 -> 0.092643224 | AH10: =Activos!$K$74 -> 925931 | AI10: =AJ10/$AJ$11 -> 0.092643224 | AJ10: =Activos!$K$74 -> 925931 | AK10: =AL10/$AL$11 -> 0.092643224 | AL10: =Activos!$K$74 -> 925931 | AM10: =AN10/$AN$11 -> 0.092643224 | AN10: =Activos!$K$74 -> 925931 | AO10: =AP10/$AP$11 -> 0.091763186 | AP10: =Activos!$K$74 -> 925931 | AQ10: =AR10/$AR$11 -> 0.089994602 | AR10: =Activos!$K$74 -> 925931 | AS10: =AT10/$AT$11 -> 0.094881947 | AT10: =Activos!$L$74 -> 981486.86 | AU10: =AV10/$AV$11 -> 0.094881947 | AV10: =Activos!$L$74 -> 981486.86 | AW10: =AX10/$AX$11 -> 0.094881947 | AX10: =Activos!$L$74 -> 981486.86 | AY10: =AZ10/$AZ$11 -> 0.094881947 | AZ10: =Activos!$L$74 -> 981486.86 | BA10: =BB10/$BB$11 -> 0.093617835 | BB10: =Activos!$L$74 -> 981486.86 | BC10: =BD10/$BD$11 -> 0.093189146 | BD10: =AF10+AH10+AJ10+AL10+AN10+AP10+AR10+AT10+AV10+AX10+AZ10+BB10 -> 11388951
B11: ARRIENDOS | D11: =SUM(D5:D10) -> 1 | E11: =SUM(E5:E10) -> 9494750 | F11: =SUM(F5:F10) -> 1 | G11: =SUM(G5:G10) -> 9494750 | H11: =SUM(H5:H10) -> 1 | I11: =SUM(I5:I10) -> 9494750 | J11: =SUM(J5:J10) -> 1 | K11: =SUM(K5:K10) -> 9494750 | ... AB11: =SUM(AB5:AB10) -> 1 | AC11: =E11+G11+I11+K11+M11+O11+Q11+S11+U11+W11+Y11+AA11 -> 1.1929987e+08 | AE11: =SUM(AE5:AE10) -> 1 | AF11: =SUM(AF5:AF10) -> 9994589.6 | AG11: =SUM(AG5:AG10) -> 1 | AH11: =SUM(AH5:AH10) -> 9994589.6 | AI11: =SUM(AI5:AI10) -> 1 | AJ11: =SUM(AJ5:AJ10) -> 9994589.6 | AK11: =SUM(AK5:AK10) -> 1 | AL11: =SUM(AL5:AL10) -> 9994589.6 | ... BC11: =SUM(BC5:BC10) -> 1 | BD11: =AF11+AH11+AJ11+AL11+AN11+AP11+AR11+AT11+AV11+AX11+AZ11+BB11 -> 1.2221328e+08
B13: =Activos!K135 -> 2693969.5 | C13: Yari | D13: =E13/E5 -> 0.12945677 | E13: =$B13/12 -> 224497.46 | F13: =G13/G5 -> 0.12945677 | G13: =$B13/12 -> 224497.46 | H13: =I13/I5 -> 0.12945677 | I13: =$B13/12 -> 224497.46 | J13: =K13/K5 -> 0.12945677 | K13: =$B13/12 -> 224497.46 | L13: =M13/M5 -> 0.12945677 | M13: =$B13/12 -> 224497.46 | N13: =O13/O5 -> 0.12945677 | O13: =$B13/12 -> 224497.46 | P13: =Q13/Q5 -> 0.12945677 | Q13: =$B13/12 -> 224497.46 | R13: =S13/S5 -> 0.12945677 | S13: =$B13/12 -> 224497.46 | T13: =U13/U5 -> 0.12945677 | U13: =$B13/12 -> 224497.46 | V13: =W13/W5 -> 0.12945677 | W13: =$B13/12 -> 224497.46 | X13: =Y13/Y5 -> 0.12945677 | Y13: =$B13/12 -> 224497.46 | Z13: =AA13/AA5 -> 0.12945677 | AA13: =$B13/12 -> 224497.46 | AB13: =AC13/AC5 -> 0.12945677 | AC13: =E13+G13+I13+K13+M13+O13+Q13+S13+U13+W13+Y13+AA13 -> 2693969.5 | AD13: =Activos!L135 -> 3098065 | AE13: =AF13/AF5 -> 0.14044838 | AF13: =$AD13/12 -> 258172.08 | AG13: =AH13/AH5 -> 0.14044838 | AH13: =$AD13/12 -> 258172.08 | AI13: =AJ13/AJ5 -> 0.14044838 | AJ13: =$AD13/12 -> 258172.08 | AK13: =AL13/AL5 -> 0.14044838 | AL13: =$AD13/12 -> 258172.08 | AM13: =AN13/AN5 -> 0.14044838 | AN13: =$AD13/12 -> 258172.08 | AO13: =AP13/AP5 -> 0.14044838 | AP13: =$AD13/12 -> 258172.08 | AQ13: =AR13/AR5 -> 0.14044838 | AR13: =$AD13/12 -> 258172.08 | AS13: =AT13/AT5 -> 0.14044838 | AT13: =$AD13/12 -> 258172.08 | AU13: =AV13/AV5 -> 0.14044838 | AV13: =$AD13/12 -> 258172.08 | AW13: =AX13/AX5 -> 0.14044838 | AX13: =$AD13/12 -> 258172.08 | AY13: =AZ13/AZ5 -> 0.14044838 | AZ13: =$AD13/12 -> 258172.08 | BA13: =BB13/BB5 -> 0.14044838 | BB13: =$AD13/12 -> 258172.08 | BC13: =BD13/BD5 -> 0.14044838 | BD13: =AF13+AH13+AJ13+AL13+AN13+AP13+AR13+AT13+AV13+AX13+AZ13+BB13 -> 3098065
B14: =Activos!K116 -> 4829800.9 | C14: Belén | D14: =E14/E6 -> 0.12799193 | E14: =$B14/12 -> 402483.41 | F14: =G14/G6 -> 0.12799193 | G14: =$B14/12 -> 402483.41 | H14: =I14/I6 -> 0.12799193 | I14: =$B14/12 -> 402483.41 | J14: =K14/K6 -> 0.12799193 | K14: =$B14/12 -> 402483.41 | L14: =M14/M6 -> 0.12799193 | M14: =$B14/12 -> 402483.41 | N14: =O14/O6 -> 0.12799193 | O14: =$B14/12 -> 402483.41 | P14: =Q14/Q6 -> 0.12178109 | Q14: =$B14/12 -> 402483.41 | R14: =S14/S6 -> 0.12178109 | S14: =$B14/12 -> 402483.41 | T14: =U14/U6 -> 0.12178109 | U14: =$B14/12 -> 402483.41 | V14: =W14/W6 -> 0.12178109 | W14: =$B14/12 -> 402483.41 | X14: =Y14/Y6 -> 0.12178109 | Y14: =$B14/12 -> 402483.41 | Z14: =AA14/AA6 -> 0.12178109 | AA14: =$B14/12 -> 402483.41 | AB14: =AC14/AC6 -> 0.12480929 | AC14: =E14+G14+I14+K14+M14+O14+Q14+S14+U14+W14+Y14+AA14 -> 4829800.9 | AD14: =Activos!L116 -> 5554271.1 | AE14: =AF14/AF6 -> 0.14004825 | AF14: =$AD14/12 -> 462855.92 | AG14: =AH14/AH6 -> 0.14004825 | AH14: =$AD14/12 -> 462855.92 | AI14: =AJ14/AJ6 -> 0.14004825 | AJ14: =$AD14/12 -> 462855.92 | AK14: =AL14/AL6 -> 0.14004825 | AL14: =$AD14/12 -> 462855.92 | AM14: =AN14/AN6 -> 0.14004825 | AN14: =$AD14/12 -> 462855.92 | AO14: =AP14/AP6 -> 0.14004825 | AP14: =$AD14/12 -> 462855.92 | AQ14: =AR14/AR6 -> 0.13212099 | AR14: =$AD14/12 -> 462855.92 | AS14: =AT14/AT6 -> 0.13212099 | AT14: =$AD14/12 -> 462855.92 | AU14: =AV14/AV6 -> 0.13212099 | AV14: =$AD14/12 -> 462855.92 | AW14: =AX14/AX6 -> 0.13212099 | AX14: =$AD14/12 -> 462855.92 | AY14: =AZ14/AZ6 -> 0.13212099 | AZ14: =$AD14/12 -> 462855.92 | BA14: =BB14/BB6 -> 0.13212099 | BB14: =$AD14/12 -> 462855.92 | BC14: =BD14/BD6 -> 0.13596918 | BD14: =AF14+AH14+AJ14+AL14+AN14+AP14+AR14+AT14+AV14+AX14+AZ14+BB14 -> 5554271.1
B15: =Activos!K40 -> 1995686.7 | C15: Ocarinas | D15: =E15/E7 -> 0.10941265 | E15: =$B15/12 -> 166307.23 | F15: =G15/G7 -> 0.10941265 | G15: =$B15/12 -> 166307.23 | H15: =I15/I7 -> 0.10941265 | I15: =$B15/12 -> 166307.23 | J15: =K15/K7 -> 0.10941265 | K15: =$B15/12 -> 166307.23 | L15: =M15/M7 -> 0.10941265 | M15: =$B15/12 -> 166307.23 | N15: =O15/O7 -> 0.085285758 | O15: =$B15/12 -> 166307.23 | P15: =Q15/Q7 -> 0.079193918 | Q15: =$B15/12 -> 166307.23 | R15: =S15/S7 -> 0.079193918 | S15: =$B15/12 -> 166307.23 | T15: =U15/U7 -> 0.079193918 | U15: =$B15/12 -> 166307.23 | V15: =W15/W7 -> 0.079193918 | W15: =$B15/12 -> 166307.23 | X15: =Y15/Y7 -> 0.079193918 | Y15: =$B15/12 -> 166307.23 | Z15: =AA15/AA7 -> 0.079193918 | AA15: =$B15/12 -> 166307.23 | AB15: =AC15/AC7 -> 0.090098724 | AC15: =E15+G15+I15+K15+M15+O15+Q15+S15+U15+W15+Y15+AA15 -> 1995686.7 | AD15: =Activos!L40 -> 2295039.7 | AE15: =AF15/AF7 -> 0.11971888 | AF15: =$AD15/12 -> 191253.31 | AG15: =AH15/AH7 -> 0.11971888 | AH15: =$AD15/12 -> 191253.31 | AI15: =AJ15/AJ7 -> 0.11971888 | AJ15: =$AD15/12 -> 191253.31 | AK15: =AL15/AL7 -> 0.11971888 | AL15: =$AD15/12 -> 191253.31 | AM15: =AN15/AN7 -> 0.11971888 | AN15: =$AD15/12 -> 191253.31 | AO15: =AP15/AP7 -> 0.11294234 | AP15: =$AD15/12 -> 191253.31 | AQ15: =AR15/AR7 -> 0.11294234 | AR15: =$AD15/12 -> 191253.31 | AS15: =AT15/AT7 -> 0.11294234 | AT15: =$AD15/12 -> 191253.31 | AU15: =AV15/AV7 -> 0.11294234 | AV15: =$AD15/12 -> 191253.31 | AW15: =AX15/AX7 -> 0.11294234 | AX15: =$AD15/12 -> 191253.31 | AY15: =AZ15/AZ7 -> 0.11294234 | AZ15: =$AD15/12 -> 191253.31 | BA15: =BB15/BB7 -> 0.11294234 | BB15: =$AD15/12 -> 191253.31 | BC15: =BD15/BD7 -> 0.11567042 | BD15: =AF15+AH15+AJ15+AL15+AN15+AP15+AR15+AT15+AV15+AX15+AZ15+BB15 -> 2295039.7
B16: =Activos!K97 -> 391504.32 | C16: Pedregal | D16: =E16/E8 -> 0.065250719 | E16: =$B16/12 -> 32625.36 | F16: =G16/G8 -> 0.065250719 | G16: =$B16/12 -> 32625.36 | H16: =I16/I8 -> 0.065250719 | I16: =$B16/12 -> 32625.36 | J16: =K16/K8 -> 0.065250719 | K16: =$B16/12 -> 32625.36 | L16: =M16/M8 -> 0.065250719 | M16: =$B16/12 -> 32625.36 | N16: =O16/O8 -> 0.062084414 | O16: =$B16/12 -> 32625.36 | P16: =Q16/Q8 -> 0.062084414 | Q16: =$B16/12 -> 32625.36 | R16: =S16/S8 -> 0.062084414 | S16: =$B16/12 -> 32625.36 | T16: =U16/U8 -> 0.062084414 | U16: =$B16/12 -> 32625.36 | V16: =W16/W8 -> 0.062084414 | W16: =$B16/12 -> 32625.36 | X16: =Y16/Y8 -> 0.062084414 | Y16: =$B16/12 -> 32625.36 | Z16: =AA16/AA8 -> 0.062084414 | AA16: =$B16/12 -> 32625.36 | AB16: =AC16/AC8 -> 0.063365593 | AC16: =E16+G16+I16+K16+M16+O16+Q16+S16+U16+W16+Y16+AA16 -> 391504.32 | AD16: =Activos!L97 -> 450229.96 | AE16: =AF16/AF8 -> 0.071397076 | AF16: =$AD16/12 -> 37519.164 | AG16: =AH16/AH8 -> 0.071397076 | AH16: =$AD16/12 -> 37519.164 | AI16: =AJ16/AJ8 -> 0.071397076 | AJ16: =$AD16/12 -> 37519.164 | AK16: =AL16/AL8 -> 0.071397076 | AL16: =$AD16/12 -> 37519.164 | AM16: =AN16/AN8 -> 0.071397076 | AN16: =$AD16/12 -> 37519.164 | AO16: =AP16/AP8 -> 0.071397076 | AP16: =$AD16/12 -> 37519.164 | AQ16: =AR16/AR8 -> 0.071397076 | AR16: =$AD16/12 -> 37519.164 | AS16: =AT16/AT8 -> 0.071397076 | AT16: =$AD16/12 -> 37519.164 | AU16: =AV16/AV8 -> 0.071397076 | AV16: =$AD16/12 -> 37519.164 | AW16: =AX16/AX8 -> 0.071397076 | AX16: =$AD16/12 -> 37519.164 | AY16: =AZ16/AZ8 -> 0.071397076 | AZ16: =$AD16/12 -> 37519.164 | BA16: =BB16/BB8 -> 0.067355732 | BB16: =$AD16/12 -> 37519.164 | BC16: =BD16/BD8 -> 0.071041867 | BD16: =AF16+AH16+AJ16+AL16+AN16+AP16+AR16+AT16+AV16+AX16+AZ16+BB16 -> 450229.96
B17: =Activos!K59 -> 1448475 | C17: Rivera del Valle | D17: =E17/E9 -> 0.070382655 | E17: =$B17/12 -> 120706.25 | F17: =G17/G9 -> 0.070382655 | G17: =$B17/12 -> 120706.25 | H17: =I17/I9 -> 0.070382655 | I17: =$B17/12 -> 120706.25 | J17: =K17/K9 -> 0.070382655 | K17: =$B17/12 -> 120706.25 | L17: =M17/M9 -> 0.070382655 | M17: =$B17/12 -> 120706.25 | N17: =O17/O9 -> 0.070382655 | O17: =$B17/12 -> 120706.25 | P17: =Q17/Q9 -> 0.070382655 | Q17: =$B17/12 -> 120706.25 | R17: =S17/S9 -> 0.070382655 | S17: =$B17/12 -> 120706.25 | T17: =U17/U9 -> 0.070382655 | U17: =$B17/12 -> 120706.25 | V17: =W17/W9 -> 0.070382655 | W17: =$B17/12 -> 120706.25 | X17: =Y17/Y9 -> 0.070382655 | Y17: =$B17/12 -> 120706.25 | Z17: =AA17/AA9 -> 0.066967322 | AA17: =$B17/12 -> 120706.25 | AB17: =AC17/AC9 -> 0.070084795 | AC17: =E17+G17+I17+K17+M17+O17+Q17+S17+U17+W17+Y17+AA17 -> 1448475 | AD17: =Activos!L59 -> 1665746.3 | AE17: =AF17/AF9 -> 0.07701242 | AF17: =$AD17/12 -> 138812.19 | AG17: =AH17/AH9 -> 0.07701242 | AH17: =$AD17/12 -> 138812.19 | AI17: =AJ17/AJ9 -> 0.07701242 | AJ17: =$AD17/12 -> 138812.19 | AK17: =AL17/AL9 -> 0.07701242 | AL17: =$AD17/12 -> 138812.19 | AM17: =AN17/AN9 -> 0.07701242 | AN17: =$AD17/12 -> 138812.19 | AO17: =AP17/AP9 -> 0.07701242 | AP17: =$AD17/12 -> 138812.19 | AQ17: =AR17/AR9 -> 0.07701242 | AR17: =$AD17/12 -> 138812.19 | AS17: =AT17/AT9 -> 0.07701242 | AT17: =$AD17/12 -> 138812.19 | AU17: =AV17/AV9 -> 0.07701242 | AV17: =$AD17/12 -> 138812.19 | AW17: =AX17/AX9 -> 0.07701242 | AX17: =$AD17/12 -> 138812.19 | AY17: =AZ17/AZ9 -> 0.07701242 | AZ17: =$AD17/12 -> 138812.19 | BA17: =BB17/BB9 -> 0.072653227 | BB17: =$AD17/12 -> 138812.19 | BC17: =BD17/BD9 -> 0.076629274 | BD17: =AF17+AH17+AJ17+AL17+AN17+AP17+AR17+AT17+AV17+AX17+AZ17+BB17 -> 1665746.3
B18: =Activos!K78 -> 946963.08 | C18: La Ceja | D18: =E18/E10 -> 0.089572747 | E18: =$B18/12 -> 78913.59 | F18: =G18/G10 -> 0.089572747 | G18: =$B18/12 -> 78913.59 | H18: =I18/I10 -> 0.089572747 | I18: =$B18/12 -> 78913.59 | J18: =K18/K10 -> 0.089572747 | K18: =$B18/12 -> 78913.59 | L18: =M18/M10 -> 0.089572747 | M18: =$B18/12 -> 78913.59 | N18: =O18/O10 -> 0.089572747 | O18: =$B18/12 -> 78913.59 | P18: =Q18/Q10 -> 0.089572747 | Q18: =$B18/12 -> 78913.59 | R18: =S18/S10 -> 0.085226211 | S18: =$B18/12 -> 78913.59 | T18: =U18/U10 -> 0.085226211 | U18: =$B18/12 -> 78913.59 | V18: =W18/W10 -> 0.085226211 | W18: =$B18/12 -> 78913.59 | X18: =Y18/Y10 -> 0.085226211 | Y18: =$B18/12 -> 78913.59 | Z18: =AA18/AA10 -> 0.085226211 | AA18: =$B18/12 -> 78913.59 | AB18: =AC18/AC10 -> 0.087708932 | AC18: =E18+G18+I18+K18+M18+O18+Q18+S18+U18+W18+Y18+AA18 -> 946963.08 | AD18: =Activos!L78 -> 1089007.5 | AE18: =AF18/AF10 -> 0.098010142 | AF18: =$AD18/12 -> 90750.629 | AG18: =AH18/AH10 -> 0.098010142 | AH18: =$AD18/12 -> 90750.629 | AI18: =AJ18/AJ10 -> 0.098010142 | AJ18: =$AD18/12 -> 90750.629 | AK18: =AL18/AL10 -> 0.098010142 | AL18: =$AD18/12 -> 90750.629 | AM18: =AN18/AN10 -> 0.098010142 | AN18: =$AD18/12 -> 90750.629 | AO18: =AP18/AP10 -> 0.098010142 | AP18: =$AD18/12 -> 90750.629 | AQ18: =AR18/AR10 -> 0.098010142 | AR18: =$AD18/12 -> 90750.629 | AS18: =AT18/AT10 -> 0.092462398 | AT18: =$AD18/12 -> 90750.629 | AU18: =AV18/AV10 -> 0.092462398 | AV18: =$AD18/12 -> 90750.629 | AW18: =AX18/AX10 -> 0.092462398 | AX18: =$AD18/12 -> 90750.629 | AY18: =AZ18/AZ10 -> 0.092462398 | AZ18: =$AD18/12 -> 90750.629 | BA18: =BB18/BB10 -> 0.092462398 | BB18: =$AD18/12 -> 90750.629 | BC18: =BD18/BD10 -> 0.095619651 | BD18: =AF18+AH18+AJ18+AL18+AN18+AP18+AR18+AT18+AV18+AX18+AZ18+BB18 -> 1089007.5
B19: PREDIAL | D19: =E19/E11 -> 0.10801056 | E19: =SUM(E13:E18) -> 1025533.3 | F19: =G19/G11 -> 0.10801056 | G19: =SUM(G13:G18) -> 1025533.3 | H19: =I19/I11 -> 0.10801056 | I19: =SUM(I13:I18) -> 1025533.3 | J19: =K19/K11 -> 0.10801056 | K19: =SUM(K13:K18) -> 1025533.3 | L19: =M19/M11 -> 0.10801056 | M19: =SUM(M13:M18) -> 1025533.3 | N19: =O19/O11 -> 0.10306608 | O19: =SUM(O13:O18) -> 1025533.3 | P19: =Q19/Q11 -> 0.099948428 | Q19: =SUM(Q13:Q18) -> 1025533.3 | R19: =S19/S11 -> 0.099512665 | S19: =SUM(S13:S18) -> 1025533.3 | T19: =U19/U11 -> 0.099512665 | U19: =SUM(U13:U18) -> 1025533.3 | V19: =W19/W11 -> 0.099512665 | W19: =SUM(W13:W18) -> 1025533.3 | X19: =Y19/Y11 -> 0.099512665 | Y19: =SUM(Y13:Y18) -> 1025533.3 | Z19: =AA19/AA11 -> 0.098675192 | AA19: =SUM(AA13:AA18) -> 1025533.3 | AB19: =AC19/AC11 -> 0.10315518 | AC19: =E19+G19+I19+K19+M19+O19+Q19+S19+U19+W19+Y19+AA19 -> 12306400 | AE19: =AF19/AF11 -> 0.11800017 | AF19: =SUM(AF13:AF18) -> 1179363.3 | AG19: =AH19/AH11 -> 0.11800017 | AH19: =SUM(AH13:AH18) -> 1179363.3 | AI19: =AJ19/AJ11 -> 0.11800017 | AJ19: =SUM(AJ13:AJ18) -> 1179363.3 | AK19: =AL19/AL11 -> 0.11800017 | AL19: =SUM(AL13:AL18) -> 1179363.3 | AM19: =AN19/AN11 -> 0.11800017 | AN19: =SUM(AN13:AN18) -> 1179363.3 | AO19: =AP19/AP11 -> 0.11687926 | AP19: =SUM(AP13:AP18) -> 1179363.3 | AQ19: =AR19/AR11 -> 0.11462661 | AR19: =SUM(AR13:AR18) -> 1179363.3 | AS19: =AT19/AT11 -> 0.11401099 | AT19: =SUM(AT13:AT18) -> 1179363.3 | AU19: =AV19/AV11 -> 0.11401099 | AV19: =SUM(AV13:AV18) -> 1179363.3 | AW19: =AX19/AX11 -> 0.11401099 | AX19: =SUM(AX13:AX18) -> 1179363.3 | AY19: =AZ19/AZ11 -> 0.11401099 | AZ19: =SUM(AZ13:AZ18) -> 1179363.3 | BA19: =BB19/BB11 -> 0.11249202 | BB19: =SUM(BB13:BB18) -> 1179363.3 | BC19: =BD19/BD11 -> 0.1158005 | BD19: =AF19+AH19+AJ19+AL19+AN19+AP19+AR19+AT19+AV19+AX19+AZ19+BB19 -> 14152360
B21: =Activos!K133 -> 156000 | C21: Yari | D21: =E21/E5 -> 0.089957616 | E21: =$B21 -> 156000 | F21: =G21/G5 -> 0.089957616 | G21: =$B21 -> 156000 | H21: =I21/I5 -> 0.089957616 | I21: =$B21 -> 156000 | J21: =K21/K5 -> 0.089957616 | K21: =$B21 -> 156000 | L21: =M21/M5 -> 0.089957616 | M21: =$B21 -> 156000 | N21: =O21/O5 -> 0.089957616 | O21: =$B21 -> 156000 | P21: =Q21/Q5 -> 0.089957616 | Q21: =$B21 -> 156000 | R21: =S21/S5 -> 0.089957616 | S21: =$B21 -> 156000 | T21: =U21/U5 -> 0.089957616 | U21: =$B21 -> 156000 | V21: =W21/W5 -> 0.089957616 | W21: =$B21 -> 156000 | X21: =Y21/Y5 -> 0.089957616 | Y21: =$B21 -> 156000 | Z21: =AA21/AA5 -> 0.089957616 | AA21: =$B21 -> 156000 | AB21: =AC21/AC5 -> 0.089957616 | AC21: =E21+G21+I21+K21+M21+O21+Q21+S21+U21+W21+Y21+AA21 -> 1872000 | AD21: =Activos!L133 -> 179400 | AE21: =AF21/AF5 -> 0.097595527 | AF21: =$AD21 -> 179400 | AG21: =AH21/AH5 -> 0.097595527 | AH21: =$AD21 -> 179400 | AI21: =AJ21/AJ5 -> 0.097595527 | AJ21: =$AD21 -> 179400 | AK21: =AL21/AL5 -> 0.097595527 | AL21: =$AD21 -> 179400 | AM21: =AN21/AN5 -> 0.097595527 | AN21: =$AD21 -> 179400 | AO21: =AP21/AP5 -> 0.097595527 | AP21: =$AD21 -> 179400 | AQ21: =AR21/AR5 -> 0.097595527 | AR21: =$AD21 -> 179400 | AS21: =AT21/AT5 -> 0.097595527 | AT21: =$AD21 -> 179400 | AU21: =AV21/AV5 -> 0.097595527 | AV21: =$AD21 -> 179400 | AW21: =AX21/AX5 -> 0.097595527 | AX21: =$AD21 -> 179400 | AY21: =AZ21/AZ5 -> 0.097595527 | AZ21: =$AD21 -> 179400 | BA21: =BB21/BB5 -> 0.097595527 | BB21: =$AD21 -> 179400 | BC21: =BD21/BD5 -> 0.097595527 | BD21: =AF21+AH21+AJ21+AL21+AN21+AP21+AR21+AT21+AV21+AX21+AZ21+BB21 -> 2152800
B22: =Activos!K38 -> 590302.59 | C22: Ocarinas | D22: =E22/E7 -> 0.38835696 | E22: =$B22 -> 590302.59 | F22: =G22/G7 -> 0.38835696 | G22: =$B22 -> 590302.59 | H22: =I22/I7 -> 0.38835696 | I22: =$B22 -> 590302.59 | J22: =K22/K7 -> 0.38835696 | K22: =$B22 -> 590302.59 | L22: =M22/M7 -> 0.38835696 | M22: =$B22 -> 590302.59 | N22: =O22/O7 -> 0.30271927 | O22: =$B22 -> 590302.59 | P22: =Q22/Q7 -> 0.28109647 | Q22: =$B22 -> 590302.59 | R22: =S22/S7 -> 0.28109647 | S22: =$B22 -> 590302.59 | T22: =U22/U7 -> 0.28109647 | U22: =$B22 -> 590302.59 | V22: =W22/W7 -> 0.28109647 | W22: =$B22 -> 590302.59 | X22: =Y22/Y7 -> 0.28109647 | Y22: =$B22 -> 590302.59 | Z22: =AA22/AA7 -> 0.28109647 | AA22: =$B22 -> 590302.59 | AB22: =AC22/AC7 -> 0.31980275 | AC22: =E22+G22+I22+K22+M22+O22+Q22+S22+U22+W22+Y22+AA22 -> 7083631 | AD22: =Activos!L38 -> 678847.97 | AE22: =AF22/AF7 -> 0.42493864 | AF22: =$AD22 -> 678847.97 | AG22: =AH22/AH7 -> 0.42493864 | AH22: =$AD22 -> 678847.97 | AI22: =AJ22/AJ7 -> 0.42493864 | AJ22: =$AD22 -> 678847.97 | AK22: =AL22/AL7 -> 0.42493864 | AL22: =$AD22 -> 678847.97 | AM22: =AN22/AN7 -> 0.42493864 | AN22: =$AD22 -> 678847.97 | AO22: =AP22/AP7 -> 0.40088551 | AP22: =$AD22 -> 678847.97 | AQ22: =AR22/AR7 -> 0.40088551 | AR22: =$AD22 -> 678847.97 | AS22: =AT22/AT7 -> 0.40088551 | AT22: =$AD22 -> 678847.97 | AU22: =AV22/AV7 -> 0.40088551 | AV22: =$AD22 -> 678847.97 | AW22: =AX22/AX7 -> 0.40088551 | AX22: =$AD22 -> 678847.97 | AY22: =AZ22/AZ7 -> 0.40088551 | AZ22: =$AD22 -> 678847.97 | BA22: =BB22/BB7 -> 0.40088551 | BB22: =$AD22 -> 678847.97 | BC22: =BD22/BD7 -> 0.41056873 | BD22: =AF22+AH22+AJ22+AL22+AN22+AP22+AR22+AT22+AV22+AX22+AZ22+BB22 -> 8146175.7
B23: =Activos!K57 -> 317043.1 | C23: Rivera del valle | D23: =E23/E9 -> 0.18486478 | E23: =$B23 -> 317043.1 | F23: =G23/G9 -> 0.18486478 | G23: =$B23 -> 317043.1 | H23: =I23/I9 -> 0.18486478 | I23: =$B23 -> 317043.1 | J23: =K23/K9 -> 0.18486478 | K23: =$B23 -> 317043.1 | L23: =M23/M9 -> 0.18486478 | M23: =$B23 -> 317043.1 | N23: =O23/O9 -> 0.18486478 | O23: =$B23 -> 317043.1 | P23: =Q23/Q9 -> 0.18486478 | Q23: =$B23 -> 317043.1 | R23: =S23/S9 -> 0.18486478 | S23: =$B23 -> 317043.1 | T23: =U23/U9 -> 0.18486478 | U23: =$B23 -> 317043.1 | V23: =W23/W9 -> 0.18486478 | W23: =$B23 -> 317043.1 | X23: =Y23/Y9 -> 0.18486478 | Y23: =$B23 -> 317043.1 | Z23: =AA23/AA9 -> 0.17589418 | AA23: =$B23 -> 317043.1 | AB23: =AC23/AC9 -> 0.18408243 | AC23: =E23+G23+I23+K23+M23+O23+Q23+S23+U23+W23+Y23+AA23 -> 3804517.2 | AD23: =Activos!L57 -> 364599.57 | AE23: =AF23/AF9 -> 0.2022783 | AF23: =$AD23 -> 364599.57 | AG23: =AH23/AH9 -> 0.2022783 | AH23: =$AD23 -> 364599.57 | AI23: =AJ23/AJ9 -> 0.2022783 | AJ23: =$AD23 -> 364599.57 | AK23: =AL23/AL9 -> 0.2022783 | AL23: =$AD23 -> 364599.57 | AM23: =AN23/AN9 -> 0.2022783 | AN23: =$AD23 -> 364599.57 | AO23: =AP23/AP9 -> 0.2022783 | AP23: =$AD23 -> 364599.57 | AQ23: =AR23/AR9 -> 0.2022783 | AR23: =$AD23 -> 364599.57 | AS23: =AT23/AT9 -> 0.2022783 | AT23: =$AD23 -> 364599.57 | AU23: =AV23/AV9 -> 0.2022783 | AV23: =$AD23 -> 364599.57 | AW23: =AX23/AX9 -> 0.2022783 | AX23: =$AD23 -> 364599.57 | AY23: =AZ23/AZ9 -> 0.2022783 | AZ23: =$AD23 -> 364599.57 | BA23: =BB23/BB9 -> 0.19082859 | BB23: =$AD23 -> 364599.57 | BC23: =BD23/BD9 -> 0.20127195 | BD23: =AF23+AH23+AJ23+AL23+AN23+AP23+AR23+AT23+AV23+AX23+AZ23+BB23 -> 4375194.8
B24: ADMINISTRACIÓN | D24: =E24/E11 -> 0.11199302 | E24: =SUM(E21:E23) -> 1063345.7 | F24: =G24/G11 -> 0.11199302 | G24: =SUM(G21:G23) -> 1063345.7 | H24: =I24/I11 -> 0.11199302 | I24: =SUM(I21:I23) -> 1063345.7 | J24: =K24/K11 -> 0.11199302 | K24: =SUM(K21:K23) -> 1063345.7 | L24: =M24/M11 -> 0.11199302 | M24: =SUM(M21:M23) -> 1063345.7 | N24: =O24/O11 -> 0.10686623 | O24: =SUM(O21:O23) -> 1063345.7 | P24: =Q24/Q11 -> 0.10363362 | Q24: =SUM(Q21:Q23) -> 1063345.7 | R24: =S24/S11 -> 0.10318179 | S24: =SUM(S21:S23) -> 1063345.7 | T24: =U24/U11 -> 0.10318179 | U24: =SUM(U21:U23) -> 1063345.7 | V24: =W24/W11 -> 0.10318179 | W24: =SUM(W21:W23) -> 1063345.7 | X24: =Y24/Y11 -> 0.10318179 | Y24: =SUM(Y21:Y23) -> 1063345.7 | Z24: =AA24/AA11 -> 0.10231344 | AA24: =SUM(AA21:AA23) -> 1063345.7 | AB24: =AC24/AC11 -> 0.10695861 | AC24: =E24+G24+I24+K24+M24+O24+Q24+S24+U24+W24+Y24+AA24 -> 12760148 | AE24: =AF24/AF11 -> 0.12235095 | AF24: =SUM(AF21:AF23) -> 1222847.5 | AG24: =AH24/AH11 -> 0.12235095 | AH24: =SUM(AH21:AH23) -> 1222847.5 | AI24: =AJ24/AJ11 -> 0.12235095 | AJ24: =SUM(AJ21:AJ23) -> 1222847.5 | AK24: =AL24/AL11 -> 0.12235095 | AL24: =SUM(AL21:AL23) -> 1222847.5 | AM24: =AN24/AN11 -> 0.12235095 | AN24: =SUM(AN21:AN23) -> 1222847.5 | AO24: =AP24/AP11 -> 0.12118871 | AP24: =SUM(AP21:AP23) -> 1222847.5 | AQ24: =AR24/AR11 -> 0.118853 | AR24: =SUM(AR21:AR23) -> 1222847.5 | AS24: =AT24/AT11 -> 0.11821468 | AT24: =SUM(AT21:AT23) -> 1222847.5 | AU24: =AV24/AV11 -> 0.11821468 | AV24: =SUM(AV21:AV23) -> 1222847.5 | AW24: =AX24/AX11 -> 0.11821468 | AX24: =SUM(AX21:AX23) -> 1222847.5 | AY24: =AZ24/AZ11 -> 0.11821468 | AZ24: =SUM(AZ21:AZ23) -> 1222847.5 | BA24: =BB24/BB11 -> 0.11663971 | BB24: =SUM(BB21:BB23) -> 1222847.5 | BC24: =BD24/BD11 -> 0.12007018 | BD24: =AF24+AH24+AJ24+AL24+AN24+AP24+AR24+AT24+AV24+AX24+AZ24+BB24 -> 14674170
C26: Yari | D26: =E26/E5 -> 0.018747202 | E26: =$B$29*D5 -> 32510.461 | F26: =G26/G5 -> 0.023190289 | G26: =$B$31*F5 -> 40215.44 | H26: =I26/I5 -> 0.023190289 | I26: =$B$31*H5 -> 40215.44 | J26: =K26/K5 -> 0.023190289 | K26: =$B$31*J5 -> 40215.44 | L26: =M26/M5 -> 0.023190289 | M26: =$B$31*L5 -> 40215.44 | N26: =O26/O5 -> 0.02212869 | O26: =$B$31*N5 -> 38374.468 | P26: =Q26/Q5 -> 0.021459317 | Q26: =$B$31*P5 -> 37213.675 | R26: =S26/S5 -> 0.021365757 | S26: =$B$31*R5 -> 37051.428 | T26: =U26/U5 -> 0.021365757 | U26: =$B$31*T5 -> 37051.428 | V26: =W26/W5 -> 0.021365757 | W26: =$B$31*V5 -> 37051.428 | X26: =Y26/Y5 -> 0.021365757 | Y26: =$B$31*X5 -> 37051.428 | Z26: =AA26/AA5 -> 0.021185949 | AA26: =$B$31*Z5 -> 36739.613 | AB26: =AC26/AC5 -> 0.021812112 | AC26: =E26+G26+I26+K26+M26+O26+Q26+S26+U26+W26+Y26+AA26 -> 453905.69 | AE26: =AF26/AF5 -> 0.022030519 | AF26: =$AD$29*AE5 -> 40496.479 | AG26: =AH26/AH5 -> 0.025335097 | AH26: =$AD$31*AG5 -> 46570.951 | AI26: =AJ26/AJ5 -> 0.025335097 | AJ26: =$AD$31*AI5 -> 46570.951 | AK26: =AL26/AL5 -> 0.025335097 | AL26: =$AD$31*AK5 -> 46570.951 | AM26: =AN26/AN5 -> 0.025335097 | AN26: =$AD$31*AM5 -> 46570.951 | AO26: =AP26/AP5 -> 0.025094434 | AP26: =$AD$31*AO5 -> 46128.563 | AQ26: =AR26/AR5 -> 0.02461078 | AR26: =$AD$31*AQ5 -> 45239.511 | AS26: =AT26/AT5 -> 0.024478604 | AT26: =$AD$31*AS5 -> 44996.545 | AU26: =AV26/AV5 -> 0.024478604 | AV26: =$AD$31*AU5 -> 44996.545 | AW26: =AX26/AX5 -> 0.024478604 | AX26: =$AD$31*AW5 -> 44996.545 | AY26: =AZ26/AZ5 -> 0.024478604 | AZ26: =$AD$31*AY5 -> 44996.545 | BA26: =BB26/BB5 -> 0.024152475 | BB26: =$AD$31*BA5 -> 44397.056 | BC26: =BD26/BD5 -> 0.024595251 | BD26: =AF26+AH26+AJ26+AL26+AN26+AP26+AR26+AT26+AV26+AX26+AZ26+BB26 -> 542531.59
C27: Belén | D27: =E27/E6 -> 0.018747202 | E27: =$B$29*D6 -> 58952.453 | F27: =G27/G6 -> 0.023190289 | G27: =$B$31*F6 -> 72924.184 | H27: =I27/I6 -> 0.023190289 | I27: =$B$31*H6 -> 72924.184 | J27: =K27/K6 -> 0.023190289 | K27: =$B$31*J6 -> 72924.184 | L27: =M27/M6 -> 0.023190289 | M27: =$B$31*L6 -> 72924.184 | N27: =O27/O6 -> 0.02212869 | O27: =$B$31*N6 -> 69585.879 | P27: =Q27/Q6 -> 0.021459317 | Q27: =$B$31*P6 -> 70922.499 | R27: =S27/S6 -> 0.021365757 | S27: =$B$31*R6 -> 70613.285 | T27: =U27/U6 -> 0.021365757 | U27: =$B$31*T6 -> 70613.285 | V27: =W27/W6 -> 0.021365757 | W27: =$B$31*V6 -> 70613.285 | X27: =Y27/Y6 -> 0.021365757 | Y27: =$B$31*X6 -> 70613.285 | Z27: =AA27/AA6 -> 0.021185949 | AA27: =$B$31*Z6 -> 70019.022 | AB27: =AC27/AC6 -> 0.021800656 | AC27: =E27+G27+I27+K27+M27+O27+Q27+S27+U27+W27+Y27+AA27 -> 843629.73 | AE27: =AF27/AF6 -> 0.022030519 | AF27: =$AD$29*AE6 -> 72810.307 | AG27: =AH27/AH6 -> 0.025335097 | AH27: =$AD$31*AG6 -> 83731.853 | AI27: =AJ27/AJ6 -> 0.025335097 | AJ27: =$AD$31*AI6 -> 83731.853 | AK27: =AL27/AL6 -> 0.025335097 | AL27: =$AD$31*AK6 -> 83731.853 | AM27: =AN27/AN6 -> 0.025335097 | AN27: =$AD$31*AM6 -> 83731.853 | AO27: =AP27/AP6 -> 0.025094434 | AP27: =$AD$31*AO6 -> 82936.467 | AQ27: =AR27/AR6 -> 0.02461078 | AR27: =$AD$31*AQ6 -> 86218.283 | AS27: =AT27/AT6 -> 0.024478604 | AT27: =$AD$31*AS6 -> 85755.233 | AU27: =AV27/AV6 -> 0.024478604 | AV27: =$AD$31*AU6 -> 85755.233 | AW27: =AX27/AX6 -> 0.024478604 | AX27: =$AD$31*AW6 -> 85755.233 | AY27: =AZ27/AZ6 -> 0.024478604 | AZ27: =$AD$31*AY6 -> 85755.233 | BA27: =BB27/BB6 -> 0.024152475 | BB27: =$AD$31*BA6 -> 84612.717 | BC27: =BD27/BD6 -> 0.024590912 | BD27: =AF27+AH27+AJ27+AL27+AN27+AP27+AR27+AT27+AV27+AX27+AZ27+BB27 -> 1004526.1
C28: Ocarinas | D28: =E28/E7 -> 0.018747202 | E28: =$B$29*D7 -> 28495.748 | F28: =G28/G7 -> 0.023190289 | G28: =$B$31*F7 -> 35249.24 | H28: =I28/I7 -> 0.023190289 | I28: =$B$31*H7 -> 35249.24 | J28: =K28/K7 -> 0.023190289 | K28: =$B$31*J7 -> 35249.24 | L28: =M28/M7 -> 0.023190289 | M28: =$B$31*L7 -> 35249.24 | N28: =O28/O7 -> 0.02212869 | O28: =$B$31*N7 -> 43150.946 | P28: =Q28/Q7 -> 0.021459317 | Q28: =$B$31*P7 -> 45064.567 | R28: =S28/S7 -> 0.021365757 | S28: =$B$31*R7 -> 44868.09 | T28: =U28/U7 -> 0.021365757 | U28: =$B$31*T7 -> 44868.09 | V28: =W28/W7 -> 0.021365757 | W28: =$B$31*V7 -> 44868.09 | X28: =Y28/Y7 -> 0.021365757 | Y28: =$B$31*X7 -> 44868.09 | Z28: =AA28/AA7 -> 0.021185949 | AA28: =$B$31*Z7 -> 44490.492 | AB28: =AC28/AC7 -> 0.021745872 | AC28: =E28+G28+I28+K28+M28+O28+Q28+S28+U28+W28+Y28+AA28 -> 481671.07 | AE28: =AF28/AF7 -> 0.022030519 | AF28: =$AD$29*AE7 -> 35194.195 | AG28: =AH28/AH7 -> 0.025335097 | AH28: =$AD$31*AG7 -> 40473.325 | AI28: =AJ28/AJ7 -> 0.025335097 | AJ28: =$AD$31*AI7 -> 40473.325 | AK28: =AL28/AL7 -> 0.025335097 | AL28: =$AD$31*AK7 -> 40473.325 | AM28: =AN28/AN7 -> 0.025335097 | AN28: =$AD$31*AM7 -> 40473.325 | AO28: =AP28/AP7 -> 0.025094434 | AP28: =$AD$31*AO7 -> 42494.192 | AQ28: =AR28/AR7 -> 0.02461078 | AR28: =$AD$31*AQ7 -> 41675.186 | AS28: =AT28/AT7 -> 0.024478604 | AT28: =$AD$31*AS7 -> 41451.362 | AU28: =AV28/AV7 -> 0.024478604 | AV28: =$AD$31*AU7 -> 41451.362 | AW28: =AX28/AX7 -> 0.024478604 | AX28: =$AD$31*AW7 -> 41451.362 | AY28: =AZ28/AZ7 -> 0.024478604 | AZ28: =$AD$31*AY7 -> 41451.362 | BA28: =BB28/BB7 -> 0.024152475 | BB28: =$AD$31*BA7 -> 40899.106 | BC28: =BD28/BD7 -> 0.024593344 | BD28: =AF28+AH28+AJ28+AL28+AN28+AP28+AR28+AT28+AV28+AX28+AZ28+BB28 -> 487961.43
B29: 178000 | C29: Pedregal | D29: =E29/E8 -> 0.018747202 | E29: =$B$29*D8 -> 9373.6012 | F29: =G29/G8 -> 0.023190289 | G29: =$B$31*F8 -> 11595.145 | H29: =I29/I8 -> 0.023190289 | I29: =$B$31*H8 -> 11595.145 | J29: =K29/K8 -> 0.023190289 | K29: =$B$31*J8 -> 11595.145 | L29: =M29/M8 -> 0.023190289 | M29: =$B$31*L8 -> 11595.145 | N29: =O29/O8 -> 0.02212869 | O29: =$B$31*N8 -> 11628.627 | P29: =Q29/Q8 -> 0.021459317 | Q29: =$B$31*P8 -> 11276.871 | R29: =S29/S8 -> 0.021365757 | S29: =$B$31*R8 -> 11227.705 | T29: =U29/U8 -> 0.021365757 | U29: =$B$31*T8 -> 11227.705 | V29: =W29/W8 -> 0.021365757 | W29: =$B$31*V8 -> 11227.705 | X29: =Y29/Y8 -> 0.021365757 | Y29: =$B$31*X8 -> 11227.705 | Z29: =AA29/AA8 -> 0.021185949 | AA29: =$B$31*Z8 -> 11133.216 | AB29: =AC29/AC8 -> 0.02180201 | AC29: =E29+G29+I29+K29+M29+O29+Q29+S29+U29+W29+Y29+AA29 -> 134703.72 | AD29: 220186 | AE29: =AF29/AF8 -> 0.022030519 | AF29: =$AD$29*AE8 -> 11577.038 | AG29: =AH29/AH8 -> 0.025335097 | AH29: =$AD$31*AG8 -> 13313.594 | AI29: =AJ29/AJ8 -> 0.025335097 | AJ29: =$AD$31*AI8 -> 13313.594 | AK29: =AL29/AL8 -> 0.025335097 | AL29: =$AD$31*AK8 -> 13313.594 | AM29: =AN29/AN8 -> 0.025335097 | AN29: =$AD$31*AM8 -> 13313.594 | AO29: =AP29/AP8 -> 0.025094434 | AP29: =$AD$31*AO8 -> 13187.125 | AQ29: =AR29/AR8 -> 0.02461078 | AR29: =$AD$31*AQ8 -> 12932.965 | AS29: =AT29/AT8 -> 0.024478604 | AT29: =$AD$31*AS8 -> 12863.506 | AU29: =AV29/AV8 -> 0.024478604 | AV29: =$AD$31*AU8 -> 12863.506 | AW29: =AX29/AX8 -> 0.024478604 | AX29: =$AD$31*AW8 -> 12863.506 | AY29: =AZ29/AZ8 -> 0.024478604 | AZ29: =$AD$31*AY8 -> 12863.506 | BA29: =BB29/BB8 -> 0.024152475 | BB29: =$AD$31*BA8 -> 13453.653 | BC29: =BD29/BD8 -> 0.024593048 | BD29: =AF29+AH29+AJ29+AL29+AN29+AP29+AR29+AT29+AV29+AX29+AZ29+BB29 -> 155859.18
B30: 0.237 | C30: Rivera del Valle | D30: =E30/E9 -> 0.018747202 | E30: =$B$29*D9 -> 32151.452 | F30: =G30/G9 -> 0.023190289 | G30: =$B$31*F9 -> 39771.346 | H30: =I30/I9 -> 0.023190289 | I30: =$B$31*H9 -> 39771.346 | J30: =K30/K9 -> 0.023190289 | K30: =$B$31*J9 -> 39771.346 | L30: =M30/M9 -> 0.023190289 | M30: =$B$31*L9 -> 39771.346 | N30: =O30/O9 -> 0.02212869 | O30: =$B$31*N9 -> 37950.704 | P30: =Q30/Q9 -> 0.021459317 | Q30: =$B$31*P9 -> 36802.729 | R30: =S30/S9 -> 0.021365757 | S30: =$B$31*R9 -> 36642.274 | T30: =U30/U9 -> 0.021365757 | U30: =$B$31*T9 -> 36642.274 | V30: =W30/W9 -> 0.021365757 | W30: =$B$31*V9 -> 36642.274 | X30: =Y30/Y9 -> 0.021365757 | Y30: =$B$31*X9 -> 36642.274 | Z30: =AA30/AA9 -> 0.021185949 | AA30: =$B$31*Z9 -> 38186.931 | AB30: =AC30/AC9 -> 0.021809462 | AC30: =E30+G30+I30+K30+M30+O30+Q30+S30+U30+W30+Y30+AA30 -> 450746.3 | AD30: 0.15 | AE30: =AF30/AF9 -> 0.022030519 | AF30: =$AD$29*AE9 -> 39709.24 | AG30: =AH30/AH9 -> 0.025335097 | AH30: =$AD$31*AG9 -> 45665.626 | AI30: =AJ30/AJ9 -> 0.025335097 | AJ30: =$AD$31*AI9 -> 45665.626 | AK30: =AL30/AL9 -> 0.025335097 | AL30: =$AD$31*AK9 -> 45665.626 | AM30: =AN30/AN9 -> 0.025335097 | AN30: =$AD$31*AM9 -> 45665.626 | AO30: =AP30/AP9 -> 0.025094434 | AP30: =$AD$31*AO9 -> 45231.839 | AQ30: =AR30/AR9 -> 0.02461078 | AR30: =$AD$31*AQ9 -> 44360.07 | AS30: =AT30/AT9 -> 0.024478604 | AT30: =$AD$31*AS9 -> 44121.826 | AU30: =AV30/AV9 -> 0.024478604 | AV30: =$AD$31*AU9 -> 44121.826 | AW30: =AX30/AX9 -> 0.024478604 | AX30: =$AD$31*AW9 -> 44121.826 | AY30: =AZ30/AZ9 -> 0.024478604 | AZ30: =$AD$31*AY9 -> 44121.826 | BA30: =BB30/BB9 -> 0.024152475 | BB30: =$AD$31*BA9 -> 46146.031 | BC30: =BD30/BD9 -> 0.024593048 | BD30: =AF30+AH30+AJ30+AL30+AN30+AP30+AR30+AT30+AV30+AX30+AZ30+BB30 -> 534596.99
B31: =B29*(1+B30) -> 220186 | C31: La Ceja | D31: =E31/E10 -> 0.018747202 | E31: =$B$29*D10 -> 16516.285 | F31: =G31/G10 -> 0.023190289 | G31: =$B$31*F10 -> 20430.645 | H31: =I31/I10 -> 0.023190289 | I31: =$B$31*H10 -> 20430.645 | J31: =K31/K10 -> 0.023190289 | K31: =$B$31*J10 -> 20430.645 | L31: =M31/M10 -> 0.023190289 | M31: =$B$31*L10 -> 20430.645 | N31: =O31/O10 -> 0.02212869 | O31: =$B$31*N10 -> 19495.376 | P31: =Q31/Q10 -> 0.021459317 | Q31: =$B$31*P10 -> 18905.659 | R31: =S31/S10 -> 0.021365757 | S31: =$B$31*R10 -> 19783.217 | T31: =U31/U10 -> 0.021365757 | U31: =$B$31*T10 -> 19783.217 | V31: =W31/W10 -> 0.021365757 | W31: =$B$31*V10 -> 19783.217 | X31: =Y31/Y10 -> 0.021365757 | Y31: =$B$31*X10 -> 19783.217 | Z31: =AA31/AA10 -> 0.021185949 | AA31: =$B$31*Z10 -> 19616.727 | AB31: =AC31/AC10 -> 0.021802076 | AC31: =E31+G31+I31+K31+M31+O31+Q31+S31+U31+W31+Y31+AA31 -> 235389.49 | AD31: =AD29*(1+AD30) -> 253213.9 | AE31: =AF31/AF10 -> 0.022030519 | AF31: =$AD$29*AE10 -> 20398.741 | AG31: =AH31/AH10 -> 0.025335097 | AH31: =$AD$31*AG10 -> 23458.552 | AI31: =AJ31/AJ10 -> 0.025335097 | AJ31: =$AD$31*AI10 -> 23458.552 | AK31: =AL31/AL10 -> 0.025335097 | AL31: =$AD$31*AK10 -> 23458.552 | AM31: =AN31/AN10 -> 0.025335097 | AN31: =$AD$31*AM10 -> 23458.552 | AO31: =AP31/AP10 -> 0.025094434 | AP31: =$AD$31*AO10 -> 23235.714 | AQ31: =AR31/AR10 -> 0.02461078 | AR31: =$AD$31*AQ10 -> 22787.884 | AS31: =AT31/AT10 -> 0.024478604 | AT31: =$AD$31*AS10 -> 24025.428 | AU31: =AV31/AV10 -> 0.024478604 | AV31: =$AD$31*AU10 -> 24025.428 | AW31: =AX31/AX10 -> 0.024478604 | AX31: =$AD$31*AW10 -> 24025.428 | AY31: =AZ31/AZ10 -> 0.024478604 | AZ31: =$AD$31*AY10 -> 24025.428 | BA31: =BB31/BB10 -> 0.024152475 | BB31: =$AD$31*BA10 -> 23705.337 | BC31: =BD31/BD10 -> 0.024590815 | BD31: =AF31+AH31+AJ31+AL31+AN31+AP31+AR31+AT31+AV31+AX31+AZ31+BB31 -> 280063.6
B32: SST MLUJ | D32: =E32/E11 -> 0.018747202 | E32: =SUM(E26:E31) -> 178000 | F32: =G32/G11 -> 0.023190289 | G32: =SUM(G26:G31) -> 220186 | H32: =I32/I11 -> 0.023190289 | I32: =SUM(I26:I31) -> 220186 | J32: =K32/K11 -> 0.023190289 | K32: =SUM(K26:K31) -> 220186 | L32: =M32/M11 -> 0.023190289 | M32: =SUM(M26:M31) -> 220186 | N32: =O32/O11 -> 0.02212869 | O32: =SUM(O26:O31) -> 220186 | P32: =Q32/Q11 -> 0.021459317 | Q32: =SUM(Q26:Q31) -> 220186 | R32: =S32/S11 -> 0.021365757 | S32: =SUM(S26:S31) -> 220186 | T32: =U32/U11 -> 0.021365757 | U32: =SUM(U26:U31) -> 220186 | V32: =W32/W11 -> 0.021365757 | W32: =SUM(W26:W31) -> 220186 | X32: =Y32/Y11 -> 0.021365757 | Y32: =SUM(Y26:Y31) -> 220186 | Z32: =AA32/AA11 -> 0.021185949 | AA32: =SUM(AA26:AA31) -> 220186 | AB32: =AC32/AC11 -> 0.021794207 | AC32: =E32+G32+I32+K32+M32+O32+Q32+S32+U32+W32+Y32+AA32 -> 2600046 | AE32: =AF32/AF11 -> 0.022030519 | AF32: =SUM(AF26:AF31) -> 220186 | AG32: =AH32/AH11 -> 0.025335097 | AH32: =SUM(AH26:AH31) -> 253213.9 | AI32: =AJ32/AJ11 -> 0.025335097 | AJ32: =SUM(AJ26:AJ31) -> 253213.9 | AK32: =AL32/AL11 -> 0.025335097 | AL32: =SUM(AL26:AL31) -> 253213.9 | AM32: =AN32/AN11 -> 0.025335097 | AN32: =SUM(AN26:AN31) -> 253213.9 | AO32: =AP32/AP11 -> 0.025094434 | AP32: =SUM(AP26:AP31) -> 253213.9 | AQ32: =AR32/AR11 -> 0.02461078 | AR32: =SUM(AR26:AR31) -> 253213.9 | AS32: =AT32/AT11 -> 0.024478604 | AT32: =SUM(AT26:AT31) -> 253213.9 | AU32: =AV32/AV11 -> 0.024478604 | AV32: =SUM(AV26:AV31) -> 253213.9 | AW32: =AX32/AX11 -> 0.024478604 | AX32: =SUM(AX26:AX31) -> 253213.9 | AY32: =AZ32/AZ11 -> 0.024478604 | AZ32: =SUM(AZ26:AZ31) -> 253213.9 | BA32: =BB32/BB11 -> 0.024152475 | BB32: =SUM(BB26:BB31) -> 253213.9 | BC32: =BD32/BD11 -> 0.024592572 | BD32: =AF32+AH32+AJ32+AL32+AN32+AP32+AR32+AT32+AV32+AX32+AZ32+BB32 -> 3005538.9
C34: Yari | D34: =E34/E5 -> 0.060946165 | E34: =$B$39*D5 -> 105689.79 | F34: =G34/G5 -> 0.060946165 | G34: =$B$39*F5 -> 105689.79 | H34: =I34/I5 -> 0.060946165 | I34: =$B$39*H5 -> 105689.79 | J34: =K34/K5 -> 0.060946165 | K34: =$B$39*J5 -> 105689.79 | L34: =M34/M5 -> 0.060946165 | M34: =$B$39*L5 -> 105689.79 | N34: =O34/O5 -> 0.058156187 | O34: =$B$39*N5 -> 100851.55 | P34: =Q34/Q5 -> 0.056397015 | Q34: =$B$39*P5 -> 97800.884 | R34: =S34/S5 -> 0.056151131 | S34: =$B$39*R5 -> 97374.483 | T34: =U34/U5 -> 0.056151131 | U34: =$B$39*T5 -> 97374.483 | V34: =W34/W5 -> 0.021365757 | W34: =$B$31*V5 -> 37051.428 | X34: =Y34/Y5 -> 0.021365757 | Y34: =$B$31*X5 -> 37051.428 | Z34: =AA34/AA5 -> 0.021185949 | AA34: =$B$31*Z5 -> 36739.613 | AB34: =AC34/AC5 -> 0.049625313 | AC34: =E34+G34+I34+K34+M34+O34+Q34+S34+U34+W34+Y34+AA34 -> 1032692.8 | AE34: =AF34/AF5 -> 0.022030519 | AF34: =$AD$37*AE5 -> 40496.479 | AG34: =AH34/AH5 -> 0.025335097 | AH34: =$AD$39*AG5 -> 46570.951 | AI34: =AJ34/AJ5 -> 0.025335097 | AJ34: =$AD$39*AI5 -> 46570.951 | AK34: =AL34/AL5 -> 0.025335097 | AL34: =$AD$39*AK5 -> 46570.951 | AM34: =AN34/AN5 -> 0.025335097 | AN34: =$AD$39*AM5 -> 46570.951 | AO34: =AP34/AP5 -> 0.025094434 | AP34: =$AD$39*AO5 -> 46128.563 | AQ34: =AR34/AR5 -> 0.02461078 | AR34: =$AD$39*AQ5 -> 45239.511 | AS34: =AT34/AT5 -> 0.024478604 | AT34: =$AD$39*AS5 -> 44996.545 | AU34: =AV34/AV5 -> 0.024478604 | AV34: =$AD$39*AU5 -> 44996.545 | AW34: =AX34/AX5 -> 0.024478604 | AX34: =$AD$39*AW5 -> 44996.545 | AY34: =AZ34/AZ5 -> 0.024478604 | AZ34: =$AD$39*AY5 -> 44996.545 | BA34: =BB34/BB5 -> 0.024152475 | BB34: =$AD$39*BA5 -> 44397.056 | BC34: =BD34/BD5 -> 0.024595251 | BD34: =AF34+AH34+AJ34+AL34+AN34+AP34+AR34+AT34+AV34+AX34+AZ34+BB34 -> 542531.59
C35: Belén | D35: =E35/E6 -> 0.060946165 | E35: =$B$39*D6 -> 191651.31 | F35: =G35/G6 -> 0.060946165 | G35: =$B$39*F6 -> 191651.31 | H35: =I35/I6 -> 0.060946165 | I35: =$B$39*H6 -> 191651.31 | J35: =K35/K6 -> 0.060946165 | K35: =$B$39*J6 -> 191651.31 | L35: =M35/M6 -> 0.060946165 | M35: =$B$39*L6 -> 191651.31 | N35: =O35/O6 -> 0.058156187 | O35: =$B$39*N6 -> 182877.95 | P35: =Q35/Q6 -> 0.056397015 | Q35: =$B$39*P6 -> 186390.7 | R35: =S35/S6 -> 0.056151131 | S35: =$B$39*R6 -> 185578.06 | T35: =U35/U6 -> 0.056151131 | U35: =$B$39*T6 -> 185578.06 | V35: =W35/W6 -> 0.021365757 | W35: =$B$31*V6 -> 70613.285 | X35: =Y35/Y6 -> 0.021365757 | Y35: =$B$31*X6 -> 70613.285 | Z35: =AA35/AA6 -> 0.021185949 | AA35: =$B$31*Z6 -> 70019.022 | AB35: =AC35/AC6 -> 0.049355372 | AC35: =E35+G35+I35+K35+M35+O35+Q35+S35+U35+W35+Y35+AA35 -> 1909926.9 | AE35: =AF35/AF6 -> 0.022030519 | AF35: =$AD$37*AE6 -> 72810.307 | AG35: =AH35/AH6 -> 0.025335097 | AH35: =$AD$39*AG6 -> 83731.853 | AI35: =AJ35/AJ6 -> 0.025335097 | AJ35: =$AD$39*AI6 -> 83731.853 | AK35: =AL35/AL6 -> 0.025335097 | AL35: =$AD$39*AK6 -> 83731.853 | AM35: =AN35/AN6 -> 0.025335097 | AN35: =$AD$39*AM6 -> 83731.853 | AO35: =AP35/AP6 -> 0.025094434 | AP35: =$AD$39*AO6 -> 82936.467 | AQ35: =AR35/AR6 -> 0.02461078 | AR35: =$AD$39*AQ6 -> 86218.283 | AS35: =AT35/AT6 -> 0.024478604 | AT35: =$AD$39*AS6 -> 85755.233 | AU35: =AV35/AV6 -> 0.024478604 | AV35: =$AD$39*AU6 -> 85755.233 | AW35: =AX35/AX6 -> 0.024478604 | AX35: =$AD$39*AW6 -> 85755.233 | AY35: =AZ35/AZ6 -> 0.024478604 | AZ35: =$AD$39*AY6 -> 85755.233 | BA35: =BB35/BB6 -> 0.024152475 | BB35: =$AD$39*BA6 -> 84612.717 | BC35: =BD35/BD6 -> 0.024590912 | BD35: =AF35+AH35+AJ35+AL35+AN35+AP35+AR35+AT35+AV35+AX35+AZ35+BB35 -> 1004526.1
C36: Ocarinas | D36: =E36/E7 -> 0.060946165 | E36: =$B$39*D7 -> 92638.171 | F36: =G36/G7 -> 0.060946165 | G36: =$B$39*F7 -> 92638.171 | H36: =I36/I7 -> 0.060946165 | I36: =$B$39*H7 -> 92638.171 | J36: =K36/K7 -> 0.060946165 | K36: =$B$39*J7 -> 92638.171 | L36: =M36/M7 -> 0.060946165 | M36: =$B$39*L7 -> 92638.171 | N36: =O36/O7 -> 0.058156187 | O36: =$B$39*N7 -> 113404.56 | P36: =Q36/Q7 -> 0.056397015 | Q36: =$B$39*P7 -> 118433.73 | R36: =S36/S7 -> 0.056151131 | S36: =$B$39*R7 -> 117917.37 | T36: =U36/U7 -> 0.056151131 | U36: =$B$39*T7 -> 117917.37 | V36: =W36/W7 -> 0.021365757 | W36: =$B$31*V7 -> 44868.09 | X36: =Y36/Y7 -> 0.021365757 | Y36: =$B$31*X7 -> 44868.09 | Z36: =AA36/AA7 -> 0.021185949 | AA36: =$B$31*Z7 -> 44490.492 | AB36: =AC36/AC7 -> 0.048085353 | AC36: =E36+G36+I36+K36+M36+O36+Q36+S36+U36+W36+Y36+AA36 -> 1065090.6 | AE36: =AF36/AF7 -> 0.022030519 | AF36: =$AD$37*AE7 -> 35194.195 | AG36: =AH36/AH7 -> 0.025335097 | AH36: =$AD$39*AG7 -> 40473.325 | AI36: =AJ36/AJ7 -> 0.025335097 | AJ36: =$AD$39*AI7 -> 40473.325 | AK36: =AL36/AL7 -> 0.025335097 | AL36: =$AD$39*AK7 -> 40473.325 | AM36: =AN36/AN7 -> 0.025335097 | AN36: =$AD$39*AM7 -> 40473.325 | AO36: =AP36/AP7 -> 0.025094434 | AP36: =$AD$39*AO7 -> 42494.192 | AQ36: =AR36/AR7 -> 0.02461078 | AR36: =$AD$39*AQ7 -> 41675.186 | AS36: =AT36/AT7 -> 0.024478604 | AT36: =$AD$39*AS7 -> 41451.362 | AU36: =AV36/AV7 -> 0.024478604 | AV36: =$AD$39*AU7 -> 41451.362 | AW36: =AX36/AX7 -> 0.024478604 | AX36: =$AD$39*AW7 -> 41451.362 | AY36: =AZ36/AZ7 -> 0.024478604 | AZ36: =$AD$39*AY7 -> 41451.362 | BA36: =BB36/BB7 -> 0.024152475 | BB36: =$AD$39*BA7 -> 40899.106 | BC36: =BD36/BD7 -> 0.024593344 | BD36: =AF36+AH36+AJ36+AL36+AN36+AP36+AR36+AT36+AV36+AX36+AZ36+BB36 -> 487961.43
B37: 467800 | C37: Pedregal | D37: =E37/E8 -> 0.060946165 | E37: =$B$39*D8 -> 30473.082 | F37: =G37/G8 -> 0.060946165 | G37: =$B$39*F8 -> 30473.082 | H37: =I37/I8 -> 0.060946165 | I37: =$B$39*H8 -> 30473.082 | J37: =K37/K8 -> 0.060946165 | K37: =$B$39*J8 -> 30473.082 | L37: =M37/M8 -> 0.060946165 | M37: =$B$39*L8 -> 30473.082 | N37: =O37/O8 -> 0.058156187 | O37: =$B$39*N8 -> 30561.076 | P37: =Q37/Q8 -> 0.056397015 | Q37: =$B$39*P8 -> 29636.631 | R37: =S37/S8 -> 0.056151131 | S37: =$B$39*R8 -> 29507.419 | T37: =U37/U8 -> 0.056151131 | U37: =$B$39*T8 -> 29507.419 | V37: =W37/W8 -> 0.021365757 | W37: =$B$31*V8 -> 11227.705 | X37: =Y37/Y8 -> 0.021365757 | Y37: =$B$31*X8 -> 11227.705 | Z37: =AA37/AA8 -> 0.021185949 | AA37: =$B$31*Z8 -> 11133.216 | AB37: =AC37/AC8 -> 0.049391695 | AC37: =E37+G37+I37+K37+M37+O37+Q37+S37+U37+W37+Y37+AA37 -> 305166.59 | AD37: 220186 | AE37: =AF37/AF8 -> 0.022030519 | AF37: =$AD$37*AE8 -> 11577.038 | AG37: =AH37/AH8 -> 0.025335097 | AH37: =$AD$39*AG8 -> 13313.594 | AI37: =AJ37/AJ8 -> 0.025335097 | AJ37: =$AD$39*AI8 -> 13313.594 | AK37: =AL37/AL8 -> 0.025335097 | AL37: =$AD$39*AK8 -> 13313.594 | AM37: =AN37/AN8 -> 0.025335097 | AN37: =$AD$39*AM8 -> 13313.594 | AO37: =AP37/AP8 -> 0.025094434 | AP37: =$AD$39*AO8 -> 13187.125 | AQ37: =AR37/AR8 -> 0.02461078 | AR37: =$AD$39*AQ8 -> 12932.965 | AS37: =AT37/AT8 -> 0.024478604 | AT37: =$AD$39*AS8 -> 12863.506 | AU37: =AV37/AV8 -> 0.024478604 | AV37: =$AD$39*AU8 -> 12863.506 | AW37: =AX37/AX8 -> 0.024478604 | AX37: =$AD$39*AW8 -> 12863.506 | AY37: =AZ37/AZ8 -> 0.024478604 | AZ37: =$AD$39*AY8 -> 12863.506 | BA37: =BB37/BB8 -> 0.024152475 | BB37: =$AD$39*BA8 -> 13453.653 | BC37: =BD37/BD8 -> 0.024593048 | BD37: =AF37+AH37+AJ37+AL37+AN37+AP37+AR37+AT37+AV37+AX37+AZ37+BB37 -> 155859.18
B38: 0.237 | C38: Rivera del Valle | D38: =E38/E9 -> 0.060946165 | E38: =$B$39*D9 -> 104522.67 | F38: =G38/G9 -> 0.060946165 | G38: =$B$39*F9 -> 104522.67 | H38: =I38/I9 -> 0.060946165 | I38: =$B$39*H9 -> 104522.67 | J38: =K38/K9 -> 0.060946165 | K38: =$B$39*J9 -> 104522.67 | L38: =M38/M9 -> 0.060946165 | M38: =$B$39*L9 -> 104522.67 | N38: =O38/O9 -> 0.058156187 | O38: =$B$39*N9 -> 99737.861 | P38: =Q38/Q9 -> 0.056397015 | Q38: =$B$39*P9 -> 96720.881 | R38: =S38/S9 -> 0.056151131 | S38: =$B$39*R9 -> 96299.189 | T38: =U38/U9 -> 0.056151131 | U38: =$B$39*T9 -> 96299.189 | V38: =W38/W9 -> 0.021365757 | W38: =$B$31*V9 -> 36642.274 | X38: =Y38/Y9 -> 0.021365757 | Y38: =$B$31*X9 -> 36642.274 | Z38: =AA38/AA9 -> 0.021185949 | AA38: =$B$31*Z9 -> 38186.931 | AB38: =AC38/AC9 -> 0.049504957 | AC38: =E38+G38+I38+K38+M38+O38+Q38+S38+U38+W38+Y38+AA38 -> 1023142 | AD38: 0.15 | AE38: =AF38/AF9 -> 0.022030519 | AF38: =$AD$37*AE9 -> 39709.24 | AG38: =AH38/AH9 -> 0.025335097 | AH38: =$AD$39*AG9 -> 45665.626 | AI38: =AJ38/AJ9 -> 0.025335097 | AJ38: =$AD$39*AI9 -> 45665.626 | AK38: =AL38/AL9 -> 0.025335097 | AL38: =$AD$39*AK9 -> 45665.626 | AM38: =AN38/AN9 -> 0.025335097 | AN38: =$AD$39*AM9 -> 45665.626 | AO38: =AP38/AP9 -> 0.025094434 | AP38: =$AD$39*AO9 -> 45231.839 | AQ38: =AR38/AR9 -> 0.02461078 | AR38: =$AD$39*AQ9 -> 44360.07 | AS38: =AT38/AT9 -> 0.024478604 | AT38: =$AD$39*AS9 -> 44121.826 | AU38: =AV38/AV9 -> 0.024478604 | AV38: =$AD$39*AU9 -> 44121.826 | AW38: =AX38/AX9 -> 0.024478604 | AX38: =$AD$39*AW9 -> 44121.826 | AY38: =AZ38/AZ9 -> 0.024478604 | AZ38: =$AD$39*AY9 -> 44121.826 | BA38: =BB38/BB9 -> 0.024152475 | BB38: =$AD$39*BA9 -> 46146.031 | BC38: =BD38/BD9 -> 0.024593048 | BD38: =AF38+AH38+AJ38+AL38+AN38+AP38+AR38+AT38+AV38+AX38+AZ38+BB38 -> 534596.99
B39: =B37*(1+B38) -> 578668.6 | C39: La Ceja | D39: =E39/E10 -> 0.060946165 | E39: =$B$39*D10 -> 53693.571 | F39: =G39/G10 -> 0.060946165 | G39: =$B$39*F10 -> 53693.571 | H39: =I39/I10 -> 0.060946165 | I39: =$B$39*H10 -> 53693.571 | J39: =K39/K10 -> 0.060946165 | K39: =$B$39*J10 -> 53693.571 | L39: =M39/M10 -> 0.060946165 | M39: =$B$39*L10 -> 53693.571 | N39: =O39/O10 -> 0.058156187 | O39: =$B$39*N10 -> 51235.601 | P39: =Q39/Q10 -> 0.056397015 | Q39: =$B$39*P10 -> 49685.77 | R39: =S39/S10 -> 0.056151131 | S39: =$B$39*R10 -> 51992.073 | T39: =U39/U10 -> 0.056151131 | U39: =$B$39*T10 -> 51992.073 | V39: =W39/W10 -> 0.021365757 | W39: =$B$31*V10 -> 19783.217 | X39: =Y39/Y10 -> 0.021365757 | Y39: =$B$31*X10 -> 19783.217 | Z39: =AA39/AA10 -> 0.021185949 | AA39: =$B$31*Z10 -> 19616.727 | AB39: =AC39/AC10 -> 0.049326068 | AC39: =E39+G39+I39+K39+M39+O39+Q39+S39+U39+W39+Y39+AA39 -> 532556.53 | AD39: =AD37*(1+AD38) -> 253213.9 | AE39: =AF39/AF10 -> 0.022030519 | AF39: =$AD$37*AE10 -> 20398.741 | AG39: =AH39/AH10 -> 0.025335097 | AH39: =$AD$39*AG10 -> 23458.552 | AI39: =AJ39/AJ10 -> 0.025335097 | AJ39: =$AD$39*AI10 -> 23458.552 | AK39: =AL39/AL10 -> 0.025335097 | AL39: =$AD$39*AK10 -> 23458.552 | AM39: =AN39/AN10 -> 0.025335097 | AN39: =$AD$39*AM10 -> 23458.552 | AO39: =AP39/AP10 -> 0.025094434 | AP39: =$AD$39*AO10 -> 23235.714 | AQ39: =AR39/AR10 -> 0.02461078 | AR39: =$AD$39*AQ10 -> 22787.884 | AS39: =AT39/AT10 -> 0.024478604 | AT39: =$AD$39*AS10 -> 24025.428 | AU39: =AV39/AV10 -> 0.024478604 | AV39: =$AD$39*AU10 -> 24025.428 | AW39: =AX39/AX10 -> 0.024478604 | AX39: =$AD$39*AW10 -> 24025.428 | AY39: =AZ39/AZ10 -> 0.024478604 | AZ39: =$AD$39*AY10 -> 24025.428 | BA39: =BB39/BB10 -> 0.024152475 | BB39: =$AD$39*BA10 -> 23705.337 | BC39: =BD39/BD10 -> 0.024590815 | BD39: =AF39+AH39+AJ39+AL39+AN39+AP39+AR39+AT39+AV39+AX39+AZ39+BB39 -> 280063.6
B40: SST ERR | D40: =E40/E11 -> 0.060946165 | E40: =SUM(E34:E39) -> 578668.6 | F40: =G40/G11 -> 0.060946165 | G40: =SUM(G34:G39) -> 578668.6 | H40: =I40/I11 -> 0.060946165 | I40: =SUM(I34:I39) -> 578668.6 | J40: =K40/K11 -> 0.060946165 | K40: =SUM(K34:K39) -> 578668.6 | L40: =M40/M11 -> 0.060946165 | M40: =SUM(M34:M39) -> 578668.6 | N40: =O40/O11 -> 0.058156187 | O40: =SUM(O34:O39) -> 578668.6 | P40: =Q40/Q11 -> 0.056397015 | Q40: =SUM(Q34:Q39) -> 578668.6 | R40: =S40/S11 -> 0.056151131 | S40: =SUM(S34:S39) -> 578668.6 | T40: =U40/U11 -> 0.056151131 | U40: =SUM(U34:U39) -> 578668.6 | V40: =W40/W11 -> 0.021365757 | W40: =SUM(W34:W39) -> 220186 | X40: =Y40/Y11 -> 0.021365757 | Y40: =SUM(Y34:Y39) -> 220186 | Z40: =AA40/AA11 -> 0.021185949 | AA40: =SUM(AA34:AA39) -> 220186 | AB40: =AC40/AC11 -> 0.049191801 | AC40: =E40+G40+I40+K40+M40+O40+Q40+S40+U40+W40+Y40+AA40 -> 5868575.4 | AE40: =AF40/AF11 -> 0.022030519 | AF40: =SUM(AF34:AF39) -> 220186 | AG40: =AH40/AH11 -> 0.025335097 | AH40: =SUM(AH34:AH39) -> 253213.9 | AI40: =AJ40/AJ11 -> 0.025335097 | AJ40: =SUM(AJ34:AJ39) -> 253213.9 | AK40: =AL40/AL11 -> 0.025335097 | AL40: =SUM(AL34:AL39) -> 253213.9 | AM40: =AN40/AN11 -> 0.025335097 | AN40: =SUM(AN34:AN39) -> 253213.9 | AO40: =AP40/AP11 -> 0.025094434 | AP40: =SUM(AP34:AP39) -> 253213.9 | AQ40: =AR40/AR11 -> 0.02461078 | AR40: =SUM(AR34:AR39) -> 253213.9 | AS40: =AT40/AT11 -> 0.024478604 | AT40: =SUM(AT34:AT39) -> 253213.9 | AU40: =AV40/AV11 -> 0.024478604 | AV40: =SUM(AV34:AV39) -> 253213.9 | AW40: =AX40/AX11 -> 0.024478604 | AX40: =SUM(AX34:AX39) -> 253213.9 | AY40: =AZ40/AZ11 -> 0.024478604 | AZ40: =SUM(AZ34:AZ39) -> 253213.9 | BA40: =BB40/BB11 -> 0.024152475 | BB40: =SUM(BB34:BB39) -> 253213.9 | BC40: =BD40/BD11 -> 0.024592572 | BD40: =AF40+AH40+AJ40+AL40+AN40+AP40+AR40+AT40+AV40+AX40+AZ40+BB40 -> 3005538.9
C42: Yari | D42: =E42/E5 -> 0.2213855 | E42: =D5*$B$47 -> 383915.67 | F42: =G42/G5 -> 0.2213855 | G42: =E42 -> 383915.67 | H42: =I42/I5 -> 0.2213855 | I42: =G42 -> 383915.67 | J42: =K42/K5 -> 0.2213855 | K42: =I42 -> 383915.67 | L42: =M42/M5 -> 0.2213855 | M42: =K42 -> 383915.67 | N42: =O42/O5 -> 0.2213855 | O42: =M42 -> 383915.67 | P42: =Q42/Q5 -> 0.2213855 | Q42: =O42 -> 383915.67 | R42: =S42/S5 -> 0.2213855 | S42: =Q42 -> 383915.67 | T42: =U42/U5 -> 0.2213855 | U42: =S42 -> 383915.67 | V42: =W42/W5 -> 0.2213855 | W42: =U42 -> 383915.67 | X42: =Y42/Y5 -> 0.2213855 | Y42: =W42 -> 383915.67 | Z42: =AA42/AA5 -> 0.2213855 | AA42: =Y42 -> 383915.67 | AB42: =AC42/AC5 -> 0.2213855 | AC42: =E42+G42+I42+K42+M42+O42+Q42+S42+U42+W42+Y42+AA42 -> 4606988 | AE42: =AF42/AF5 -> 0.22335684 | AF42: =AE5*$AD$47 -> 410574.33 | AG42: =AH42/AH5 -> 0.22335684 | AH42: =AG5*$AD$47 -> 410574.33 | AI42: =AJ42/AJ5 -> 0.22335684 | AJ42: =AI5*$AD$47 -> 410574.33 | AK42: =AL42/AL5 -> 0.22335684 | AL42: =AK5*$AD$47 -> 410574.33 | AM42: =AN42/AN5 -> 0.22335684 | AN42: =AM5*$AD$47 -> 410574.33 | AO42: =AP42/AP5 -> 0.22123513 | AP42: =AO5*$AD$47 -> 406674.2 | AQ42: =AR42/AR5 -> 0.21697119 | AR42: =AQ5*$AD$47 -> 398836.22 | AS42: =AT42/AT5 -> 0.21580591 | AT42: =AS5*$AD$47 -> 396694.2 | AU42: =AV42/AV5 -> 0.21580591 | AV42: =AU5*$AD$47 -> 396694.2 | AW42: =AX42/AX5 -> 0.21580591 | AX42: =AW5*$AD$47 -> 396694.2 | AY42: =AZ42/AZ5 -> 0.21580591 | AZ42: =AY5*$AD$47 -> 396694.2 | BA42: =BB42/BB5 -> 0.21293073 | BB42: =BA5*$AD$47 -> 391409.05 | BC42: =BD42/BD5 -> 0.21926208 | BD42: =AF42+AH42+AJ42+AL42+AN42+AP42+AR42+AT42+AV42+AX42+AZ42+BB42 -> 4836567.9
C43: Belén | D43: =E43/E6 -> 0.2213855 | E43: =D6*$B$47 -> 696168.85 | F43: =G43/G6 -> 0.2213855 | G43: =E43 -> 696168.85 | H43: =I43/I6 -> 0.2213855 | I43: =G43 -> 696168.85 | J43: =K43/K6 -> 0.2213855 | K43: =I43 -> 696168.85 | L43: =M43/M6 -> 0.2213855 | M43: =K43 -> 696168.85 | N43: =O43/O6 -> 0.2213855 | O43: =M43 -> 696168.85 | P43: =Q43/Q6 -> 0.21064272 | Q43: =O43 -> 696168.85 | R43: =S43/S6 -> 0.21064272 | S43: =Q43 -> 696168.85 | T43: =U43/U6 -> 0.21064272 | U43: =S43 -> 696168.85 | V43: =W43/W6 -> 0.21064272 | W43: =U43 -> 696168.85 | X43: =Y43/Y6 -> 0.21064272 | Y43: =W43 -> 696168.85 | Z43: =AA43/AA6 -> 0.21064272 | AA43: =Y43 -> 696168.85 | AB43: =AC43/AC6 -> 0.21588055 | AC43: =E43+G43+I43+K43+M43+O43+Q43+S43+U43+W43+Y43+AA43 -> 8354026.2 | AE43: =AF43/AF6 -> 0.22335684 | AF43: =AE6*$AD$47 -> 738188.7 | AG43: =AH43/AH6 -> 0.22335684 | AH43: =AG6*$AD$47 -> 738188.7 | AI43: =AJ43/AJ6 -> 0.22335684 | AJ43: =AI6*$AD$47 -> 738188.7 | AK43: =AL43/AL6 -> 0.22335684 | AL43: =AK6*$AD$47 -> 738188.7 | AM43: =AN43/AN6 -> 0.22335684 | AN43: =AM6*$AD$47 -> 738188.7 | AO43: =AP43/AP6 -> 0.22123513 | AP43: =AO6*$AD$47 -> 731176.49 | AQ43: =AR43/AR6 -> 0.21697119 | AR43: =AQ6*$AD$47 -> 760109.33 | AS43: =AT43/AT6 -> 0.21580591 | AT43: =AS6*$AD$47 -> 756027.03 | AU43: =AV43/AV6 -> 0.21580591 | AV43: =AU6*$AD$47 -> 756027.03 | AW43: =AX43/AX6 -> 0.21580591 | AX43: =AW6*$AD$47 -> 756027.03 | AY43: =AZ43/AZ6 -> 0.21580591 | AZ43: =AY6*$AD$47 -> 756027.03 | BA43: =BB43/BB6 -> 0.21293073 | BB43: =BA6*$AD$47 -> 745954.48 | BC43: =BD43/BD6 -> 0.21915311 | BD43: =AF43+AH43+AJ43+AL43+AN43+AP43+AR43+AT43+AV43+AX43+AZ43+BB43 -> 8952291.9
C44: Ocarinas | D44: =E44/E7 -> 0.2213855 | E44: =D7*$B$47 -> 336505.96 | F44: =G44/G7 -> 0.2213855 | G44: =E44 -> 336505.96 | H44: =I44/I7 -> 0.2213855 | I44: =G44 -> 336505.96 | J44: =K44/K7 -> 0.2213855 | K44: =I44 -> 336505.96 | L44: =M44/M7 -> 0.2213855 | M44: =K44 -> 336505.96 | N44: =O44/O7 -> 0.17256716 | O44: =M44 -> 336505.96 | P44: =Q44/Q7 -> 0.16024094 | Q44: =O44 -> 336505.96 | R44: =S44/S7 -> 0.16024094 | S44: =Q44 -> 336505.96 | T44: =U44/U7 -> 0.16024094 | U44: =S44 -> 336505.96 | V44: =W44/W7 -> 0.16024094 | W44: =U44 -> 336505.96 | X44: =Y44/Y7 -> 0.16024094 | Y44: =W44 -> 336505.96 | Z44: =AA44/AA7 -> 0.16024094 | AA44: =Y44 -> 336505.96 | AB44: =AC44/AC7 -> 0.18230571 | AC44: =E44+G44+I44+K44+M44+O44+Q44+S44+U44+W44+Y44+AA44 -> 4038071.6 | AE44: =AF44/AF7 -> 0.22335684 | AF44: =AE7*$AD$47 -> 356817.03 | AG44: =AH44/AH7 -> 0.22335684 | AH44: =AG7*$AD$47 -> 356817.03 | AI44: =AJ44/AJ7 -> 0.22335684 | AJ44: =AI7*$AD$47 -> 356817.03 | AK44: =AL44/AL7 -> 0.22335684 | AL44: =AK7*$AD$47 -> 356817.03 | AM44: =AN44/AN7 -> 0.22335684 | AN44: =AM7*$AD$47 -> 356817.03 | AO44: =AP44/AP7 -> 0.22123513 | AP44: =AO7*$AD$47 -> 374633.2 | AQ44: =AR44/AR7 -> 0.21697119 | AR44: =AQ7*$AD$47 -> 367412.76 | AS44: =AT44/AT7 -> 0.21580591 | AT44: =AS7*$AD$47 -> 365439.51 | AU44: =AV44/AV7 -> 0.21580591 | AV44: =AU7*$AD$47 -> 365439.51 | AW44: =AX44/AX7 -> 0.21580591 | AX44: =AW7*$AD$47 -> 365439.51 | AY44: =AZ44/AZ7 -> 0.21580591 | AZ44: =AY7*$AD$47 -> 365439.51 | BA44: =BB44/BB7 -> 0.21293073 | BB44: =BA7*$AD$47 -> 360570.76 | BC44: =BD44/BD7 -> 0.21916317 | BD44: =AF44+AH44+AJ44+AL44+AN44+AP44+AR44+AT44+AV44+AX44+AZ44+BB44 -> 4348459.9
B45: 2000000 | C45: Pedregal | D45: =E45/E8 -> 0.2213855 | E45: =D8*$B$47 -> 110692.75 | F45: =G45/G8 -> 0.2213855 | G45: =E45 -> 110692.75 | H45: =I45/I8 -> 0.2213855 | I45: =G45 -> 110692.75 | J45: =K45/K8 -> 0.2213855 | K45: =I45 -> 110692.75 | L45: =M45/M8 -> 0.2213855 | M45: =K45 -> 110692.75 | N45: =O45/O8 -> 0.21064272 | O45: =M45 -> 110692.75 | P45: =Q45/Q8 -> 0.21064272 | Q45: =O45 -> 110692.75 | R45: =S45/S8 -> 0.21064272 | S45: =Q45 -> 110692.75 | T45: =U45/U8 -> 0.21064272 | U45: =S45 -> 110692.75 | V45: =W45/W8 -> 0.21064272 | W45: =U45 -> 110692.75 | X45: =Y45/Y8 -> 0.21064272 | Y45: =W45 -> 110692.75 | Z45: =AA45/AA8 -> 0.21064272 | AA45: =Y45 -> 110692.75 | AB45: =AC45/AC8 -> 0.21498956 | AC45: =E45+G45+I45+K45+M45+O45+Q45+S45+U45+W45+Y45+AA45 -> 1328313 | AD45: 2106000 | AE45: =AF45/AF8 -> 0.22335684 | AF45: =AE8*$AD$47 -> 117374.02 | AG45: =AH45/AH8 -> 0.22335684 | AH45: =AG8*$AD$47 -> 117374.02 | AI45: =AJ45/AJ8 -> 0.22335684 | AJ45: =AI8*$AD$47 -> 117374.02 | AK45: =AL45/AL8 -> 0.22335684 | AL45: =AK8*$AD$47 -> 117374.02 | AM45: =AN45/AN8 -> 0.22335684 | AN45: =AM8*$AD$47 -> 117374.02 | AO45: =AP45/AP8 -> 0.22123513 | AP45: =AO8*$AD$47 -> 116259.06 | AQ45: =AR45/AR8 -> 0.21697119 | AR45: =AQ8*$AD$47 -> 114018.36 | AS45: =AT45/AT8 -> 0.21580591 | AT45: =AS8*$AD$47 -> 113406 | AU45: =AV45/AV8 -> 0.21580591 | AV45: =AU8*$AD$47 -> 113406 | AW45: =AX45/AX8 -> 0.21580591 | AX45: =AW8*$AD$47 -> 113406 | AY45: =AZ45/AZ8 -> 0.21580591 | AZ45: =AY8*$AD$47 -> 113406 | BA45: =BB45/BB8 -> 0.21293073 | BB45: =BA8*$AD$47 -> 118608.8 | BC45: =BD45/BD8 -> 0.21923058 | BD45: =AF45+AH45+AJ45+AL45+AN45+AP45+AR45+AT45+AV45+AX45+AZ45+BB45 -> 1389380.4
B46: 0.051 | C46: Rivera del Valle | D46: =E46/E9 -> 0.2213855 | E46: =D9*$B$47 -> 379676.14 | F46: =G46/G9 -> 0.2213855 | G46: =E46 -> 379676.14 | H46: =I46/I9 -> 0.2213855 | I46: =G46 -> 379676.14 | J46: =K46/K9 -> 0.2213855 | K46: =I46 -> 379676.14 | L46: =M46/M9 -> 0.2213855 | M46: =K46 -> 379676.14 | N46: =O46/O9 -> 0.2213855 | O46: =M46 -> 379676.14 | P46: =Q46/Q9 -> 0.2213855 | Q46: =O46 -> 379676.14 | R46: =S46/S9 -> 0.2213855 | S46: =Q46 -> 379676.14 | T46: =U46/U9 -> 0.2213855 | U46: =S46 -> 379676.14 | V46: =W46/W9 -> 0.2213855 | W46: =U46 -> 379676.14 | X46: =Y46/Y9 -> 0.2213855 | Y46: =W46 -> 379676.14 | Z46: =AA46/AA9 -> 0.21064272 | AA46: =Y46 -> 379676.14 | AB46: =AC46/AC9 -> 0.2204486 | AC46: =E46+G46+I46+K46+M46+O46+Q46+S46+U46+W46+Y46+AA46 -> 4556113.6 | AD46: 0.06 | AE46: =AF46/AF9 -> 0.22335684 | AF46: =AE9*$AD$47 -> 402592.9 | AG46: =AH46/AH9 -> 0.22335684 | AH46: =AG9*$AD$47 -> 402592.9 | AI46: =AJ46/AJ9 -> 0.22335684 | AJ46: =AI9*$AD$47 -> 402592.9 | AK46: =AL46/AL9 -> 0.22335684 | AL46: =AK9*$AD$47 -> 402592.9 | AM46: =AN46/AN9 -> 0.22335684 | AN46: =AM9*$AD$47 -> 402592.9 | AO46: =AP46/AP9 -> 0.22123513 | AP46: =AO9*$AD$47 -> 398768.58 | AQ46: =AR46/AR9 -> 0.21697119 | AR46: =AQ9*$AD$47 -> 391082.98 | AS46: =AT46/AT9 -> 0.21580591 | AT46: =AS9*$AD$47 -> 388982.6 | AU46: =AV46/AV9 -> 0.21580591 | AV46: =AU9*$AD$47 -> 388982.6 | AW46: =AX46/AX9 -> 0.21580591 | AX46: =AW9*$AD$47 -> 388982.6 | AY46: =AZ46/AZ9 -> 0.21580591 | AZ46: =AY9*$AD$47 -> 388982.6 | BA46: =BB46/BB9 -> 0.21293073 | BB46: =BA9*$AD$47 -> 406828.19 | BC46: =BD46/BD9 -> 0.21923058 | BD46: =AF46+AH46+AJ46+AL46+AN46+AP46+AR46+AT46+AV46+AX46+AZ46+BB46 -> 4765574.6
B47: =B45*(1+B46) -> 2102000 | C47: La Ceja | D47: =E47/E10 -> 0.2213855 | E47: =D10*$B$47 -> 195040.63 | F47: =G47/G10 -> 0.2213855 | G47: =E47 -> 195040.63 | H47: =I47/I10 -> 0.2213855 | I47: =G47 -> 195040.63 | J47: =K47/K10 -> 0.2213855 | K47: =I47 -> 195040.63 | L47: =M47/M10 -> 0.2213855 | M47: =K47 -> 195040.63 | N47: =O47/O10 -> 0.2213855 | O47: =M47 -> 195040.63 | P47: =Q47/Q10 -> 0.2213855 | Q47: =O47 -> 195040.63 | R47: =S47/S10 -> 0.21064272 | S47: =Q47 -> 195040.63 | T47: =U47/U10 -> 0.21064272 | U47: =S47 -> 195040.63 | V47: =W47/W10 -> 0.21064272 | W47: =U47 -> 195040.63 | X47: =Y47/Y10 -> 0.21064272 | Y47: =W47 -> 195040.63 | Z47: =AA47/AA10 -> 0.21064272 | AA47: =Y47 -> 195040.63 | AB47: =AC47/AC10 -> 0.21677895 | AC47: =E47+G47+I47+K47+M47+O47+Q47+S47+U47+W47+Y47+AA47 -> 2340487.5 | AD47: =AD45*(1+AD46) -> 2232360 | AE47: =AF47/AF10 -> 0.22335684 | AF47: =AE10*$AD$47 -> 206813.03 | AG47: =AH47/AH10 -> 0.22335684 | AH47: =AG10*$AD$47 -> 206813.03 | AI47: =AJ47/AJ10 -> 0.22335684 | AJ47: =AI10*$AD$47 -> 206813.03 | AK47: =AL47/AL10 -> 0.22335684 | AL47: =AK10*$AD$47 -> 206813.03 | AM47: =AN47/AN10 -> 0.22335684 | AN47: =AM10*$AD$47 -> 206813.03 | AO47: =AP47/AP10 -> 0.22123513 | AP47: =AO10*$AD$47 -> 204848.47 | AQ47: =AR47/AR10 -> 0.21697119 | AR47: =AQ10*$AD$47 -> 200900.35 | AS47: =AT47/AT10 -> 0.21580591 | AT47: =AS10*$AD$47 -> 211810.66 | AU47: =AV47/AV10 -> 0.21580591 | AV47: =AU10*$AD$47 -> 211810.66 | AW47: =AX47/AX10 -> 0.21580591 | AX47: =AW10*$AD$47 -> 211810.66 | AY47: =AZ47/AZ10 -> 0.21580591 | AZ47: =AY10*$AD$47 -> 211810.66 | BA47: =BB47/BB10 -> 0.21293073 | BB47: =BA10*$AD$47 -> 208988.71 | BC47: =BD47/BD10 -> 0.21916375 | BD47: =AF47+AH47+AJ47+AL47+AN47+AP47+AR47+AT47+AV47+AX47+AZ47+BB47 -> 2496045.3
B48: DUEÑA | D48: =E48/E11 -> 0.2213855 | E48: =SUM(E42:E47) -> 2102000 | F48: =G48/G11 -> 0.2213855 | G48: =SUM(G42:G47) -> 2102000 | H48: =I48/I11 -> 0.2213855 | I48: =SUM(I42:I47) -> 2102000 | J48: =K48/K11 -> 0.2213855 | K48: =SUM(K42:K47) -> 2102000 | L48: =M48/M11 -> 0.2213855 | M48: =SUM(M42:M47) -> 2102000 | N48: =O48/O11 -> 0.21125097 | O48: =SUM(O42:O47) -> 2102000 | P48: =Q48/Q11 -> 0.20486082 | Q48: =SUM(Q42:Q47) -> 2102000 | R48: =S48/S11 -> 0.20396765 | S48: =SUM(S42:S47) -> 2102000 | T48: =U48/U11 -> 0.20396765 | U48: =SUM(U42:U47) -> 2102000 | V48: =W48/W11 -> 0.20396765 | W48: =SUM(W42:W47) -> 2102000 | X48: =Y48/Y11 -> 0.20396765 | Y48: =SUM(Y42:Y47) -> 2102000 | Z48: =AA48/AA11 -> 0.20225111 | AA48: =SUM(AA42:AA47) -> 2102000 | AB48: =AC48/AC11 -> 0.2114336 | AC48: =E48+G48+I48+K48+M48+O48+Q48+S48+U48+W48+Y48+AA48 -> 25224000 | AE48: =AF48/AF11 -> 0.22335684 | AF48: =SUM(AF42:AF47) -> 2232360 | AG48: =AH48/AH11 -> 0.22335684 | AH48: =SUM(AH42:AH47) -> 2232360 | AI48: =AJ48/AJ11 -> 0.22335684 | AJ48: =SUM(AJ42:AJ47) -> 2232360 | AK48: =AL48/AL11 -> 0.22335684 | AL48: =SUM(AL42:AL47) -> 2232360 | AM48: =AN48/AN11 -> 0.22335684 | AN48: =SUM(AN42:AN47) -> 2232360 | AO48: =AP48/AP11 -> 0.22123513 | AP48: =SUM(AP42:AP47) -> 2232360 | AQ48: =AR48/AR11 -> 0.21697119 | AR48: =SUM(AR42:AR47) -> 2232360 | AS48: =AT48/AT11 -> 0.21580591 | AT48: =SUM(AT42:AT47) -> 2232360 | AU48: =AV48/AV11 -> 0.21580591 | AV48: =SUM(AV42:AV47) -> 2232360 | AW48: =AX48/AX11 -> 0.21580591 | AX48: =SUM(AX42:AX47) -> 2232360 | AY48: =AZ48/AZ11 -> 0.21580591 | AZ48: =SUM(AZ42:AZ47) -> 2232360 | BA48: =BB48/BB11 -> 0.21293073 | BB48: =SUM(BB42:BB47) -> 2232360 | BC48: =BD48/BD11 -> 0.2191932 | BD48: =AF48+AH48+AJ48+AL48+AN48+AP48+AR48+AT48+AV48+AX48+AZ48+BB48 -> 26788320
C50: Yari | D50: =E50/E5 -> 0.2 | E50: =$B$55*E5 -> 346830 | F50: =G50/G5 -> 0.2 | G50: =$B$55*G5 -> 346830 | H50: =I50/I5 -> 0.2 | I50: =$B$55*I5 -> 346830 | J50: =K50/K5 -> 0.2 | K50: =$B$55*K5 -> 346830 | L50: =M50/M5 -> 0.2 | M50: =$B$55*M5 -> 346830 | N50: =O50/O5 -> 0.2 | O50: =$B$55*O5 -> 346830 | P50: =Q50/Q5 -> 0.2 | Q50: =$B$55*Q5 -> 346830 | R50: =S50/S5 -> 0.2 | S50: =$B$55*S5 -> 346830 | T50: =U50/U5 -> 0.2 | U50: =$B$55*U5 -> 346830 | V50: =W50/W5 -> 0.2 | W50: =$B$55*W5 -> 346830 | X50: =Y50/Y5 -> 0.2 | Y50: =$B$55*Y5 -> 346830 | Z50: =AA50/AA5 -> 0.2 | AA50: =$B$55*AA5 -> 346830 | AB50: =AC50/AC5 -> 0.2 | AC50: =E50+G50+I50+K50+M50+O50+Q50+S50+U50+W50+Y50+AA50 -> 4161960 | AE50: =AF50/AF5 -> 0.2 | AF50: =$AD$55*AF5 -> 367639.8 | AG50: =AH50/AH5 -> 0.2 | AH50: =$AD$55*AH5 -> 367639.8 | AI50: =AJ50/AJ5 -> 0.2 | AJ50: =$AD$55*AJ5 -> 367639.8 | AK50: =AL50/AL5 -> 0.2 | AL50: =$AD$55*AL5 -> 367639.8 | AM50: =AN50/AN5 -> 0.2 | AN50: =$AD$55*AN5 -> 367639.8 | AO50: =AP50/AP5 -> 0.2 | AP50: =$AD$55*AP5 -> 367639.8 | AQ50: =AR50/AR5 -> 0.2 | AR50: =$AD$55*AR5 -> 367639.8 | AS50: =AT50/AT5 -> 0.2 | AT50: =$AD$55*AT5 -> 367639.8 | AU50: =AV50/AV5 -> 0.2 | AV50: =$AD$55*AV5 -> 367639.8 | AW50: =AX50/AX5 -> 0.2 | AX50: =$AD$55*AX5 -> 367639.8 | AY50: =AZ50/AZ5 -> 0.2 | AZ50: =$AD$55*AZ5 -> 367639.8 | BA50: =BB50/BB5 -> 0.2 | BB50: =$AD$55*BB5 -> 367639.8 | BC50: =BD50/BD5 -> 0.2 | BD50: =AF50+AH50+AJ50+AL50+AN50+AP50+AR50+AT50+AV50+AX50+AZ50+BB50 -> 4411677.6
C51: Belén | D51: =E51/E6 -> 0.2 | E51: =$B$55*E6 -> 628920 | F51: =G51/G6 -> 0.2 | G51: =$B$55*G6 -> 628920 | H51: =I51/I6 -> 0.2 | I51: =$B$55*I6 -> 628920 | J51: =K51/K6 -> 0.2 | K51: =$B$55*K6 -> 628920 | L51: =M51/M6 -> 0.2 | M51: =$B$55*M6 -> 628920 | N51: =O51/O6 -> 0.2 | O51: =$B$55*O6 -> 628920 | P51: =Q51/Q6 -> 0.2 | Q51: =$B$55*Q6 -> 660994.92 | R51: =S51/S6 -> 0.2 | S51: =$B$55*S6 -> 660994.92 | T51: =U51/U6 -> 0.2 | U51: =$B$55*U6 -> 660994.92 | V51: =W51/W6 -> 0.2 | W51: =$B$55*W6 -> 660994.92 | X51: =Y51/Y6 -> 0.2 | Y51: =$B$55*Y6 -> 660994.92 | Z51: =AA51/AA6 -> 0.2 | AA51: =$B$55*AA6 -> 660994.92 | AB51: =AC51/AC6 -> 0.2 | AC51: =E51+G51+I51+K51+M51+O51+Q51+S51+U51+W51+Y51+AA51 -> 7739489.5 | AE51: =AF51/AF6 -> 0.2 | AF51: =$AD$55*AF6 -> 660994.92 | AG51: =AH51/AH6 -> 0.2 | AH51: =$AD$55*AH6 -> 660994.92 | AI51: =AJ51/AJ6 -> 0.2 | AJ51: =$AD$55*AJ6 -> 660994.92 | AK51: =AL51/AL6 -> 0.2 | AL51: =$AD$55*AL6 -> 660994.92 | AM51: =AN51/AN6 -> 0.2 | AN51: =$AD$55*AN6 -> 660994.92 | AO51: =AP51/AP6 -> 0.2 | AP51: =$AD$55*AP6 -> 660994.92 | AQ51: =AR51/AR6 -> 0.2 | AR51: =$AD$55*AR6 -> 700654.62 | AS51: =AT51/AT6 -> 0.2 | AT51: =$AD$55*AT6 -> 700654.62 | AU51: =AV51/AV6 -> 0.2 | AV51: =$AD$55*AV6 -> 700654.62 | AW51: =AX51/AX6 -> 0.2 | AX51: =$AD$55*AX6 -> 700654.62 | AY51: =AZ51/AZ6 -> 0.2 | AZ51: =$AD$55*AZ6 -> 700654.62 | BA51: =BB51/BB6 -> 0.2 | BB51: =$AD$55*BB6 -> 700654.62 | BC51: =BD51/BD6 -> 0.2 | BD51: =AF51+AH51+AJ51+AL51+AN51+AP51+AR51+AT51+AV51+AX51+AZ51+BB51 -> 8169897.2
C52: Ocarinas | D52: =E52/E7 -> 0.2 | E52: =$B$55*E7 -> 304000 | F52: =G52/G7 -> 0.2 | G52: =$B$55*G7 -> 304000 | H52: =I52/I7 -> 0.2 | I52: =$B$55*I7 -> 304000 | J52: =K52/K7 -> 0.2 | K52: =$B$55*K7 -> 304000 | L52: =M52/M7 -> 0.2 | M52: =$B$55*M7 -> 304000 | N52: =O52/O7 -> 0.2 | O52: =$B$55*O7 -> 390000 | P52: =Q52/Q7 -> 0.2 | Q52: =$B$55*Q7 -> 420000 | R52: =S52/S7 -> 0.2 | S52: =$B$55*S7 -> 420000 | T52: =U52/U7 -> 0.2 | U52: =$B$55*U7 -> 420000 | V52: =W52/W7 -> 0.2 | W52: =$B$55*W7 -> 420000 | X52: =Y52/Y7 -> 0.2 | Y52: =$B$55*Y7 -> 420000 | Z52: =AA52/AA7 -> 0.2 | AA52: =$B$55*AA7 -> 420000 | AB52: =AC52/AC7 -> 0.2 | AC52: =E52+G52+I52+K52+M52+O52+Q52+S52+U52+W52+Y52+AA52 -> 4430000 | AE52: =AF52/AF7 -> 0.2 | AF52: =$AD$55*AF7 -> 319504 | AG52: =AH52/AH7 -> 0.2 | AH52: =$AD$55*AH7 -> 319504 | AI52: =AJ52/AJ7 -> 0.2 | AJ52: =$AD$55*AJ7 -> 319504 | AK52: =AL52/AL7 -> 0.2 | AL52: =$AD$55*AL7 -> 319504 | AM52: =AN52/AN7 -> 0.2 | AN52: =$AD$55*AN7 -> 319504 | AO52: =AP52/AP7 -> 0.2 | AP52: =$AD$55*AP7 -> 338674.24 | AQ52: =AR52/AR7 -> 0.2 | AR52: =$AD$55*AR7 -> 338674.24 | AS52: =AT52/AT7 -> 0.2 | AT52: =$AD$55*AT7 -> 338674.24 | AU52: =AV52/AV7 -> 0.2 | AV52: =$AD$55*AV7 -> 338674.24 | AW52: =AX52/AX7 -> 0.2 | AX52: =$AD$55*AX7 -> 338674.24 | AY52: =AZ52/AZ7 -> 0.2 | AZ52: =$AD$55*AZ7 -> 338674.24 | BA52: =BB52/BB7 -> 0.2 | BB52: =$AD$55*BB7 -> 338674.24 | BC52: =BD52/BD7 -> 0.2 | BD52: =AF52+AH52+AJ52+AL52+AN52+AP52+AR52+AT52+AV52+AX52+AZ52+BB52 -> 3968239.7
C53: Pedregal | D53: =E53/E8 -> 0.2 | E53: =$B$55*E8 -> 100000 | F53: =G53/G8 -> 0.2 | G53: =$B$55*G8 -> 100000 | H53: =I53/I8 -> 0.2 | I53: =$B$55*I8 -> 100000 | J53: =K53/K8 -> 0.2 | K53: =$B$55*K8 -> 100000 | L53: =M53/M8 -> 0.2 | M53: =$B$55*M8 -> 100000 | N53: =O53/O8 -> 0.2 | O53: =$B$55*O8 -> 105100 | P53: =Q53/Q8 -> 0.2 | Q53: =$B$55*Q8 -> 105100 | R53: =S53/S8 -> 0.2 | S53: =$B$55*S8 -> 105100 | T53: =U53/U8 -> 0.2 | U53: =$B$55*U8 -> 105100 | V53: =W53/W8 -> 0.2 | W53: =$B$55*W8 -> 105100 | X53: =Y53/Y8 -> 0.2 | Y53: =$B$55*Y8 -> 105100 | Z53: =AA53/AA8 -> 0.2 | AA53: =$B$55*AA8 -> 105100 | AB53: =AC53/AC8 -> 0.2 | AC53: =E53+G53+I53+K53+M53+O53+Q53+S53+U53+W53+Y53+AA53 -> 1235700 | AE53: =AF53/AF8 -> 0.2 | AF53: =$AD$55*AF8 -> 105100 | AG53: =AH53/AH8 -> 0.2 | AH53: =$AD$55*AH8 -> 105100 | AI53: =AJ53/AJ8 -> 0.2 | AJ53: =$AD$55*AJ8 -> 105100 | AK53: =AL53/AL8 -> 0.2 | AL53: =$AD$55*AL8 -> 105100 | AM53: =AN53/AN8 -> 0.2 | AN53: =$AD$55*AN8 -> 105100 | AO53: =AP53/AP8 -> 0.2 | AP53: =$AD$55*AP8 -> 105100 | AQ53: =AR53/AR8 -> 0.2 | AR53: =$AD$55*AR8 -> 105100 | AS53: =AT53/AT8 -> 0.2 | AT53: =$AD$55*AT8 -> 105100 | AU53: =AV53/AV8 -> 0.2 | AV53: =$AD$55*AV8 -> 105100 | AW53: =AX53/AX8 -> 0.2 | AX53: =$AD$55*AX8 -> 105100 | AY53: =AZ53/AZ8 -> 0.2 | AZ53: =$AD$55*AZ8 -> 105100 | BA53: =BB53/BB8 -> 0.2 | BB53: =$AD$55*BB8 -> 111406 | BC53: =BD53/BD8 -> 0.2 | BD53: =AF53+AH53+AJ53+AL53+AN53+AP53+AR53+AT53+AV53+AX53+AZ53+BB53 -> 1267506
C54: Rivera del Valle | D54: =E54/E9 -> 0.2 | E54: =$B$55*E9 -> 343000 | F54: =G54/G9 -> 0.2 | G54: =$B$55*G9 -> 343000 | H54: =I54/I9 -> 0.2 | I54: =$B$55*I9 -> 343000 | J54: =K54/K9 -> 0.2 | K54: =$B$55*K9 -> 343000 | L54: =M54/M9 -> 0.2 | M54: =$B$55*M9 -> 343000 | N54: =O54/O9 -> 0.2 | O54: =$B$55*O9 -> 343000 | P54: =Q54/Q9 -> 0.2 | Q54: =$B$55*Q9 -> 343000 | R54: =S54/S9 -> 0.2 | S54: =$B$55*S9 -> 343000 | T54: =U54/U9 -> 0.2 | U54: =$B$55*U9 -> 343000 | V54: =W54/W9 -> 0.2 | W54: =$B$55*W9 -> 343000 | X54: =Y54/Y9 -> 0.2 | Y54: =$B$55*Y9 -> 343000 | Z54: =AA54/AA9 -> 0.2 | AA54: =$B$55*AA9 -> 360493 | AB54: =AC54/AC9 -> 0.2 | AC54: =E54+G54+I54+K54+M54+O54+Q54+S54+U54+W54+Y54+AA54 -> 4133493 | AE54: =AF54/AF9 -> 0.2 | AF54: =$AD$55*AF9 -> 360493 | AG54: =AH54/AH9 -> 0.2 | AH54: =$AD$55*AH9 -> 360493 | AI54: =AJ54/AJ9 -> 0.2 | AJ54: =$AD$55*AJ9 -> 360493 | AK54: =AL54/AL9 -> 0.2 | AL54: =$AD$55*AL9 -> 360493 | AM54: =AN54/AN9 -> 0.2 | AN54: =$AD$55*AN9 -> 360493 | AO54: =AP54/AP9 -> 0.2 | AP54: =$AD$55*AP9 -> 360493 | AQ54: =AR54/AR9 -> 0.2 | AR54: =$AD$55*AR9 -> 360493 | AS54: =AT54/AT9 -> 0.2 | AT54: =$AD$55*AT9 -> 360493 | AU54: =AV54/AV9 -> 0.2 | AV54: =$AD$55*AV9 -> 360493 | AW54: =AX54/AX9 -> 0.2 | AX54: =$AD$55*AX9 -> 360493 | AY54: =AZ54/AZ9 -> 0.2 | AZ54: =$AD$55*AZ9 -> 360493 | BA54: =BB54/BB9 -> 0.2 | BB54: =$AD$55*BB9 -> 382122.58 | BC54: =BD54/BD9 -> 0.2 | BD54: =AF54+AH54+AJ54+AL54+AN54+AP54+AR54+AT54+AV54+AX54+AZ54+BB54 -> 4347545.6
B55: 0.2 | C55: La Ceja | D55: =E55/E10 -> 0.2 | E55: =$B$55*E10 -> 176200 | F55: =G55/G10 -> 0.2 | G55: =$B$55*G10 -> 176200 | H55: =I55/I10 -> 0.2 | I55: =$B$55*I10 -> 176200 | J55: =K55/K10 -> 0.2 | K55: =$B$55*K10 -> 176200 | L55: =M55/M10 -> 0.2 | M55: =$B$55*M10 -> 176200 | N55: =O55/O10 -> 0.2 | O55: =$B$55*O10 -> 176200 | P55: =Q55/Q10 -> 0.2 | Q55: =$B$55*Q10 -> 176200 | R55: =S55/S10 -> 0.2 | S55: =$B$55*S10 -> 185186.2 | T55: =U55/U10 -> 0.2 | U55: =$B$55*U10 -> 185186.2 | V55: =W55/W10 -> 0.2 | W55: =$B$55*W10 -> 185186.2 | X55: =Y55/Y10 -> 0.2 | Y55: =$B$55*Y10 -> 185186.2 | Z55: =AA55/AA10 -> 0.2 | AA55: =$B$55*AA10 -> 185186.2 | AB55: =AC55/AC10 -> 0.2 | AC55: =E55+G55+I55+K55+M55+O55+Q55+S55+U55+W55+Y55+AA55 -> 2159331 | AD55: 0.2 | AE55: =AF55/AF10 -> 0.2 | AF55: =$AD$55*AF10 -> 185186.2 | AG55: =AH55/AH10 -> 0.2 | AH55: =$AD$55*AH10 -> 185186.2 | AI55: =AJ55/AJ10 -> 0.2 | AJ55: =$AD$55*AJ10 -> 185186.2 | AK55: =AL55/AL10 -> 0.2 | AL55: =$AD$55*AL10 -> 185186.2 | AM55: =AN55/AN10 -> 0.2 | AN55: =$AD$55*AN10 -> 185186.2 | AO55: =AP55/AP10 -> 0.2 | AP55: =$AD$55*AP10 -> 185186.2 | AQ55: =AR55/AR10 -> 0.2 | AR55: =$AD$55*AR10 -> 185186.2 | AS55: =AT55/AT10 -> 0.2 | AT55: =$AD$55*AT10 -> 196297.37 | AU55: =AV55/AV10 -> 0.2 | AV55: =$AD$55*AV10 -> 196297.37 | AW55: =AX55/AX10 -> 0.2 | AX55: =$AD$55*AX10 -> 196297.37 | AY55: =AZ55/AZ10 -> 0.2 | AZ55: =$AD$55*AZ10 -> 196297.37 | BA55: =BB55/BB10 -> 0.2 | BB55: =$AD$55*BB10 -> 196297.37 | BC55: =BD55/BD10 -> 0.2 | BD55: =AF55+AH55+AJ55+AL55+AN55+AP55+AR55+AT55+AV55+AX55+AZ55+BB55 -> 2277790.3
B56: MANTENIMIENTO | D56: =E56/E11 -> 0.2 | E56: =SUM(E50:E55) -> 1898950 | F56: =G56/G11 -> 0.2 | G56: =SUM(G50:G55) -> 1898950 | H56: =I56/I11 -> 0.2 | I56: =SUM(I50:I55) -> 1898950 | J56: =K56/K11 -> 0.2 | K56: =SUM(K50:K55) -> 1898950 | L56: =M56/M11 -> 0.2 | M56: =SUM(M50:M55) -> 1898950 | N56: =O56/O11 -> 0.2 | O56: =SUM(O50:O55) -> 1990050 | P56: =Q56/Q11 -> 0.2 | Q56: =SUM(Q50:Q55) -> 2052124.9 | R56: =S56/S11 -> 0.2 | S56: =SUM(S50:S55) -> 2061111.1 | T56: =U56/U11 -> 0.2 | U56: =SUM(U50:U55) -> 2061111.1 | V56: =W56/W11 -> 0.2 | W56: =SUM(W50:W55) -> 2061111.1 | X56: =Y56/Y11 -> 0.2 | Y56: =SUM(Y50:Y55) -> 2061111.1 | Z56: =AA56/AA11 -> 0.2 | AA56: =SUM(AA50:AA55) -> 2078604.1 | AB56: =AC56/AC11 -> 0.2 | AC56: =E56+G56+I56+K56+M56+O56+Q56+S56+U56+W56+Y56+AA56 -> 23859974 | AE56: =AF56/AF11 -> 0.2 | AF56: =SUM(AF50:AF55) -> 1998917.9 | AG56: =AH56/AH11 -> 0.2 | AH56: =SUM(AH50:AH55) -> 1998917.9 | AI56: =AJ56/AJ11 -> 0.2 | AJ56: =SUM(AJ50:AJ55) -> 1998917.9 | AK56: =AL56/AL11 -> 0.2 | AL56: =SUM(AL50:AL55) -> 1998917.9 | AM56: =AN56/AN11 -> 0.2 | AN56: =SUM(AN50:AN55) -> 1998917.9 | AO56: =AP56/AP11 -> 0.2 | AP56: =SUM(AP50:AP55) -> 2018088.2 | AQ56: =AR56/AR11 -> 0.2 | AR56: =SUM(AR50:AR55) -> 2057747.9 | AS56: =AT56/AT11 -> 0.2 | AT56: =SUM(AT50:AT55) -> 2068859 | AU56: =AV56/AV11 -> 0.2 | AV56: =SUM(AV50:AV55) -> 2068859 | AW56: =AX56/AX11 -> 0.2 | AX56: =SUM(AX50:AX55) -> 2068859 | AY56: =AZ56/AZ11 -> 0.2 | AZ56: =SUM(AZ50:AZ55) -> 2068859 | BA56: =BB56/BB11 -> 0.2 | BB56: =SUM(BB50:BB55) -> 2096794.6 | BC56: =BD56/BD11 -> 0.2 | BD56: =AF56+AH56+AJ56+AL56+AN56+AP56+AR56+AT56+AV56+AX56+AZ56+BB56 -> 24442656
C58: Yari | D58: =E58/E5 -> 0.1 | E58: =E5*$B$63 -> 173415 | F58: =G58/G5 -> 0.1 | G58: =G5*$B$63 -> 173415 | H58: =I58/I5 -> 0.1 | I58: =I5*$B$63 -> 173415 | J58: =K58/K5 -> 0.1 | K58: =K5*$B$63 -> 173415 | L58: =M58/M5 -> 0.1 | M58: =M5*$B$63 -> 173415 | N58: =O58/O5 -> 0.1 | O58: =O5*$B$63 -> 173415 | P58: =Q58/Q5 -> 0.1 | Q58: =Q5*$B$63 -> 173415 | R58: =S58/S5 -> 0.1 | S58: =S5*$B$63 -> 173415 | T58: =U58/U5 -> 0.1 | U58: =U5*$B$63 -> 173415 | V58: =W58/W5 -> 0.1 | W58: =W5*$B$63 -> 173415 | X58: =Y58/Y5 -> 0.1 | Y58: =Y5*$B$63 -> 173415 | Z58: =AA58/AA5 -> 0.1 | AA58: =AA5*$B$63 -> 173415 | AB58: =AC58/AC5 -> 0.1 | AC58: =E58+G58+I58+K58+M58+O58+Q58+S58+U58+W58+Y58+AA58 -> 2080980 | AE58: =AF58/AF5 -> 0.1 | AF58: =AF5*$AD$63 -> 183819.9 | AG58: =AH58/AH5 -> 0.1 | AH58: =AH5*$AD$63 -> 183819.9 | AI58: =AJ58/AJ5 -> 0.1 | AJ58: =AJ5*$AD$63 -> 183819.9 | AK58: =AL58/AL5 -> 0.1 | AL58: =AL5*$AD$63 -> 183819.9 | AM58: =AN58/AN5 -> 0.1 | AN58: =AN5*$AD$63 -> 183819.9 | AO58: =AP58/AP5 -> 0.1 | AP58: =AP5*$AD$63 -> 183819.9 | AQ58: =AR58/AR5 -> 0.1 | AR58: =AR5*$AD$63 -> 183819.9 | AS58: =AT58/AT5 -> 0.1 | AT58: =AT5*$AD$63 -> 183819.9 | AU58: =AV58/AV5 -> 0.1 | AV58: =AV5*$AD$63 -> 183819.9 | AW58: =AX58/AX5 -> 0.1 | AX58: =AX5*$AD$63 -> 183819.9 | AY58: =AZ58/AZ5 -> 0.1 | AZ58: =AZ5*$AD$63 -> 183819.9 | BA58: =BB58/BB5 -> 0.1 | BB58: =BB5*$AD$63 -> 183819.9 | BC58: =BD58/BD5 -> 0.1 | BD58: =AF58+AH58+AJ58+AL58+AN58+AP58+AR58+AT58+AV58+AX58+AZ58+BB58 -> 2205838.8
C59: Belén | D59: =E59/E6 -> 0.1 | E59: =E6*$B$63 -> 314460 | F59: =G59/G6 -> 0.1 | G59: =G6*$B$63 -> 314460 | H59: =I59/I6 -> 0.1 | I59: =I6*$B$63 -> 314460 | J59: =K59/K6 -> 0.1 | K59: =K6*$B$63 -> 314460 | L59: =M59/M6 -> 0.1 | M59: =M6*$B$63 -> 314460 | N59: =O59/O6 -> 0.1 | O59: =O6*$B$63 -> 314460 | P59: =Q59/Q6 -> 0.1 | Q59: =Q6*$B$63 -> 330497.46 | R59: =S59/S6 -> 0.1 | S59: =S6*$B$63 -> 330497.46 | T59: =U59/U6 -> 0.1 | U59: =U6*$B$63 -> 330497.46 | V59: =W59/W6 -> 0.1 | W59: =W6*$B$63 -> 330497.46 | X59: =Y59/Y6 -> 0.1 | Y59: =Y6*$B$63 -> 330497.46 | Z59: =AA59/AA6 -> 0.1 | AA59: =AA6*$B$63 -> 330497.46 | AB59: =AC59/AC6 -> 0.1 | AC59: =E59+G59+I59+K59+M59+O59+Q59+S59+U59+W59+Y59+AA59 -> 3869744.8 | AE59: =AF59/AF6 -> 0.1 | AF59: =AF6*$AD$63 -> 330497.46 | AG59: =AH59/AH6 -> 0.1 | AH59: =AH6*$AD$63 -> 330497.46 | AI59: =AJ59/AJ6 -> 0.1 | AJ59: =AJ6*$AD$63 -> 330497.46 | AK59: =AL59/AL6 -> 0.1 | AL59: =AL6*$AD$63 -> 330497.46 | AM59: =AN59/AN6 -> 0.1 | AN59: =AN6*$AD$63 -> 330497.46 | AO59: =AP59/AP6 -> 0.1 | AP59: =AP6*$AD$63 -> 330497.46 | AQ59: =AR59/AR6 -> 0.1 | AR59: =AR6*$AD$63 -> 350327.31 | AS59: =AT59/AT6 -> 0.1 | AT59: =AT6*$AD$63 -> 350327.31 | AU59: =AV59/AV6 -> 0.1 | AV59: =AV6*$AD$63 -> 350327.31 | AW59: =AX59/AX6 -> 0.1 | AX59: =AX6*$AD$63 -> 350327.31 | AY59: =AZ59/AZ6 -> 0.1 | AZ59: =AZ6*$AD$63 -> 350327.31 | BA59: =BB59/BB6 -> 0.1 | BB59: =BB6*$AD$63 -> 350327.31 | BC59: =BD59/BD6 -> 0.1 | BD59: =AF59+AH59+AJ59+AL59+AN59+AP59+AR59+AT59+AV59+AX59+AZ59+BB59 -> 4084948.6
C60: Ocarinas | D60: =E60/E7 -> 0.1 | E60: =E7*$B$63 -> 152000 | F60: =G60/G7 -> 0.1 | G60: =G7*$B$63 -> 152000 | H60: =I60/I7 -> 0.1 | I60: =I7*$B$63 -> 152000 | J60: =K60/K7 -> 0.1 | K60: =K7*$B$63 -> 152000 | L60: =M60/M7 -> 0.1 | M60: =M7*$B$63 -> 152000 | N60: =O60/O7 -> 0.1 | O60: =O7*$B$63 -> 195000 | P60: =Q60/Q7 -> 0.1 | Q60: =Q7*$B$63 -> 210000 | R60: =S60/S7 -> 0.1 | S60: =S7*$B$63 -> 210000 | T60: =U60/U7 -> 0.1 | U60: =U7*$B$63 -> 210000 | V60: =W60/W7 -> 0.1 | W60: =W7*$B$63 -> 210000 | X60: =Y60/Y7 -> 0.1 | Y60: =Y7*$B$63 -> 210000 | Z60: =AA60/AA7 -> 0.1 | AA60: =AA7*$B$63 -> 210000 | AB60: =AC60/AC7 -> 0.1 | AC60: =E60+G60+I60+K60+M60+O60+Q60+S60+U60+W60+Y60+AA60 -> 2215000 | AE60: =AF60/AF7 -> 0.1 | AF60: =AF7*$AD$63 -> 159752 | AG60: =AH60/AH7 -> 0.1 | AH60: =AH7*$AD$63 -> 159752 | AI60: =AJ60/AJ7 -> 0.1 | AJ60: =AJ7*$AD$63 -> 159752 | AK60: =AL60/AL7 -> 0.1 | AL60: =AL7*$AD$63 -> 159752 | AM60: =AN60/AN7 -> 0.1 | AN60: =AN7*$AD$63 -> 159752 | AO60: =AP60/AP7 -> 0.1 | AP60: =AP7*$AD$63 -> 169337.12 | AQ60: =AR60/AR7 -> 0.1 | AR60: =AR7*$AD$63 -> 169337.12 | AS60: =AT60/AT7 -> 0.1 | AT60: =AT7*$AD$63 -> 169337.12 | AU60: =AV60/AV7 -> 0.1 | AV60: =AV7*$AD$63 -> 169337.12 | AW60: =AX60/AX7 -> 0.1 | AX60: =AX7*$AD$63 -> 169337.12 | AY60: =AZ60/AZ7 -> 0.1 | AZ60: =AZ7*$AD$63 -> 169337.12 | BA60: =BB60/BB7 -> 0.1 | BB60: =BB7*$AD$63 -> 169337.12 | BC60: =BD60/BD7 -> 0.1 | BD60: =AF60+AH60+AJ60+AL60+AN60+AP60+AR60+AT60+AV60+AX60+AZ60+BB60 -> 1984119.8
C61: Pedregal | D61: =E61/E8 -> 0.1 | E61: =E8*$B$63 -> 50000 | F61: =G61/G8 -> 0.1 | G61: =G8*$B$63 -> 50000 | H61: =I61/I8 -> 0.1 | I61: =I8*$B$63 -> 50000 | J61: =K61/K8 -> 0.1 | K61: =K8*$B$63 -> 50000 | L61: =M61/M8 -> 0.1 | M61: =M8*$B$63 -> 50000 | N61: =O61/O8 -> 0.1 | O61: =O8*$B$63 -> 52550 | P61: =Q61/Q8 -> 0.1 | Q61: =Q8*$B$63 -> 52550 | R61: =S61/S8 -> 0.1 | S61: =S8*$B$63 -> 52550 | T61: =U61/U8 -> 0.1 | U61: =U8*$B$63 -> 52550 | V61: =W61/W8 -> 0.1 | W61: =W8*$B$63 -> 52550 | X61: =Y61/Y8 -> 0.1 | Y61: =Y8*$B$63 -> 52550 | Z61: =AA61/AA8 -> 0.1 | AA61: =AA8*$B$63 -> 52550 | AB61: =AC61/AC8 -> 0.1 | AC61: =E61+G61+I61+K61+M61+O61+Q61+S61+U61+W61+Y61+AA61 -> 617850 | AE61: =AF61/AF8 -> 0.1 | AF61: =AF8*$AD$63 -> 52550 | AG61: =AH61/AH8 -> 0.1 | AH61: =AH8*$AD$63 -> 52550 | AI61: =AJ61/AJ8 -> 0.1 | AJ61: =AJ8*$AD$63 -> 52550 | AK61: =AL61/AL8 -> 0.1 | AL61: =AL8*$AD$63 -> 52550 | AM61: =AN61/AN8 -> 0.1 | AN61: =AN8*$AD$63 -> 52550 | AO61: =AP61/AP8 -> 0.1 | AP61: =AP8*$AD$63 -> 52550 | AQ61: =AR61/AR8 -> 0.1 | AR61: =AR8*$AD$63 -> 52550 | AS61: =AT61/AT8 -> 0.1 | AT61: =AT8*$AD$63 -> 52550 | AU61: =AV61/AV8 -> 0.1 | AV61: =AV8*$AD$63 -> 52550 | AW61: =AX61/AX8 -> 0.1 | AX61: =AX8*$AD$63 -> 52550 | AY61: =AZ61/AZ8 -> 0.1 | AZ61: =AZ8*$AD$63 -> 52550 | BA61: =BB61/BB8 -> 0.1 | BB61: =BB8*$AD$63 -> 55703 | BC61: =BD61/BD8 -> 0.1 | BD61: =AF61+AH61+AJ61+AL61+AN61+AP61+AR61+AT61+AV61+AX61+AZ61+BB61 -> 633753
C62: Rivera del Valle | D62: =E62/E9 -> 0.1 | E62: =E9*$B$63 -> 171500 | F62: =G62/G9 -> 0.1 | G62: =G9*$B$63 -> 171500 | H62: =I62/I9 -> 0.1 | I62: =I9*$B$63 -> 171500 | J62: =K62/K9 -> 0.1 | K62: =K9*$B$63 -> 171500 | L62: =M62/M9 -> 0.1 | M62: =M9*$B$63 -> 171500 | N62: =O62/O9 -> 0.1 | O62: =O9*$B$63 -> 171500 | P62: =Q62/Q9 -> 0.1 | Q62: =Q9*$B$63 -> 171500 | R62: =S62/S9 -> 0.1 | S62: =S9*$B$63 -> 171500 | T62: =U62/U9 -> 0.1 | U62: =U9*$B$63 -> 171500 | V62: =W62/W9 -> 0.1 | W62: =W9*$B$63 -> 171500 | X62: =Y62/Y9 -> 0.1 | Y62: =Y9*$B$63 -> 171500 | Z62: =AA62/AA9 -> 0.1 | AA62: =AA9*$B$63 -> 180246.5 | AB62: =AC62/AC9 -> 0.1 | AC62: =E62+G62+I62+K62+M62+O62+Q62+S62+U62+W62+Y62+AA62 -> 2066746.5 | AE62: =AF62/AF9 -> 0.1 | AF62: =AF9*$AD$63 -> 180246.5 | AG62: =AH62/AH9 -> 0.1 | AH62: =AH9*$AD$63 -> 180246.5 | AI62: =AJ62/AJ9 -> 0.1 | AJ62: =AJ9*$AD$63 -> 180246.5 | AK62: =AL62/AL9 -> 0.1 | AL62: =AL9*$AD$63 -> 180246.5 | AM62: =AN62/AN9 -> 0.1 | AN62: =AN9*$AD$63 -> 180246.5 | AO62: =AP62/AP9 -> 0.1 | AP62: =AP9*$AD$63 -> 180246.5 | AQ62: =AR62/AR9 -> 0.1 | AR62: =AR9*$AD$63 -> 180246.5 | AS62: =AT62/AT9 -> 0.1 | AT62: =AT9*$AD$63 -> 180246.5 | AU62: =AV62/AV9 -> 0.1 | AV62: =AV9*$AD$63 -> 180246.5 | AW62: =AX62/AX9 -> 0.1 | AX62: =AX9*$AD$63 -> 180246.5 | AY62: =AZ62/AZ9 -> 0.1 | AZ62: =AZ9*$AD$63 -> 180246.5 | BA62: =BB62/BB9 -> 0.1 | BB62: =BB9*$AD$63 -> 191061.29 | BC62: =BD62/BD9 -> 0.1 | BD62: =AF62+AH62+AJ62+AL62+AN62+AP62+AR62+AT62+AV62+AX62+AZ62+BB62 -> 2173772.8
B63: 0.1 | C63: La Ceja | D63: =E63/E10 -> 0.1 | E63: =E10*$B$63 -> 88100 | F63: =G63/G10 -> 0.1 | G63: =G10*$B$63 -> 88100 | H63: =I63/I10 -> 0.1 | I63: =I10*$B$63 -> 88100 | J63: =K63/K10 -> 0.1 | K63: =K10*$B$63 -> 88100 | L63: =M63/M10 -> 0.1 | M63: =M10*$B$63 -> 88100 | N63: =O63/O10 -> 0.1 | O63: =O10*$B$63 -> 88100 | P63: =Q63/Q10 -> 0.1 | Q63: =Q10*$B$63 -> 88100 | R63: =S63/S10 -> 0.1 | S63: =S10*$B$63 -> 92593.1 | T63: =U63/U10 -> 0.1 | U63: =U10*$B$63 -> 92593.1 | V63: =W63/W10 -> 0.1 | W63: =W10*$B$63 -> 92593.1 | X63: =Y63/Y10 -> 0.1 | Y63: =Y10*$B$63 -> 92593.1 | Z63: =AA63/AA10 -> 0.1 | AA63: =AA10*$B$63 -> 92593.1 | AB63: =AC63/AC10 -> 0.1 | AC63: =E63+G63+I63+K63+M63+O63+Q63+S63+U63+W63+Y63+AA63 -> 1079665.5 | AD63: 0.1 | AE63: =AF63/AF10 -> 0.1 | AF63: =AF10*$AD$63 -> 92593.1 | AG63: =AH63/AH10 -> 0.1 | AH63: =AH10*$AD$63 -> 92593.1 | AI63: =AJ63/AJ10 -> 0.1 | AJ63: =AJ10*$AD$63 -> 92593.1 | AK63: =AL63/AL10 -> 0.1 | AL63: =AL10*$AD$63 -> 92593.1 | AM63: =AN63/AN10 -> 0.1 | AN63: =AN10*$AD$63 -> 92593.1 | AO63: =AP63/AP10 -> 0.1 | AP63: =AP10*$AD$63 -> 92593.1 | AQ63: =AR63/AR10 -> 0.1 | AR63: =AR10*$AD$63 -> 92593.1 | AS63: =AT63/AT10 -> 0.1 | AT63: =AT10*$AD$63 -> 98148.686 | AU63: =AV63/AV10 -> 0.1 | AV63: =AV10*$AD$63 -> 98148.686 | AW63: =AX63/AX10 -> 0.1 | AX63: =AX10*$AD$63 -> 98148.686 | AY63: =AZ63/AZ10 -> 0.1 | AZ63: =AZ10*$AD$63 -> 98148.686 | BA63: =BB63/BB10 -> 0.1 | BB63: =BB10*$AD$63 -> 98148.686 | BC63: =BD63/BD10 -> 0.1 | BD63: =AF63+AH63+AJ63+AL63+AN63+AP63+AR63+AT63+AV63+AX63+AZ63+BB63 -> 1138895.1
B64: GESTIÓN | D64: =E64/E11 -> 0.1 | E64: =SUM(E58:E63) -> 949475 | F64: =G64/G11 -> 0.1 | G64: =SUM(G58:G63) -> 949475 | H64: =I64/I11 -> 0.1 | I64: =SUM(I58:I63) -> 949475 | J64: =K64/K11 -> 0.1 | K64: =SUM(K58:K63) -> 949475 | L64: =M64/M11 -> 0.1 | M64: =SUM(M58:M63) -> 949475 | N64: =O64/O11 -> 0.1 | O64: =SUM(O58:O63) -> 995025 | P64: =Q64/Q11 -> 0.1 | Q64: =SUM(Q58:Q63) -> 1026062.5 | R64: =S64/S11 -> 0.1 | S64: =SUM(S58:S63) -> 1030555.6 | T64: =U64/U11 -> 0.1 | U64: =SUM(U58:U63) -> 1030555.6 | V64: =W64/W11 -> 0.1 | W64: =SUM(W58:W63) -> 1030555.6 | X64: =Y64/Y11 -> 0.1 | Y64: =SUM(Y58:Y63) -> 1030555.6 | Z64: =AA64/AA11 -> 0.1 | AA64: =SUM(AA58:AA63) -> 1039302.1 | AB64: =AC64/AC11 -> 0.1 | AC64: =E64+G64+I64+K64+M64+O64+Q64+S64+U64+W64+Y64+AA64 -> 11929987 | AE64: =AF64/AF11 -> 0.1 | AF64: =SUM(AF58:AF63) -> 999458.96 | AG64: =AH64/AH11 -> 0.1 | AH64: =SUM(AH58:AH63) -> 999458.96 | AI64: =AJ64/AJ11 -> 0.1 | AJ64: =SUM(AJ58:AJ63) -> 999458.96 | AK64: =AL64/AL11 -> 0.1 | AL64: =SUM(AL58:AL63) -> 999458.96 | AM64: =AN64/AN11 -> 0.1 | AN64: =SUM(AN58:AN63) -> 999458.96 | AO64: =AP64/AP11 -> 0.1 | AP64: =SUM(AP58:AP63) -> 1009044.1 | AQ64: =AR64/AR11 -> 0.1 | AR64: =SUM(AR58:AR63) -> 1028873.9 | AS64: =AT64/AT11 -> 0.1 | AT64: =SUM(AT58:AT63) -> 1034429.5 | AU64: =AV64/AV11 -> 0.1 | AV64: =SUM(AV58:AV63) -> 1034429.5 | AW64: =AX64/AX11 -> 0.1 | AX64: =SUM(AX58:AX63) -> 1034429.5 | AY64: =AZ64/AZ11 -> 0.1 | AZ64: =SUM(AZ58:AZ63) -> 1034429.5 | BA64: =BB64/BB11 -> 0.1 | BB64: =SUM(BB58:BB63) -> 1048397.3 | BC64: =BD64/BD11 -> 0.1 | BD64: =AF64+AH64+AJ64+AL64+AN64+AP64+AR64+AT64+AV64+AX64+AZ64+BB64 -> 12221328
C66: Yari | D66: =E66/E5 -> 0.0076886851 | E66: =$B$70/12 -> 13333.333 | F66: =G66/G5 -> 0.0076886851 | G66: =$B$70/12 -> 13333.333 | H66: =I66/I5 -> 0.0076886851 | I66: =$B$70/12 -> 13333.333 | J66: =K66/K5 -> 0.0076886851 | K66: =$B$70/12 -> 13333.333 | L66: =M66/M5 -> 0.0076886851 | M66: =$B$70/12 -> 13333.333 | N66: =O66/O5 -> 0.0076886851 | O66: =$B$70/12 -> 13333.333 | P66: =Q66/Q5 -> 0.0076886851 | Q66: =$B$70/12 -> 13333.333 | R66: =S66/S5 -> 0.0076886851 | S66: =$B$70/12 -> 13333.333 | T66: =U66/U5 -> 0.0076886851 | U66: =$B$70/12 -> 13333.333 | V66: =W66/W5 -> 0.0076886851 | W66: =$B$70/12 -> 13333.333 | X66: =Y66/Y5 -> 0.0076886851 | Y66: =$B$70/12 -> 13333.333 | Z66: =AA66/AA5 -> 0.0076886851 | AA66: =$B$70/12 -> 13333.333 | AB66: =AC66/AC5 -> 0.0076886851 | AC66: =E66+G66+I66+K66+M66+O66+Q66+S66+U66+W66+Y66+AA66 -> 160000 | AE66: =AF66/AF5 -> 0.0072534765 | AF66: =$AD$70/12 -> 13333.333 | AG66: =AH66/AH5 -> 0.0072534765 | AH66: =$AD$70/12 -> 13333.333 | AI66: =AJ66/AJ5 -> 0.0072534765 | AJ66: =$AD$70/12 -> 13333.333 | AK66: =AL66/AL5 -> 0.0072534765 | AL66: =$AD$70/12 -> 13333.333 | AM66: =AN66/AN5 -> 0.0072534765 | AN66: =$AD$70/12 -> 13333.333 | AO66: =AP66/AP5 -> 0.0072534765 | AP66: =$AD$70/12 -> 13333.333 | AQ66: =AR66/AR5 -> 0.0072534765 | AR66: =$AD$70/12 -> 13333.333 | AS66: =AT66/AT5 -> 0.0072534765 | AT66: =$AD$70/12 -> 13333.333 | AU66: =AV66/AV5 -> 0.0072534765 | AV66: =$AD$70/12 -> 13333.333 | AW66: =AX66/AX5 -> 0.0072534765 | AX66: =$AD$70/12 -> 13333.333 | AY66: =AZ66/AZ5 -> 0.0072534765 | AZ66: =$AD$70/12 -> 13333.333 | BA66: =BB66/BB5 -> 0.0072534765 | BB66: =$AD$70/12 -> 13333.333 | BC66: =BD66/BD5 -> 0.0072534765 | BD66: =AF66+AH66+AJ66+AL66+AN66+AP66+AR66+AT66+AV66+AX66+AZ66+BB66 -> 160000
C67: Belén | D67: =E67/E6 -> 0.0042400729 | E67: =$B$70/12 -> 13333.333 | F67: =G67/G6 -> 0.0042400729 | G67: =$B$70/12 -> 13333.333 | H67: =I67/I6 -> 0.0042400729 | I67: =$B$70/12 -> 13333.333 | J67: =K67/K6 -> 0.0042400729 | K67: =$B$70/12 -> 13333.333 | L67: =M67/M6 -> 0.0042400729 | M67: =$B$70/12 -> 13333.333 | N67: =O67/O6 -> 0.0042400729 | O67: =$B$70/12 -> 13333.333 | P67: =Q67/Q6 -> 0.0040343225 | Q67: =$B$70/12 -> 13333.333 | R67: =S67/S6 -> 0.0040343225 | S67: =$B$70/12 -> 13333.333 | T67: =U67/U6 -> 0.0040343225 | U67: =$B$70/12 -> 13333.333 | V67: =W67/W6 -> 0.0040343225 | W67: =$B$70/12 -> 13333.333 | X67: =Y67/Y6 -> 0.0040343225 | Y67: =$B$70/12 -> 13333.333 | Z67: =AA67/AA6 -> 0.0040343225 | AA67: =$B$70/12 -> 13333.333 | AB67: =AC67/AC6 -> 0.0041346396 | AC67: =E67+G67+I67+K67+M67+O67+Q67+S67+U67+W67+Y67+AA67 -> 160000 | AE67: =AF67/AF6 -> 0.0040343225 | AF67: =$AD$70/12 -> 13333.333 | AG67: =AH67/AH6 -> 0.0040343225 | AH67: =$AD$70/12 -> 13333.333 | AI67: =AJ67/AJ6 -> 0.0040343225 | AJ67: =$AD$70/12 -> 13333.333 | AK67: =AL67/AL6 -> 0.0040343225 | AL67: =$AD$70/12 -> 13333.333 | AM67: =AN67/AN6 -> 0.0040343225 | AN67: =$AD$70/12 -> 13333.333 | AO67: =AP67/AP6 -> 0.0040343225 | AP67: =$AD$70/12 -> 13333.333 | AQ67: =AR67/AR6 -> 0.0038059646 | AR67: =$AD$70/12 -> 13333.333 | AS67: =AT67/AT6 -> 0.0038059646 | AT67: =$AD$70/12 -> 13333.333 | AU67: =AV67/AV6 -> 0.0038059646 | AV67: =$AD$70/12 -> 13333.333 | AW67: =AX67/AX6 -> 0.0038059646 | AX67: =$AD$70/12 -> 13333.333 | AY67: =AZ67/AZ6 -> 0.0038059646 | AZ67: =$AD$70/12 -> 13333.333 | BA67: =BB67/BB6 -> 0.0038059646 | BB67: =$AD$70/12 -> 13333.333 | BC67: =BD67/BD6 -> 0.0039168179 | BD67: =AF67+AH67+AJ67+AL67+AN67+AP67+AR67+AT67+AV67+AX67+AZ67+BB67 -> 160000
C68: Ocarinas | D68: =E68/E7 -> 0.0087719298 | E68: =$B$70/12 -> 13333.333 | F68: =G68/G7 -> 0.0087719298 | G68: =$B$70/12 -> 13333.333 | H68: =I68/I7 -> 0.0087719298 | I68: =$B$70/12 -> 13333.333 | J68: =K68/K7 -> 0.0087719298 | K68: =$B$70/12 -> 13333.333 | L68: =M68/M7 -> 0.0087719298 | M68: =$B$70/12 -> 13333.333 | N68: =O68/O7 -> 0.0068376068 | O68: =$B$70/12 -> 13333.333 | P68: =Q68/Q7 -> 0.0063492063 | Q68: =$B$70/12 -> 13333.333 | R68: =S68/S7 -> 0.0063492063 | S68: =$B$70/12 -> 13333.333 | T68: =U68/U7 -> 0.0063492063 | U68: =$B$70/12 -> 13333.333 | V68: =W68/W7 -> 0.0063492063 | W68: =$B$70/12 -> 13333.333 | X68: =Y68/Y7 -> 0.0063492063 | Y68: =$B$70/12 -> 13333.333 | Z68: =AA68/AA7 -> 0.0063492063 | AA68: =$B$70/12 -> 13333.333 | AB68: =AC68/AC7 -> 0.0072234763 | AC68: =E68+G68+I68+K68+M68+O68+Q68+S68+U68+W68+Y68+AA68 -> 160000 | AE68: =AF68/AF7 -> 0.0083462701 | AF68: =$AD$70/12 -> 13333.333 | AG68: =AH68/AH7 -> 0.0083462701 | AH68: =$AD$70/12 -> 13333.333 | AI68: =AJ68/AJ7 -> 0.0083462701 | AJ68: =$AD$70/12 -> 13333.333 | AK68: =AL68/AL7 -> 0.0083462701 | AL68: =$AD$70/12 -> 13333.333 | AM68: =AN68/AN7 -> 0.0083462701 | AN68: =$AD$70/12 -> 13333.333 | AO68: =AP68/AP7 -> 0.0078738397 | AP68: =$AD$70/12 -> 13333.333 | AQ68: =AR68/AR7 -> 0.0078738397 | AR68: =$AD$70/12 -> 13333.333 | AS68: =AT68/AT7 -> 0.0078738397 | AT68: =$AD$70/12 -> 13333.333 | AU68: =AV68/AV7 -> 0.0078738397 | AV68: =$AD$70/12 -> 13333.333 | AW68: =AX68/AX7 -> 0.0078738397 | AX68: =$AD$70/12 -> 13333.333 | AY68: =AZ68/AZ7 -> 0.0078738397 | AZ68: =$AD$70/12 -> 13333.333 | BA68: =BB68/BB7 -> 0.0078738397 | BB68: =$AD$70/12 -> 13333.333 | BC68: =BD68/BD7 -> 0.008064029 | BD68: =AF68+AH68+AJ68+AL68+AN68+AP68+AR68+AT68+AV68+AX68+AZ68+BB68 -> 160000
C69: Rivera del Valle | D69: =E69/E9 -> 0.0077745384 | E69: =$B$70/12 -> 13333.333 | F69: =G69/G9 -> 0.0077745384 | G69: =$B$70/12 -> 13333.333 | H69: =I69/I9 -> 0.0077745384 | I69: =$B$70/12 -> 13333.333 | J69: =K69/K9 -> 0.0077745384 | K69: =$B$70/12 -> 13333.333 | L69: =M69/M9 -> 0.0077745384 | M69: =$B$70/12 -> 13333.333 | N69: =O69/O9 -> 0.0077745384 | O69: =$B$70/12 -> 13333.333 | P69: =Q69/Q9 -> 0.0077745384 | Q69: =$B$70/12 -> 13333.333 | R69: =S69/S9 -> 0.0077745384 | S69: =$B$70/12 -> 13333.333 | T69: =U69/U9 -> 0.0077745384 | U69: =$B$70/12 -> 13333.333 | V69: =W69/W9 -> 0.0077745384 | W69: =$B$70/12 -> 13333.333 | X69: =Y69/Y9 -> 0.0077745384 | Y69: =$B$70/12 -> 13333.333 | Z69: =AA69/AA9 -> 0.0073972772 | AA69: =$B$70/12 -> 13333.333 | AB69: =AC69/AC9 -> 0.0077416364 | AC69: =E69+G69+I69+K69+M69+O69+Q69+S69+U69+W69+Y69+AA69 -> 160000 | AE69: =AF69/AF9 -> 0.0073972772 | AF69: =$AD$70/12 -> 13333.333 | AG69: =AH69/AH9 -> 0.0073972772 | AH69: =$AD$70/12 -> 13333.333 | AI69: =AJ69/AJ9 -> 0.0073972772 | AJ69: =$AD$70/12 -> 13333.333 | AK69: =AL69/AL9 -> 0.0073972772 | AL69: =$AD$70/12 -> 13333.333 | AM69: =AN69/AN9 -> 0.0073972772 | AN69: =$AD$70/12 -> 13333.333 | AO69: =AP69/AP9 -> 0.0073972772 | AP69: =$AD$70/12 -> 13333.333 | AQ69: =AR69/AR9 -> 0.0073972772 | AR69: =$AD$70/12 -> 13333.333 | AS69: =AT69/AT9 -> 0.0073972772 | AT69: =$AD$70/12 -> 13333.333 | AU69: =AV69/AV9 -> 0.0073972772 | AV69: =$AD$70/12 -> 13333.333 | AW69: =AX69/AX9 -> 0.0073972772 | AX69: =$AD$70/12 -> 13333.333 | AY69: =AZ69/AZ9 -> 0.0073972772 | AZ69: =$AD$70/12 -> 13333.333 | BA69: =BB69/BB9 -> 0.0069785634 | BB69: =$AD$70/12 -> 13333.333 | BC69: =BD69/BD9 -> 0.0073604749 | BD69: =AF69+AH69+AJ69+AL69+AN69+AP69+AR69+AT69+AV69+AX69+AZ69+BB69 -> 160000
B70: 160000 | C70: La Ceja | D70: =E70/E10 -> 0.015134317 | E70: =$B$70/12 -> 13333.333 | F70: =G70/G10 -> 0.015134317 | G70: =$B$70/12 -> 13333.333 | H70: =I70/I10 -> 0.015134317 | I70: =$B$70/12 -> 13333.333 | J70: =K70/K10 -> 0.015134317 | K70: =$B$70/12 -> 13333.333 | L70: =M70/M10 -> 0.015134317 | M70: =$B$70/12 -> 13333.333 | N70: =O70/O10 -> 0.015134317 | O70: =$B$70/12 -> 13333.333 | P70: =Q70/Q10 -> 0.015134317 | Q70: =$B$70/12 -> 13333.333 | R70: =S70/S10 -> 0.014399921 | S70: =$B$70/12 -> 13333.333 | T70: =U70/U10 -> 0.014399921 | U70: =$B$70/12 -> 13333.333 | V70: =W70/W10 -> 0.014399921 | W70: =$B$70/12 -> 13333.333 | X70: =Y70/Y10 -> 0.014399921 | Y70: =$B$70/12 -> 13333.333 | Z70: =AA70/AA10 -> 0.014399921 | AA70: =$B$70/12 -> 13333.333 | AB70: =AC70/AC10 -> 0.014819405 | AC70: =E70+G70+I70+K70+M70+O70+Q70+S70+U70+W70+Y70+AA70 -> 160000 | AD70: 160000 | AE70: =AF70/AF10 -> 0.014399921 | AF70: =$AD$70/12 -> 13333.333 | AG70: =AH70/AH10 -> 0.014399921 | AH70: =$AD$70/12 -> 13333.333 | AI70: =AJ70/AJ10 -> 0.014399921 | AJ70: =$AD$70/12 -> 13333.333 | AK70: =AL70/AL10 -> 0.014399921 | AL70: =$AD$70/12 -> 13333.333 | AM70: =AN70/AN10 -> 0.014399921 | AN70: =$AD$70/12 -> 13333.333 | AO70: =AP70/AP10 -> 0.014399921 | AP70: =$AD$70/12 -> 13333.333 | AQ70: =AR70/AR10 -> 0.014399921 | AR70: =$AD$70/12 -> 13333.333 | AS70: =AT70/AT10 -> 0.013584831 | AT70: =$AD$70/12 -> 13333.333 | AU70: =AV70/AV10 -> 0.013584831 | AV70: =$AD$70/12 -> 13333.333 | AW70: =AX70/AX10 -> 0.013584831 | AX70: =$AD$70/12 -> 13333.333 | AY70: =AZ70/AZ10 -> 0.013584831 | AZ70: =$AD$70/12 -> 13333.333 | BA70: =BB70/BB10 -> 0.013584831 | BB70: =$AD$70/12 -> 13333.333 | BC70: =BD70/BD10 -> 0.014048704 | BD70: =AF70+AH70+AJ70+AL70+AN70+AP70+AR70+AT70+AV70+AX70+AZ70+BB70 -> 160000
B71: TASA DE SEGURIDAD | D71: =E71/E11 -> 0.0070214241 | E71: =SUM(E66:E70) -> 66666.667 | F71: =G71/G11 -> 0.0070214241 | G71: =SUM(G66:G70) -> 66666.667 | H71: =I71/I11 -> 0.0070214241 | I71: =SUM(I66:I70) -> 66666.667 | J71: =K71/K11 -> 0.0070214241 | K71: =SUM(K66:K70) -> 66666.667 | L71: =M71/M11 -> 0.0070214241 | M71: =SUM(M66:M70) -> 66666.667 | N71: =O71/O11 -> 0.0066999992 | O71: =SUM(O66:O70) -> 66666.667 | P71: =Q71/Q11 -> 0.0064973303 | Q71: =SUM(Q66:Q70) -> 66666.667 | R71: =S71/S11 -> 0.0064690027 | S71: =SUM(S66:S70) -> 66666.667 | T71: =U71/U11 -> 0.0064690027 | U71: =SUM(U66:U70) -> 66666.667 | V71: =W71/W11 -> 0.0064690027 | W71: =SUM(W66:W70) -> 66666.667 | X71: =Y71/Y11 -> 0.0064690027 | Y71: =SUM(Y66:Y70) -> 66666.667 | Z71: =AA71/AA11 -> 0.0064145612 | AA71: =SUM(AA66:AA70) -> 66666.667 | AB71: =AC71/AC11 -> 0.0067057912 | AC71: =E71+G71+I71+K71+M71+O71+Q71+S71+U71+W71+Y71+AA71 -> 800000 | AE71: =AF71/AF11 -> 0.0066702756 | AF71: =SUM(AF66:AF70) -> 66666.667 | AG71: =AH71/AH11 -> 0.0066702756 | AH71: =SUM(AH66:AH70) -> 66666.667 | AI71: =AJ71/AJ11 -> 0.0066702756 | AJ71: =SUM(AJ66:AJ70) -> 66666.667 | AK71: =AL71/AL11 -> 0.0066702756 | AL71: =SUM(AL66:AL70) -> 66666.667 | AM71: =AN71/AN11 -> 0.0066702756 | AN71: =SUM(AN66:AN70) -> 66666.667 | AO71: =AP71/AP11 -> 0.0066069132 | AP71: =SUM(AP66:AP70) -> 66666.667 | AQ71: =AR71/AR11 -> 0.0064795759 | AR71: =SUM(AR66:AR70) -> 66666.667 | AS71: =AT71/AT11 -> 0.0064447762 | AT71: =SUM(AT66:AT70) -> 66666.667 | AU71: =AV71/AV11 -> 0.0064447762 | AV71: =SUM(AV66:AV70) -> 66666.667 | AW71: =AX71/AX11 -> 0.0064447762 | AX71: =SUM(AX66:AX70) -> 66666.667 | AY71: =AZ71/AZ11 -> 0.0064447762 | AZ71: =SUM(AZ66:AZ70) -> 66666.667 | BA71: =BB71/BB11 -> 0.0063589125 | BB71: =SUM(BB66:BB70) -> 66666.667 | BC71: =BD71/BD11 -> 0.0065459334 | BD71: =AF71+AH71+AJ71+AL71+AN71+AP71+AR71+AT71+AV71+AX71+AZ71+BB71 -> 800000
C73: Yari | D73: =E73/E5 -> 0.17181806 | E73: =E5-E13-E21-E26-E34-E42-E50-E58-E66 -> 297958.28 | F73: =G73/G5 -> 0.16737497 | G73: =G5-G13-G21-G26-G34-G42-G50-G58-G66 -> 290253.3 | H73: =I73/I5 -> 0.16737497 | I73: =I5-I13-I21-I26-I34-I42-I50-I58-I66 -> 290253.3 | J73: =K73/K5 -> 0.16737497 | K73: =K5-K13-K21-K26-K34-K42-K50-K58-K66 -> 290253.3 | L73: =M73/M5 -> 0.16737497 | M73: =M5-M13-M21-M26-M34-M42-M50-M58-M66 -> 290253.3 | N73: =O73/O5 -> 0.17122655 | O73: =O5-O13-O21-O26-O34-O42-O50-O58-O66 -> 296932.52 | P73: =Q73/Q5 -> 0.17365509 | Q73: =Q5-Q13-Q21-Q26-Q34-Q42-Q50-Q58-Q66 -> 301143.98 | R73: =S73/S5 -> 0.17399454 | S73: =S5-S13-S21-S26-S34-S42-S50-S58-S66 -> 301732.63 | T73: =U73/U5 -> 0.17399454 | U73: =U5-U13-U21-U26-U34-U42-U50-U58-U66 -> 301732.63 | V73: =W73/W5 -> 0.20877991 | W73: =W5-W13-W21-W26-W34-W42-W50-W58-W66 -> 362055.68 | X73: =Y73/Y5 -> 0.20877991 | Y73: =Y5-Y13-Y21-Y26-Y34-Y42-Y50-Y58-Y66 -> 362055.68 | Z73: =AA73/AA5 -> 0.20913953 | AA73: =AA5-AA13-AA21-AA26-AA34-AA42-AA50-AA58-AA66 -> 362679.31 | AB73: =AC73/AC5 -> 0.180074 | AC73: =E73+G73+I73+K73+M73+O73+Q73+S73+U73+W73+Y73+AA73 -> 3747303.9 | AE73: =AF73/AF5 -> 0.18728473 | AF73: =AF5-AF13-AF21-AF26-AF34-AF42-AF50-AF58-AF66 -> 344266.6 | AG73: =AH73/AH5 -> 0.18067557 | AH73: =AH5-AH13-AH21-AH26-AH34-AH42-AH50-AH58-AH66 -> 332117.66 | AI73: =AJ73/AJ5 -> 0.18067557 | AJ73: =AJ5-AJ13-AJ21-AJ26-AJ34-AJ42-AJ50-AJ58-AJ66 -> 332117.66 | AK73: =AL73/AL5 -> 0.18067557 | AL73: =AL5-AL13-AL21-AL26-AL34-AL42-AL50-AL58-AL66 -> 332117.66 | AM73: =AN73/AN5 -> 0.18067557 | AN73: =AN5-AN13-AN21-AN26-AN34-AN42-AN50-AN58-AN66 -> 332117.66 | AO73: =AP73/AP5 -> 0.18327861 | AP73: =AP5-AP13-AP21-AP26-AP34-AP42-AP50-AP58-AP66 -> 336902.56 | AQ73: =AR73/AR5 -> 0.18850986 | AR73: =AR5-AR13-AR21-AR26-AR34-AR42-AR50-AR58-AR66 -> 346518.64 | AS73: =AT73/AT5 -> 0.1899395 | AT73: =AT5-AT13-AT21-AT26-AT34-AT42-AT50-AT58-AT66 -> 349146.59 | AU73: =AV73/AV5 -> 0.1899395 | AV73: =AV5-AV13-AV21-AV26-AV34-AV42-AV50-AV58-AV66 -> 349146.59 | AW73: =AX73/AX5 -> 0.1899395 | AX73: =AX5-AX13-AX21-AX26-AX34-AX42-AX50-AX58-AX66 -> 349146.59 | AY73: =AZ73/AZ5 -> 0.1899395 | AZ73: =AZ5-AZ13-AZ21-AZ26-AZ34-AZ42-AZ50-AZ58-AZ66 -> 349146.59 | BA73: =BB73/BB5 -> 0.19346693 | BB73: =BB5-BB13-BB21-BB26-BB34-BB42-BB50-BB58-BB66 -> 355630.73 | BC73: =BD73/BD5 -> 0.18625003 | BD73: =AF73+AH73+AJ73+AL73+AN73+AP73+AR73+AT73+AV73+AX73+AZ73+BB73 -> 4108375.5
C74: Belén | D74: =E74/E6 -> 0.26668913 | E74: =E6-E14-E27-E35-E43-E51-E59-E67 -> 838630.64 | F74: =G74/G6 -> 0.26224604 | G74: =G6-G14-G27-G35-G43-G51-G59-G67 -> 824658.91 | H74: =I74/I6 -> 0.26224604 | I74: =I6-I14-I27-I35-I43-I51-I59-I67 -> 824658.91 | J74: =K74/K6 -> 0.26224604 | K74: =K6-K14-K27-K35-K43-K51-K59-K67 -> 824658.91 | L74: =M74/M6 -> 0.26224604 | M74: =M6-M14-M27-M35-M43-M51-M59-M67 -> 824658.91 | N74: =O74/O6 -> 0.26609762 | O74: =O6-O14-O27-O35-O43-O51-O59-O67 -> 836770.58 | P74: =Q74/Q6 -> 0.28568553 | Q74: =Q6-Q14-Q27-Q35-Q43-Q51-Q59-Q67 -> 944183.42 | R74: =S74/S6 -> 0.28602498 | S74: =S6-S14-S27-S35-S43-S51-S59-S67 -> 945305.28 | T74: =U74/U6 -> 0.28602498 | U74: =U6-U14-U27-U35-U43-U51-U59-U67 -> 945305.28 | V74: =W74/W6 -> 0.32081035 | W74: =W6-W14-W27-W35-W43-W51-W59-W67 -> 1060270.1 | X74: =Y74/Y6 -> 0.32081035 | Y74: =Y6-Y14-Y27-Y35-Y43-Y51-Y59-Y67 -> 1060270.1 | Z74: =AA74/AA6 -> 0.32116997 | AA74: =AA6-AA14-AA27-AA35-AA43-AA51-AA59-AA67 -> 1061458.6 | AB74: =AC74/AC6 -> 0.28401949 | AC74: =E74+G74+I74+K74+M74+O74+Q74+S74+U74+W74+Y74+AA74 -> 10990830 | AE74: =AF74/AF6 -> 0.28849954 | AF74: =AF6-AF14-AF27-AF35-AF43-AF51-AF59-AF67 -> 953483.65 | AG74: =AH74/AH6 -> 0.28189038 | AH74: =AH6-AH14-AH27-AH35-AH43-AH51-AH59-AH67 -> 931640.56 | AI74: =AJ74/AJ6 -> 0.28189038 | AJ74: =AJ6-AJ14-AJ27-AJ35-AJ43-AJ51-AJ59-AJ67 -> 931640.56 | AK74: =AL74/AL6 -> 0.28189038 | AL74: =AL6-AL14-AL27-AL35-AL43-AL51-AL59-AL67 -> 931640.56 | AM74: =AN74/AN6 -> 0.28189038 | AN74: =AN6-AN14-AN27-AN35-AN43-AN51-AN59-AN67 -> 931640.56 | AO74: =AP74/AP6 -> 0.28449342 | AP74: =AP6-AP14-AP27-AP35-AP43-AP51-AP59-AP67 -> 940243.54 | AQ74: =AR74/AR6 -> 0.29788029 | AR74: =AR6-AR14-AR27-AR35-AR43-AR51-AR59-AR67 -> 1043556 | AS74: =AT74/AT6 -> 0.29930993 | AT74: =AT6-AT14-AT27-AT35-AT43-AT51-AT59-AT67 -> 1048564.4 | AU74: =AV74/AV6 -> 0.29930993 | AV74: =AV6-AV14-AV27-AV35-AV43-AV51-AV59-AV67 -> 1048564.4 | AW74: =AX74/AX6 -> 0.29930993 | AX74: =AX6-AX14-AX27-AX35-AX43-AX51-AX59-AX67 -> 1048564.4 | AY74: =AZ74/AZ6 -> 0.29930993 | AZ74: =AZ6-AZ14-AZ27-AZ35-AZ43-AZ51-AZ59-AZ67 -> 1048564.4 | BA74: =BB74/BB6 -> 0.30283736 | BB74: =BB6-BB14-BB27-BB35-BB43-BB51-BB59-BB67 -> 1060922 | BC74: =BD74/BD6 -> 0.29177907 | BD74: =AF74+AH74+AJ74+AL74+AN74+AP74+AR74+AT74+AV74+AX74+AZ74+BB74 -> 11919025
C75: Ocarinas | D75: =E75/E7 -> -0.10762041 | E75: =E7-E15-E22-E28-E36-E44-E52-E60-E68 -> -163583.03 | F75: =G75/G7 -> -0.1120635 | G75: =G7-G15-G22-G28-G36-G44-G52-G60-G68 -> -170336.52 | H75: =I75/I7 -> -0.1120635 | I75: =I7-I15-I22-I28-I36-I44-I52-I60-I68 -> -170336.52 | J75: =K75/K7 -> -0.1120635 | K75: =K7-K15-K22-K28-K36-K44-K52-K60-K68 -> -170336.52 | L75: =M75/M7 -> -0.1120635 | M75: =M7-M15-M22-M28-M36-M44-M52-M60-M68 -> -170336.52 | N75: =O75/O7 -> 0.052305323 | O75: =O7-O15-O22-O28-O36-O44-O52-O60-O68 -> 101995.38 | P75: =Q75/Q7 -> 0.095263139 | Q75: =Q7-Q15-Q22-Q28-Q36-Q44-Q52-Q60-Q68 -> 200052.59 | R75: =S75/S7 -> 0.095602583 | S75: =S7-S15-S22-S28-S36-S44-S52-S60-S68 -> 200765.42 | T75: =U75/U7 -> 0.095602583 | U75: =U7-U15-U22-U28-U36-U44-U52-U60-U68 -> 200765.42 | V75: =W75/W7 -> 0.13038796 | W75: =W7-W15-W22-W28-W36-W44-W52-W60-W68 -> 273814.71 | X75: =Y75/Y7 -> 0.13038796 | Y75: =Y7-Y15-Y22-Y28-Y36-Y44-Y52-Y60-Y68 -> 273814.71 | Z75: =AA75/AA7 -> 0.13074757 | AA75: =AA7-AA15-AA22-AA28-AA36-AA44-AA52-AA60-AA68 -> 274569.91 | AB75: =AC75/AC7 -> 0.030738105 | AC75: =E75+G75+I75+K75+M75+O75+Q75+S75+U75+W75+Y75+AA75 -> 680849.03 | AE75: =AF75/AF7 -> -0.12042168 | AF75: =AF7-AF15-AF22-AF28-AF36-AF44-AF52-AF60-AF68 -> -192376.04 | AG75: =AH75/AH7 -> -0.12703083 | AH75: =AH7-AH15-AH22-AH28-AH36-AH44-AH52-AH60-AH68 -> -202934.29 | AI75: =AJ75/AJ7 -> -0.12703083 | AJ75: =AJ7-AJ15-AJ22-AJ28-AJ36-AJ44-AJ52-AJ60-AJ68 -> -202934.29 | AK75: =AL75/AL7 -> -0.12703083 | AL75: =AL7-AL15-AL22-AL28-AL36-AL44-AL52-AL60-AL68 -> -202934.29 | AM75: =AN75/AN7 -> -0.12703083 | AN75: =AN7-AN15-AN22-AN28-AN36-AN44-AN52-AN60-AN68 -> -202934.29 | AO75: =AP75/AP7 -> -0.09312569 | AP75: =AP7-AP15-AP22-AP28-AP36-AP44-AP52-AP60-AP68 -> -157696.36 | AQ75: =AR75/AR7 -> -0.087894441 | AR75: =AR7-AR15-AR22-AR28-AR36-AR44-AR52-AR60-AR68 -> -148837.91 | AS75: =AT75/AT7 -> -0.086464806 | AT75: =AT7-AT15-AT22-AT28-AT36-AT44-AT52-AT60-AT68 -> -146417.01 | AU75: =AV75/AV7 -> -0.086464806 | AV75: =AV7-AV15-AV22-AV28-AV36-AV44-AV52-AV60-AV68 -> -146417.01 | AW75: =AX75/AX7 -> -0.086464806 | AX75: =AX7-AX15-AX22-AX28-AX36-AX44-AX52-AX60-AX68 -> -146417.01 | AY75: =AZ75/AZ7 -> -0.086464806 | AZ75: =AZ7-AZ15-AZ22-AZ28-AZ36-AZ44-AZ52-AZ60-AZ68 -> -146417.01 | BA75: =BB75/BB7 -> -0.082937368 | BB75: =BB7-BB15-BB22-BB28-BB36-BB44-BB52-BB60-BB68 -> -140443.75 | BC75: =BD75/BD7 -> -0.10265304 | BD75: =AF75+AH75+AJ75+AL75+AN75+AP75+AR75+AT75+AV75+AX75+AZ75+BB75 -> -2036759.3
C76: Pedregal | D76: =E76/E8 -> 0.33367041 | E76: =E8-E16-E29-E37-E45-E53-E61 -> 166835.21 | F76: =G76/G8 -> 0.32922732 | G76: =G8-G16-G29-G37-G45-G53-G61 -> 164613.66 | H76: =I76/I8 -> 0.32922732 | I76: =I8-I16-I29-I37-I45-I53-I61 -> 164613.66 | J76: =K76/K8 -> 0.32922732 | K76: =K8-K16-K29-K37-K45-K53-K61 -> 164613.66 | L76: =M76/M8 -> 0.32922732 | M76: =M8-M16-M29-M37-M45-M53-M61 -> 164613.66 | N76: =O76/O8 -> 0.34698799 | O76: =O8-O16-O29-O37-O45-O53-O61 -> 182342.19 | P76: =Q76/Q8 -> 0.34941653 | Q76: =Q8-Q16-Q29-Q37-Q45-Q53-Q61 -> 183618.39 | R76: =S76/S8 -> 0.34975597 | S76: =S8-S16-S29-S37-S45-S53-S61 -> 183796.76 | T76: =U76/U8 -> 0.34975597 | U76: =U8-U16-U29-U37-U45-U53-U61 -> 183796.76 | V76: =W76/W8 -> 0.38454135 | W76: =W8-W16-W29-W37-W45-W53-W61 -> 202076.48 | X76: =Y76/Y8 -> 0.38454135 | Y76: =Y8-Y16-Y29-Y37-Y45-Y53-Y61 -> 202076.48 | Z76: =AA76/AA8 -> 0.38490097 | AA76: =AA8-AA16-AA29-AA37-AA45-AA53-AA61 -> 202265.46 | AB76: =AC76/AC8 -> 0.35045114 | AC76: =E76+G76+I76+K76+M76+O76+Q76+S76+U76+W76+Y76+AA76 -> 2165262.4 | AE76: =AF76/AF8 -> 0.36118504 | AF76: =AF8-AF16-AF29-AF37-AF45-AF53-AF61 -> 189802.74 | AG76: =AH76/AH8 -> 0.35457588 | AH76: =AH8-AH16-AH29-AH37-AH45-AH53-AH61 -> 186329.63 | AI76: =AJ76/AJ8 -> 0.35457588 | AJ76: =AJ8-AJ16-AJ29-AJ37-AJ45-AJ53-AJ61 -> 186329.63 | AK76: =AL76/AL8 -> 0.35457588 | AL76: =AL8-AL16-AL29-AL37-AL45-AL53-AL61 -> 186329.63 | AM76: =AN76/AN8 -> 0.35457588 | AN76: =AN8-AN16-AN29-AN37-AN45-AN53-AN61 -> 186329.63 | AO76: =AP76/AP8 -> 0.35717892 | AP76: =AP8-AP16-AP29-AP37-AP45-AP53-AP61 -> 187697.52 | AQ76: =AR76/AR8 -> 0.36241017 | AR76: =AR8-AR16-AR29-AR37-AR45-AR53-AR61 -> 190446.55 | AS76: =AT76/AT8 -> 0.36383981 | AT76: =AT8-AT16-AT29-AT37-AT45-AT53-AT61 -> 191197.82 | AU76: =AV76/AV8 -> 0.36383981 | AV76: =AV8-AV16-AV29-AV37-AV45-AV53-AV61 -> 191197.82 | AW76: =AX76/AX8 -> 0.36383981 | AX76: =AX8-AX16-AX29-AX37-AX45-AX53-AX61 -> 191197.82 | AY76: =AZ76/AZ8 -> 0.36383981 | AZ76: =AZ8-AZ16-AZ29-AZ37-AZ45-AZ53-AZ61 -> 191197.82 | BA76: =BB76/BB8 -> 0.37140859 | BB76: =BB8-BB16-BB29-BB37-BB45-BB53-BB61 -> 206885.73 | BC76: =BD76/BD8 -> 0.36054146 | BD76: =AF76+AH76+AJ76+AL76+AN76+AP76+AR76+AT76+AV76+AX76+AZ76+BB76 -> 2284942.3
C77: Rivera del Valle | D77: =E77/E9 -> 0.13589916 | E77: =E9-E17-E23-E30-E38-E46-E54-E62-E69 -> 233067.05 | F77: =G77/G9 -> 0.13145607 | G77: =G9-G17-G23-G30-G38-G46-G54-G62-G69 -> 225447.16 | H77: =I77/I9 -> 0.13145607 | I77: =I9-I17-I23-I30-I38-I46-I54-I62-I69 -> 225447.16 | J77: =K77/K9 -> 0.13145607 | K77: =K9-K17-K23-K30-K38-K46-K54-K62-K69 -> 225447.16 | L77: =M77/M9 -> 0.13145607 | M77: =M9-M17-M23-M30-M38-M46-M54-M62-M69 -> 225447.16 | N77: =O77/O9 -> 0.13530765 | O77: =O9-O17-O23-O30-O38-O46-O54-O62-O69 -> 232052.61 | P77: =Q77/Q9 -> 0.13773619 | Q77: =Q9-Q17-Q23-Q30-Q38-Q46-Q54-Q62-Q69 -> 236217.57 | R77: =S77/S9 -> 0.13807563 | S77: =S9-S17-S23-S30-S38-S46-S54-S62-S69 -> 236799.71 | T77: =U77/U9 -> 0.13807563 | U77: =U9-U17-U23-U30-U38-U46-U54-U62-U69 -> 236799.71 | V77: =W77/W9 -> 0.17286101 | W77: =W9-W17-W23-W30-W38-W46-W54-W62-W69 -> 296456.63 | X77: =Y77/Y9 -> 0.17286101 | Y77: =Y9-Y17-Y23-Y30-Y38-Y46-Y54-Y62-Y69 -> 296456.63 | Z77: =AA77/AA9 -> 0.1967266 | AA77: =AA9-AA17-AA23-AA30-AA38-AA46-AA54-AA62-AA69 -> 354592.81 | AB77: =AC77/AC9 -> 0.14632812 | AC77: =E77+G77+I77+K77+M77+O77+Q77+S77+U77+W77+Y77+AA77 -> 3024231.4 | AE77: =AF77/AF9 -> 0.14589411 | AF77: =AF9-AF17-AF23-AF30-AF38-AF46-AF54-AF62-AF69 -> 262969.03 | AG77: =AH77/AH9 -> 0.13928496 | AH77: =AH9-AH17-AH23-AH30-AH38-AH46-AH54-AH62-AH69 -> 251056.26 | AI77: =AJ77/AJ9 -> 0.13928496 | AJ77: =AJ9-AJ17-AJ23-AJ30-AJ38-AJ46-AJ54-AJ62-AJ69 -> 251056.26 | AK77: =AL77/AL9 -> 0.13928496 | AL77: =AL9-AL17-AL23-AL30-AL38-AL46-AL54-AL62-AL69 -> 251056.26 | AM77: =AN77/AN9 -> 0.13928496 | AN77: =AN9-AN17-AN23-AN30-AN38-AN46-AN54-AN62-AN69 -> 251056.26 | AO77: =AP77/AP9 -> 0.141888 | AP77: =AP9-AP17-AP23-AP30-AP38-AP46-AP54-AP62-AP69 -> 255748.15 | AQ77: =AR77/AR9 -> 0.14711925 | AR77: =AR9-AR17-AR23-AR30-AR38-AR46-AR54-AR62-AR69 -> 265177.29 | AS77: =AT77/AT9 -> 0.14854888 | AT77: =AT9-AT17-AT23-AT30-AT38-AT46-AT54-AT62-AT69 -> 267754.16 | AU77: =AV77/AV9 -> 0.14854888 | AV77: =AV9-AV17-AV23-AV30-AV38-AV46-AV54-AV62-AV69 -> 267754.16 | AW77: =AX77/AX9 -> 0.14854888 | AX77: =AX9-AX17-AX23-AX30-AX38-AX46-AX54-AX62-AX69 -> 267754.16 | AY77: =AZ77/AZ9 -> 0.14854888 | AZ77: =AZ9-AZ17-AZ23-AZ30-AZ38-AZ46-AZ54-AZ62-AZ69 -> 267754.16 | BA77: =BB77/BB9 -> 0.16830394 | BB77: =BB9-BB17-BB23-BB30-BB38-BB46-BB54-BB62-BB69 -> 321563.68 | BC77: =BD77/BD9 -> 0.14632163 | BD77: =AF77+AH77+AJ77+AL77+AN77+AP77+AR77+AT77+AV77+AX77+AZ77+BB77 -> 3180699.9
C78: La Ceja | D78: =E78/E10 -> 0.29421407 | E78: =E10-E18-E31-E39-E47-E55-E63-E70 -> 259202.59 | F78: =G78/G10 -> 0.28977098 | G78: =G10-G18-G31-G39-G47-G55-G63-G70 -> 255288.23 | H78: =I78/I10 -> 0.28977098 | I78: =I10-I18-I31-I39-I47-I55-I63-I70 -> 255288.23 | J78: =K78/K10 -> 0.28977098 | K78: =K10-K18-K31-K39-K47-K55-K63-K70 -> 255288.23 | L78: =M78/M10 -> 0.28977098 | M78: =M10-M18-M31-M39-M47-M55-M63-M70 -> 255288.23 | N78: =O78/O10 -> 0.29362256 | O78: =O10-O18-O31-O39-O47-O55-O63-O70 -> 258681.47 | P78: =Q78/Q10 -> 0.2960511 | Q78: =Q10-Q18-Q31-Q39-Q47-Q55-Q63-Q70 -> 260821.02 | R78: =S78/S10 -> 0.31221426 | S78: =S10-S18-S31-S39-S47-S55-S63-S70 -> 289088.86 | T78: =U78/U10 -> 0.31221426 | U78: =U10-U18-U31-U39-U47-U55-U63-U70 -> 289088.86 | V78: =W78/W10 -> 0.34699963 | W78: =W10-W18-W31-W39-W47-W55-W63-W70 -> 321297.71 | X78: =Y78/Y10 -> 0.34699963 | Y78: =Y10-Y18-Y31-Y39-Y47-Y55-Y63-Y70 -> 321297.71 | Z78: =AA78/AA10 -> 0.34735925 | AA78: =AA10-AA18-AA31-AA39-AA47-AA55-AA63-AA70 -> 321630.7 | AB78: =AC78/AC10 -> 0.30956457 | AC78: =E78+G78+I78+K78+M78+O78+Q78+S78+U78+W78+Y78+AA78 -> 3342261.9 | AE78: =AF78/AF10 -> 0.32017205 | AF78: =AF10-AF18-AF31-AF39-AF47-AF55-AF63-AF70 -> 296457.23 | AG78: =AH78/AH10 -> 0.3135629 | AH78: =AH10-AH18-AH31-AH39-AH47-AH55-AH63-AH70 -> 290337.61 | AI78: =AJ78/AJ10 -> 0.3135629 | AJ78: =AJ10-AJ18-AJ31-AJ39-AJ47-AJ55-AJ63-AJ70 -> 290337.61 | AK78: =AL78/AL10 -> 0.3135629 | AL78: =AL10-AL18-AL31-AL39-AL47-AL55-AL63-AL70 -> 290337.61 | AM78: =AN78/AN10 -> 0.3135629 | AN78: =AN10-AN18-AN31-AN39-AN47-AN55-AN63-AN70 -> 290337.61 | AO78: =AP78/AP10 -> 0.31616594 | AP78: =AP10-AP18-AP31-AP39-AP47-AP55-AP63-AP70 -> 292747.84 | AQ78: =AR78/AR10 -> 0.32139719 | AR78: =AR10-AR18-AR31-AR39-AR47-AR55-AR63-AR70 -> 297591.62 | AS78: =AT78/AT10 -> 0.32918966 | AT78: =AT10-AT18-AT31-AT39-AT47-AT55-AT63-AT70 -> 323095.32 | AU78: =AV78/AV10 -> 0.32918966 | AV78: =AV10-AV18-AV31-AV39-AV47-AV55-AV63-AV70 -> 323095.32 | AW78: =AX78/AX10 -> 0.32918966 | AX78: =AX10-AX18-AX31-AX39-AX47-AX55-AX63-AX70 -> 323095.32 | AY78: =AZ78/AZ10 -> 0.32918966 | AZ78: =AZ10-AZ18-AZ31-AZ39-AZ47-AZ55-AZ63-AZ70 -> 323095.32 | BA78: =BB78/BB10 -> 0.33271709 | BB78: =BB10-BB18-BB31-BB39-BB47-BB55-BB63-BB70 -> 326557.45 | BC78: =BD78/BD10 -> 0.32198626 | BD78: =AF78+AH78+AJ78+AL78+AN78+AP78+AR78+AT78+AV78+AX78+AZ78+BB78 -> 3667085.9
B79: PRELIMINAR | D79: =E79/E11 -> 0.17189613 | E79: =SUM(E73:E78) -> 1632110.7 | F79: =G79/G11 -> 0.16745304 | G79: =SUM(G73:G78) -> 1589924.7 | H79: =I79/I11 -> 0.16745304 | I79: =SUM(I73:I78) -> 1589924.7 | J79: =K79/K11 -> 0.16745304 | K79: =SUM(K73:K78) -> 1589924.7 | L79: =M79/M11 -> 0.16745304 | M79: =SUM(M73:M78) -> 1589924.7 | N79: =O79/O11 -> 0.19183184 | O79: =SUM(O73:O78) -> 1908774.7 | P79: =Q79/Q11 -> 0.20720346 | Q79: =SUM(Q73:Q78) -> 2126037 | R79: =S79/S11 -> 0.209352 | S79: =SUM(S73:S78) -> 2157488.7 | T79: =U79/U11 -> 0.209352 | U79: =SUM(U73:U78) -> 2157488.7 | V79: =W79/W11 -> 0.24413737 | W79: =SUM(W73:W78) -> 2515971.3 | X79: =Y79/Y11 -> 0.24413737 | Y79: =SUM(Y73:Y78) -> 2515971.3 | Z79: =AA79/AA11 -> 0.2479738 | AA79: =SUM(AA73:AA78) -> 2577196.8 | AB79: =AC79/AC11 -> 0.20076081 | AC79: =E79+G79+I79+K79+M79+O79+Q79+S79+U79+W79+Y79+AA79 -> 23950738 | AE79: =AF79/AF11 -> 0.18556072 | AF79: =SUM(AF73:AF78) -> 1854603.2 | AG79: =AH79/AH11 -> 0.17895156 | AH79: =SUM(AH73:AH78) -> 1788547.4 | AI79: =AJ79/AJ11 -> 0.17895156 | AJ79: =SUM(AJ73:AJ78) -> 1788547.4 | AK79: =AL79/AL11 -> 0.17895156 | AL79: =SUM(AL73:AL78) -> 1788547.4 | AM79: =AN79/AN11 -> 0.17895156 | AN79: =SUM(AN73:AN78) -> 1788547.4 | AO79: =AP79/AP11 -> 0.18390111 | AP79: =SUM(AP73:AP78) -> 1855643.3 | AQ79: =AR79/AR11 -> 0.19384806 | AR79: =SUM(AR73:AR78) -> 1994452.2 | AS79: =AT79/AT11 -> 0.19656644 | AT79: =SUM(AT73:AT78) -> 2033341.3 | AU79: =AV79/AV11 -> 0.19656644 | AV79: =SUM(AV73:AV78) -> 2033341.3 | AW79: =AX79/AX11 -> 0.19656644 | AX79: =SUM(AX73:AX78) -> 2033341.3 | AY79: =AZ79/AZ11 -> 0.19656644 | AZ79: =SUM(AZ73:AZ78) -> 2033341.3 | BA79: =BB79/BB11 -> 0.20327368 | BB79: =SUM(BB73:BB78) -> 2131115.8 | BC79: =BD79/BD11 -> 0.18920504 | BD79: =AF79+AH79+AJ79+AL79+AN79+AP79+AR79+AT79+AV79+AX79+AZ79+BB79 -> 23123369
C81: 0.051 | AD81: 0.06
B82: Seguro de Pasajeros taxi | C82: 1503502 | E82: =($C$82*(1+$C$81))/12 -> 131681.72 | G82: =($C$82*(1+$C$81))/12 -> 131681.72 | I82: =($C$82*(1+$C$81))/12 -> 131681.72 | K82: =($C$82*(1+$C$81))/12 -> 131681.72 | M82: =($C$82*(1+$C$81))/12 -> 131681.72 | O82: =($C$82*(1+$C$81))/12 -> 131681.72 | Q82: =($C$82*(1+$C$81))/12 -> 131681.72 | S82: =($C$82*(1+$C$81))/12 -> 131681.72 | U82: =($C$82*(1+$C$81))/12 -> 131681.72 | W82: =($C$82*(1+$C$81))/12 -> 131681.72 | Y82: =($C$82*(1+$C$81))/12 -> 131681.72 | AA82: =($C$82*(1+$C$81))/12 -> 131681.72 | AC82: =E82+G82+I82+K82+M82+O82+Q82+S82+U82+W82+Y82+AA82 -> 1580180.6 | AD82: 1583187.6 | AF82: =($AD$82*(1+$AD$81))/12 -> 139848.24 | AH82: =($AD$82*(1+$AD$81))/12 -> 139848.24 | AJ82: =($AD$82*(1+$AD$81))/12 -> 139848.24 | AL82: =($AD$82*(1+$AD$81))/12 -> 139848.24 | AN82: =($AD$82*(1+$AD$81))/12 -> 139848.24 | AP82: =($AD$82*(1+$AD$81))/12 -> 139848.24 | AR82: =($AD$82*(1+$AD$81))/12 -> 139848.24 | AT82: =($AD$82*(1+$AD$81))/12 -> 139848.24 | AV82: =($AD$82*(1+$AD$81))/12 -> 139848.24 | AX82: =($AD$82*(1+$AD$81))/12 -> 139848.24 | AZ82: =($AD$82*(1+$AD$81))/12 -> 139848.24 | BB82: =($AD$82*(1+$AD$81))/12 -> 139848.24 | BD82: =AF82+AH82+AJ82+AL82+AN82+AP82+AR82+AT82+AV82+AX82+AZ82+BB82 -> 1678178.9
B83: Seguro taxi | C83: 2200000 | E83: =($C$83*(1+$C$81))/12 -> 192683.33 | G83: =($C$83*(1+$C$81))/12 -> 192683.33 | I83: =($C$83*(1+$C$81))/12 -> 192683.33 | K83: =($C$83*(1+$C$81))/12 -> 192683.33 | M83: =($C$83*(1+$C$81))/12 -> 192683.33 | O83: =($C$83*(1+$C$81))/12 -> 192683.33 | Q83: =($C$83*(1+$C$81))/12 -> 192683.33 | S83: =($C$83*(1+$C$81))/12 -> 192683.33 | U83: =($C$83*(1+$C$81))/12 -> 192683.33 | W83: =($C$83*(1+$C$81))/12 -> 192683.33 | Y83: =($C$83*(1+$C$81))/12 -> 192683.33 | AA83: =($C$83*(1+$C$81))/12 -> 192683.33 | AC83: =E83+G83+I83+K83+M83+O83+Q83+S83+U83+W83+Y83+AA83 -> 2312200 | AD83: 2316600 | AF83: =($AD$83*(1+$AD$81))/12 -> 204633 | AH83: =($AD$83*(1+$AD$81))/12 -> 204633 | AJ83: =($AD$83*(1+$AD$81))/12 -> 204633 | AL83: =($AD$83*(1+$AD$81))/12 -> 204633 | AN83: =($AD$83*(1+$AD$81))/12 -> 204633 | AP83: =($AD$83*(1+$AD$81))/12 -> 204633 | AR83: =($AD$83*(1+$AD$81))/12 -> 204633 | AT83: =($AD$83*(1+$AD$81))/12 -> 204633 | AV83: =($AD$83*(1+$AD$81))/12 -> 204633 | AX83: =($AD$83*(1+$AD$81))/12 -> 204633 | AZ83: =($AD$83*(1+$AD$81))/12 -> 204633 | BB83: =($AD$83*(1+$AD$81))/12 -> 204633 | BD83: =AF83+AH83+AJ83+AL83+AN83+AP83+AR83+AT83+AV83+AX83+AZ83+BB83 -> 2455596
B84: CDA Taxi | C84: 324523 | E84: =($C$84*(1+$C$81))/12 -> 28422.806 | G84: =($C$84*(1+$C$81))/12 -> 28422.806 | I84: =($C$84*(1+$C$81))/12 -> 28422.806 | K84: =($C$84*(1+$C$81))/12 -> 28422.806 | M84: =($C$84*(1+$C$81))/12 -> 28422.806 | O84: =($C$84*(1+$C$81))/12 -> 28422.806 | Q84: =($C$84*(1+$C$81))/12 -> 28422.806 | S84: =($C$84*(1+$C$81))/12 -> 28422.806 | U84: =($C$84*(1+$C$81))/12 -> 28422.806 | W84: =($C$84*(1+$C$81))/12 -> 28422.806 | Y84: =($C$84*(1+$C$81))/12 -> 28422.806 | AA84: =($C$84*(1+$C$81))/12 -> 28422.806 | AC84: =E84+G84+I84+K84+M84+O84+Q84+S84+U84+W84+Y84+AA84 -> 341073.67 | AD84: 341722.72 | AF84: =($AD$84*(1+$AD$81))/12 -> 30185.507 | AH84: =($AD$84*(1+$AD$81))/12 -> 30185.507 | AJ84: =($AD$84*(1+$AD$81))/12 -> 30185.507 | AL84: =($AD$84*(1+$AD$81))/12 -> 30185.507 | AN84: =($AD$84*(1+$AD$81))/12 -> 30185.507 | AP84: =($AD$84*(1+$AD$81))/12 -> 30185.507 | AR84: =($AD$84*(1+$AD$81))/12 -> 30185.507 | AT84: =($AD$84*(1+$AD$81))/12 -> 30185.507 | AV84: =($AD$84*(1+$AD$81))/12 -> 30185.507 | AX84: =($AD$84*(1+$AD$81))/12 -> 30185.507 | AZ84: =($AD$84*(1+$AD$81))/12 -> 30185.507 | BB84: =($AD$84*(1+$AD$81))/12 -> 30185.507 | BD84: =AF84+AH84+AJ84+AL84+AN84+AP84+AR84+AT84+AV84+AX84+AZ84+BB84 -> 362226.08
B85: SOAT Taxi | C85: 268200 | E85: =($C$85*(1+$C$81))/12 -> 23489.85 | G85: =($C$85*(1+$C$81))/12 -> 23489.85 | I85: =($C$85*(1+$C$81))/12 -> 23489.85 | K85: =($C$85*(1+$C$81))/12 -> 23489.85 | M85: =($C$85*(1+$C$81))/12 -> 23489.85 | O85: =($C$85*(1+$C$81))/12 -> 23489.85 | Q85: =($C$85*(1+$C$81))/12 -> 23489.85 | S85: =($C$85*(1+$C$81))/12 -> 23489.85 | U85: =($C$85*(1+$C$81))/12 -> 23489.85 | W85: =($C$85*(1+$C$81))/12 -> 23489.85 | Y85: =($C$85*(1+$C$81))/12 -> 23489.85 | AA85: =($C$85*(1+$C$81))/12 -> 23489.85 | AC85: =E85+G85+I85+K85+M85+O85+Q85+S85+U85+W85+Y85+AA85 -> 281878.2 | AD85: 282414.6 | AF85: =($AD$85*(1+$AD$81))/12 -> 24946.623 | AH85: =($AD$85*(1+$AD$81))/12 -> 24946.623 | AJ85: =($AD$85*(1+$AD$81))/12 -> 24946.623 | AL85: =($AD$85*(1+$AD$81))/12 -> 24946.623 | AN85: =($AD$85*(1+$AD$81))/12 -> 24946.623 | AP85: =($AD$85*(1+$AD$81))/12 -> 24946.623 | AR85: =($AD$85*(1+$AD$81))/12 -> 24946.623 | AT85: =($AD$85*(1+$AD$81))/12 -> 24946.623 | AV85: =($AD$85*(1+$AD$81))/12 -> 24946.623 | AX85: =($AD$85*(1+$AD$81))/12 -> 24946.623 | AZ85: =($AD$85*(1+$AD$81))/12 -> 24946.623 | BB85: =($AD$85*(1+$AD$81))/12 -> 24946.623 | BD85: =AF85+AH85+AJ85+AL85+AN85+AP85+AR85+AT85+AV85+AX85+AZ85+BB85 -> 299359.48
B86: Impuestos Taxi | C86: 60000 | E86: =($C$86*(1+$C$81))/12 -> 5255 | G86: =($C$86*(1+$C$81))/12 -> 5255 | I86: =($C$86*(1+$C$81))/12 -> 5255 | K86: =($C$86*(1+$C$81))/12 -> 5255 | M86: =($C$86*(1+$C$81))/12 -> 5255 | O86: =($C$86*(1+$C$81))/12 -> 5255 | Q86: =($C$86*(1+$C$81))/12 -> 5255 | S86: =($C$86*(1+$C$81))/12 -> 5255 | U86: =($C$86*(1+$C$81))/12 -> 5255 | W86: =($C$86*(1+$C$81))/12 -> 5255 | Y86: =($C$86*(1+$C$81))/12 -> 5255 | AA86: =($C$86*(1+$C$81))/12 -> 5255 | AC86: =E86+G86+I86+K86+M86+O86+Q86+S86+U86+W86+Y86+AA86 -> 63060 | AD86: 63180 | AF86: =($AD$86*(1+$AD$81))/12 -> 5580.9 | AH86: =($AD$86*(1+$AD$81))/12 -> 5580.9 | AJ86: =($AD$86*(1+$AD$81))/12 -> 5580.9 | AL86: =($AD$86*(1+$AD$81))/12 -> 5580.9 | AN86: =($AD$86*(1+$AD$81))/12 -> 5580.9 | AP86: =($AD$86*(1+$AD$81))/12 -> 5580.9 | AR86: =($AD$86*(1+$AD$81))/12 -> 5580.9 | AT86: =($AD$86*(1+$AD$81))/12 -> 5580.9 | AV86: =($AD$86*(1+$AD$81))/12 -> 5580.9 | AX86: =($AD$86*(1+$AD$81))/12 -> 5580.9 | AZ86: =($AD$86*(1+$AD$81))/12 -> 5580.9 | BB86: =($AD$86*(1+$AD$81))/12 -> 5580.9 | BD86: =AF86+AH86+AJ86+AL86+AN86+AP86+AR86+AT86+AV86+AX86+AZ86+BB86 -> 66970.8
B87: Seguro Mazda | C87: 3000000 | E87: =($C$87*(1))/12 -> 250000 | G87: =($C$87*(1))/12 -> 250000 | I87: =($C$87*(1))/12 -> 250000 | K87: =($C$87*(1))/12 -> 250000 | M87: =($C$87*(1))/12 -> 250000 | O87: =($C$87*(1))/12 -> 250000 | Q87: =($C$87*(1))/12 -> 250000 | S87: =($C$87*(1))/12 -> 250000 | U87: =($C$87*(1))/12 -> 250000 | W87: =($C$87*(1))/12 -> 250000 | Y87: =($C$87*(1))/12 -> 250000 | AA87: =($C$87*(1))/12 -> 250000 | AC87: =E87+G87+I87+K87+M87+O87+Q87+S87+U87+W87+Y87+AA87 -> 3000000 | AD87: 3000000 | AF87: =($AD$87*(1))/12 -> 250000 | AH87: =($AD$87*(1))/12 -> 250000 | AJ87: =($AD$87*(1))/12 -> 250000 | AL87: =($AD$87*(1))/12 -> 250000 | AN87: =($AD$87*(1))/12 -> 250000 | AP87: =($AD$87*(1))/12 -> 250000 | AR87: =($AD$87*(1))/12 -> 250000 | AT87: =($AD$87*(1))/12 -> 250000 | AV87: =($AD$87*(1))/12 -> 250000 | AX87: =($AD$87*(1))/12 -> 250000 | AZ87: =($AD$87*(1))/12 -> 250000 | BB87: =($AD$87*(1))/12 -> 250000 | BD87: =AF87+AH87+AJ87+AL87+AN87+AP87+AR87+AT87+AV87+AX87+AZ87+BB87 -> 3000000
B88: CDA Mazda | C88: 216000 | E88: =($C$88*(1+$C$81))/12 -> 18918 | G88: =($C$88*(1+$C$81))/12 -> 18918 | I88: =($C$88*(1+$C$81))/12 -> 18918 | K88: =($C$88*(1+$C$81))/12 -> 18918 | M88: =($C$88*(1+$C$81))/12 -> 18918 | O88: =($C$88*(1+$C$81))/12 -> 18918 | Q88: =($C$88*(1+$C$81))/12 -> 18918 | S88: =($C$88*(1+$C$81))/12 -> 18918 | U88: =($C$88*(1+$C$81))/12 -> 18918 | W88: =($C$88*(1+$C$81))/12 -> 18918 | Y88: =($C$88*(1+$C$81))/12 -> 18918 | AA88: =($C$88*(1+$C$81))/12 -> 18918 | AC88: =E88+G88+I88+K88+M88+O88+Q88+S88+U88+W88+Y88+AA88 -> 227016 | AD88: 227448 | AF88: =($AD$88*(1+$AD$81))/12 -> 20091.24 | AH88: =($AD$88*(1+$AD$81))/12 -> 20091.24 | AJ88: =($AD$88*(1+$AD$81))/12 -> 20091.24 | AL88: =($AD$88*(1+$AD$81))/12 -> 20091.24 | AN88: =($AD$88*(1+$AD$81))/12 -> 20091.24 | AP88: =($AD$88*(1+$AD$81))/12 -> 20091.24 | AR88: =($AD$88*(1+$AD$81))/12 -> 20091.24 | AT88: =($AD$88*(1+$AD$81))/12 -> 20091.24 | AV88: =($AD$88*(1+$AD$81))/12 -> 20091.24 | AX88: =($AD$88*(1+$AD$81))/12 -> 20091.24 | AZ88: =($AD$88*(1+$AD$81))/12 -> 20091.24 | BB88: =($AD$88*(1+$AD$81))/12 -> 20091.24 | BD88: =AF88+AH88+AJ88+AL88+AN88+AP88+AR88+AT88+AV88+AX88+AZ88+BB88 -> 241094.88
B89: Semaforización Mazda | C89: 40800 | E89: =($C$89*(1+$C$81))/12 -> 3573.4 | G89: =($C$89*(1+$C$81))/12 -> 3573.4 | I89: =($C$89*(1+$C$81))/12 -> 3573.4 | K89: =($C$89*(1+$C$81))/12 -> 3573.4 | M89: =($C$89*(1+$C$81))/12 -> 3573.4 | O89: =($C$89*(1+$C$81))/12 -> 3573.4 | Q89: =($C$89*(1+$C$81))/12 -> 3573.4 | S89: =($C$89*(1+$C$81))/12 -> 3573.4 | U89: =($C$89*(1+$C$81))/12 -> 3573.4 | W89: =($C$89*(1+$C$81))/12 -> 3573.4 | Y89: =($C$89*(1+$C$81))/12 -> 3573.4 | AA89: =($C$89*(1+$C$81))/12 -> 3573.4 | AC89: =E89+G89+I89+K89+M89+O89+Q89+S89+U89+W89+Y89+AA89 -> 42880.8 | AD89: 42962.4 | AF89: =($AD$89*(1+$AD$81))/12 -> 3795.012 | AH89: =($AD$89*(1+$AD$81))/12 -> 3795.012 | AJ89: =($AD$89*(1+$AD$81))/12 -> 3795.012 | AL89: =($AD$89*(1+$AD$81))/12 -> 3795.012 | AN89: =($AD$89*(1+$AD$81))/12 -> 3795.012 | AP89: =($AD$89*(1+$AD$81))/12 -> 3795.012 | AR89: =($AD$89*(1+$AD$81))/12 -> 3795.012 | AT89: =($AD$89*(1+$AD$81))/12 -> 3795.012 | AV89: =($AD$89*(1+$AD$81))/12 -> 3795.012 | AX89: =($AD$89*(1+$AD$81))/12 -> 3795.012 | AZ89: =($AD$89*(1+$AD$81))/12 -> 3795.012 | BB89: =($AD$89*(1+$AD$81))/12 -> 3795.012 | BD89: =AF89+AH89+AJ89+AL89+AN89+AP89+AR89+AT89+AV89+AX89+AZ89+BB89 -> 45540.144
B90: Impuestos Mazda | C90: 674700 | E90: =($C$90*(1+$C$81))/12 -> 59092.475 | G90: =($C$90*(1+$C$81))/12 -> 59092.475 | I90: =($C$90*(1+$C$81))/12 -> 59092.475 | K90: =($C$90*(1+$C$81))/12 -> 59092.475 | M90: =($C$90*(1+$C$81))/12 -> 59092.475 | O90: =($C$90*(1+$C$81))/12 -> 59092.475 | Q90: =($C$90*(1+$C$81))/12 -> 59092.475 | S90: =($C$90*(1+$C$81))/12 -> 59092.475 | U90: =($C$90*(1+$C$81))/12 -> 59092.475 | W90: =($C$90*(1+$C$81))/12 -> 59092.475 | Y90: =($C$90*(1+$C$81))/12 -> 59092.475 | AA90: =($C$90*(1+$C$81))/12 -> 59092.475 | AC90: =E90+G90+I90+K90+M90+O90+Q90+S90+U90+W90+Y90+AA90 -> 709109.7 | AD90: 710459.1 | AF90: =($AD$90*(1+$AD$81))/12 -> 62757.221 | AH90: =($AD$90*(1+$AD$81))/12 -> 62757.221 | AJ90: =($AD$90*(1+$AD$81))/12 -> 62757.221 | AL90: =($AD$90*(1+$AD$81))/12 -> 62757.221 | AN90: =($AD$90*(1+$AD$81))/12 -> 62757.221 | AP90: =($AD$90*(1+$AD$81))/12 -> 62757.221 | AR90: =($AD$90*(1+$AD$81))/12 -> 62757.221 | AT90: =($AD$90*(1+$AD$81))/12 -> 62757.221 | AV90: =($AD$90*(1+$AD$81))/12 -> 62757.221 | AX90: =($AD$90*(1+$AD$81))/12 -> 62757.221 | AZ90: =($AD$90*(1+$AD$81))/12 -> 62757.221 | BB90: =($AD$90*(1+$AD$81))/12 -> 62757.221 | BD90: =AF90+AH90+AJ90+AL90+AN90+AP90+AR90+AT90+AV90+AX90+AZ90+BB90 -> 753086.65
B91: Agogados | C91: 9000000 | E91: =($C$91*(1))/12 -> 750000 | G91: =($C$91*(1))/12 -> 750000 | I91: =($C$91*(1))/12 -> 750000 | K91: =($C$91*(1))/12 -> 750000 | M91: =($C$91*(1))/12 -> 750000 | O91: =($C$91*(1))/12 -> 750000 | Q91: =($C$91*(1))/12 -> 750000 | S91: =($C$91*(1))/12 -> 750000 | U91: =($C$91*(1))/12 -> 750000 | W91: =($C$91*(1))/12 -> 750000 | Y91: =($C$91*(1))/12 -> 750000 | AA91: =($C$91*(1))/12 -> 750000 | AC91: =E91+G91+I91+K91+M91+O91+Q91+S91+U91+W91+Y91+AA91 -> 9000000 | AF91: =($AD$91*(1))/12 -> 0 | AH91: =($AD$91*(1))/12 -> 0 | AJ91: =($AD$91*(1))/12 -> 0 | AL91: =($AD$91*(1))/12 -> 0 | AN91: =($AD$91*(1))/12 -> 0 | AP91: =($AD$91*(1))/12 -> 0 | AR91: =($AD$91*(1))/12 -> 0 | AT91: =($AD$91*(1))/12 -> 0 | AV91: =($AD$91*(1))/12 -> 0 | AX91: =($AD$91*(1))/12 -> 0 | AZ91: =($AD$91*(1))/12 -> 0 | BB91: =($AD$91*(1))/12 -> 0 | BD91: =AF91+AH91+AJ91+AL91+AN91+AP91+AR91+AT91+AV91+AX91+AZ91+BB91 -> 0
B92: Impuestos DIAN | C92: 1000000 | E92: =($C$92*(1))/12 -> 83333.333 | G92: =($C$92*(1))/12 -> 83333.333 | I92: =($C$92*(1))/12 -> 83333.333 | K92: =($C$92*(1))/12 -> 83333.333 | M92: =($C$92*(1))/12 -> 83333.333 | O92: =($C$92*(1))/12 -> 83333.333 | Q92: =($C$92*(1))/12 -> 83333.333 | S92: =($C$92*(1))/12 -> 83333.333 | U92: =($C$92*(1))/12 -> 83333.333 | W92: =($C$92*(1))/12 -> 83333.333 | Y92: =($C$92*(1))/12 -> 83333.333 | AA92: =($C$92*(1))/12 -> 83333.333 | AC92: =E92+G92+I92+K92+M92+O92+Q92+S92+U92+W92+Y92+AA92 -> 1000000 | AD92: 1000000 | AF92: =($AD$92*(1))/12 -> 83333.333 | AH92: =($AD$92*(1))/12 -> 83333.333 | AJ92: =($AD$92*(1))/12 -> 83333.333 | AL92: =($AD$92*(1))/12 -> 83333.333 | AN92: =($AD$92*(1))/12 -> 83333.333 | AP92: =($AD$92*(1))/12 -> 83333.333 | AR92: =($AD$92*(1))/12 -> 83333.333 | AT92: =($AD$92*(1))/12 -> 83333.333 | AV92: =($AD$92*(1))/12 -> 83333.333 | AX92: =($AD$92*(1))/12 -> 83333.333 | AZ92: =($AD$92*(1))/12 -> 83333.333 | BB92: =($AD$92*(1))/12 -> 83333.333 | BD92: =AF92+AH92+AJ92+AL92+AN92+AP92+AR92+AT92+AV92+AX92+AZ92+BB92 -> 1000000
B93: Contador | C93: 1000000 | E93: =($C$93*(1))/12 -> 83333.333 | G93: =($C$93*(1))/12 -> 83333.333 | I93: =($C$93*(1))/12 -> 83333.333 | K93: =($C$93*(1))/12 -> 83333.333 | M93: =($C$93*(1))/12 -> 83333.333 | O93: =($C$93*(1))/12 -> 83333.333 | Q93: =($C$93*(1))/12 -> 83333.333 | S93: =($C$93*(1))/12 -> 83333.333 | U93: =($C$93*(1))/12 -> 83333.333 | W93: =($C$93*(1))/12 -> 83333.333 | Y93: =($C$93*(1))/12 -> 83333.333 | AA93: =($C$93*(1))/12 -> 83333.333 | AC93: =E93+G93+I93+K93+M93+O93+Q93+S93+U93+W93+Y93+AA93 -> 1000000 | AD93: 1000000 | AF93: =($AD$93*(1))/12 -> 83333.333 | AH93: =($AD$93*(1))/12 -> 83333.333 | AJ93: =($AD$93*(1))/12 -> 83333.333 | AL93: =($AD$93*(1))/12 -> 83333.333 | AN93: =($AD$93*(1))/12 -> 83333.333 | AP93: =($AD$93*(1))/12 -> 83333.333 | AR93: =($AD$93*(1))/12 -> 83333.333 | AT93: =($AD$93*(1))/12 -> 83333.333 | AV93: =($AD$93*(1))/12 -> 83333.333 | AX93: =($AD$93*(1))/12 -> 83333.333 | AZ93: =($AD$93*(1))/12 -> 83333.333 | BB93: =($AD$93*(1))/12 -> 83333.333 | BD93: =AF93+AH93+AJ93+AL93+AN93+AP93+AR93+AT93+AV93+AX93+AZ93+BB93 -> 1000000
